Workbook

Sheet Pivot
A1: Facility Name | B1: (All)
A2: County | B2: (All)
A3: Health Facility Planning Area (HFPA) | B3: (All)
A4: Type of Care | B4: (All)
A5: License Category | B5: (All)
A6: Type of Control | B6: (All)
A7: Bed Size | B7: (All)
A8: Residential Care | B8: (All)
A10: Data | B10: Total
A11: Sum of FAC_NO | B11: 221944919376
A12: Count of FAC_NO | B12: 1076
A13: Sum of BED_AVG | B13: 108060
A14: Sum of BED_END | B14: 108060
A15: Sum of DAY_TOTL | B15: 34576964
A16: Sum of Licensed Bed Days | B16: 39061329
A17: Sum of ADMITS | B17: 348227
A18: Sum of DISCHS | B18: 346685
A19: Sum of DAYS_MCARE_FFS2 | B19: 5656431
A20: Sum of DAYS_MCARE_MGD2 | B20: 2216758
A21: Sum of DAYS_MCAL_FFS2 | B21: 3266548
A22: Sum of DAYS_MCAL_MGD2 | B22: 19260667
... A39: Sum of GR_AN_MCAL_FFS_IP2 | B39: 90681588
A40: Sum of GR_AN_MCAL_FFS_OP
A41: Sum of GR_AN_MCAL_MGD_IP | B41: 416072176
A42: Sum of GR_AN_MCAL_MGD_OP
A43: Sum of GR_AN_CC_FFS_IP | B43: 165372780
A44: Sum of GR_AN_CC_FFS_OP | B44: 80693
A45: Sum of GR_AN_CC_MGD_IP | B45: 328764116
A46: Sum of GR_AN_CC_MGD_OP2 | B46: 115064
A47: Sum of GR_AN_SELF_IP | B47: 26125257
A48: Sum of GR_AN_OTH_IP | B48: 69426448
A49: Sum of GR_AN_SELF_OP | B49: 64598
A50: Sum of GR_AN_OTH_OP | B50: 36839
A51: Sum of DAY_SN | B51: 32708093
A52: Sum of DAY_IC | B52: 11531
A53: Sum of DAY_MD | B53: 769034
A54: Sum of DAY_DD | B54: 138892
... A56: Sum of DAY_SUBPED | B56: 44633
A57: Sum of DAY_TIC
A58: Sum of DAY_HOSPIC
A59: Sum of DAY_OTH_RT
A60: Sum of GR_SN | B60: 14640053186
A61: Sum of GR_IC | B61: 1639841
A62: Sum of GR_MD | B62: 257002219
A63: Sum of GR_DD | B63: 46442806
A64: Sum of GR_SUBACU | B64: 749382412
A65: Sum of GR_SUBPED | B65: 70974239
A66: Sum of GR_TIC
A67: Sum of GR_HOSPIC
A68: Sum of GR_OTH_RT | B68: 1000
A69: Sum of EXP_SN | B69: 6111106482
A70: Sum of EXP_IC | B70: 821880
A71: Sum of EXP_MD | B71: 113350522
A72: Sum of EXP_DD | B72: 21887937
A73: Sum of EXP_SUBACU | B73: 354956468
A74: Sum of EXP_SUBPED | B74: 33736842
A75: Sum of EXP_TIC
A76: Sum of EXP_HOSPIC
A77: Sum of EXP_OTH_RT | B77: 244879
A78: Sum of EXP_PSUPPL | B78: 42469566
A79: Sum of EXP_SPSURF | B79: 8859015
A80: Sum of EXP_PT | B80: 495788064
A81: Sum of EXP_RT | B81: 46938397
A82: Sum of EXP_OT | B82: 402398152
A83: Sum of EXP_SP | B83: 103201501
A84: Sum of EXP_PHARM | B84: 285716416
A85: Sum of EXP_LAB | B85: 51398140
A86: Sum of EXP_HMHLTH | B86: 258037
A87: Sum of EXP_OTH_AN | B87: 71732617
A88: Sum of EXP_POM | B88: 561815648
... A146: Sum of DFR_IP_SELF_PAY_CHARITY | B146: 192194
A147: Sum of DFR_OP_SELF_PAY_CHARITY
A148: Sum of DFR_IP_OTHER_PAYERS_CHARITY
A149: Sum of DFR_OP_OTHER_PAYERS_CHARITY
A150: Sum of DFR_IP_SELF_PAY_ADM_ADJ | B150: 3254567
A151: Sum of DFR_OP_SELF_PAY_ADM_ADJ
A152: Sum of DFR_IP_OTHER_PAYERS_ADM_ADJ
A153: Sum of DFR_OP_OTHER_PAYERS_ADM_ADJ
A154: Sum of DFR_IP_MCARE_FFS_CONT_ADJ | B154: 701599582
A155: Sum of DFR_OP_MCARE_FFS_CONT_ADJ | B155: 9286716
A156: Sum of DFR_IP_MCARE_MGD_CONT_ADJ | B156: 833212646
A157: Sum of DFR_OP_MCARE_MGD_CONT_ADJ | B157: 297466
A158: Sum of DFR_IP_MCAL_FFS_CONT_ADJ | B158: 174278492
A159: Sum of DFR_OP_MCAL_FFS_CONT_ADJ | B159: 12056886
A160: Sum of DFR_IP_MCAL_MGD_CONT_ADJ | B160: 1893851407
A161: Sum of DFR_OP_MCAL_MGD_CONT_ADJ
A162: Sum of DFR_IP_CC_FFS_CONT_ADJ | B162: 119821231
A163: Sum of DFR_OP_CC_FFS_CONT_ADJ
A164: Sum of DFR_IP_CC_MGD_CONT_ADJ | B164: 212057402
A165: Sum of DFR_OP_CC_MGD_CONT_ADJ
A166: Sum of DFR_IP_OTHER_PAYERS_CONT_ADJ | B166: 61604343
A167: Sum of DFR_OP_OTHER_PAYERS_CONT_ADJ | B167: 999054
A168: Sum of DFR_IP_SELF_PAY_OTH_DFR | B168: 1793269
A169: Sum of DFR_OP_SELF_PAY_OTH_DFR
A170: Sum of DFR_IP_OTHER_PAYERS_OTH_DFR | B170: 3612561
A171: Sum of DFR_OP_OTHER_PAYERS_OTH_DFR
A172: Sum of Investor | B172: 980
A173: Sum of Not-for-profit | B173: 92
A174: Sum of Governmental | B174: 4
A175: Sum of 1-59 Beds | B175: 265
...

Sheet Profile
A1: Profile Characteristics | E1: =IF($B$2=1,"Individual Facility Characteristics","Type of Control") -> Type of Control
A2: No. of Facilities | B2: =Pivot!B12 -> 1076 | E2: =IF($B$2=1,"Facility Name","Investor Owned:") -> Investor Owned: | F2: =IF($B$2=1,VLOOKUP($H$6,Data!$A$1:$IS$1061,2,FALSE),Pivot!B172) -> 980
A3: Facility Name | B3: =Pivot!B1 -> (All) | E3: =IF($B$2=1,"Address","Not-For-Profit:") -> Not-For-Profit: | F3: =IF($B$2=1,VLOOKUP($H$6,Data!$A$1:$IS$1061,14,FALSE),Pivot!B173) -> 92
A4: County | B4: =Pivot!B2 -> (All) | E4: =IF($B$2=1,"City","Governmental:") -> Governmental: | F4: =IF($B$2=1,VLOOKUP($H$6,Data!$A$1:$IS$1061,15,FALSE),Pivot!B174) -> 4
A5: HFPA | B5: =Pivot!B3 -> (All) | E5: =IF($B$2=1,"State","") | F5: =IF($B$2=1,"CALIFORNIA","") | G5: =IF($B$2=1,"","Facility Size") -> Facility Size
A6: Type of Care | B6: =Pivot!B4 -> (All) | E6: =IF($B$2=1,"Zip","") | F6: =IF($B$2=1,VLOOKUP($H$6,Data!$A$1:$IS$1061,16,FALSE),"") | G6: =IF($B$2=1,"OSHPD ID","1 - 59 Beds:") -> 1 - 59 Beds: | H6: =IF($B$2=1,Pivot!B11,Pivot!B175) -> 265
A7: License Category | B7: =Pivot!B5 -> (All) | E7: =IF($B$2=1,"Phone #","") | F7: =IF($B$2=1,VLOOKUP($H$6,Data!$A$1:$IS$1061,13,FALSE),"") | G7: =IF($B$2=1,"Medi-Cal Provider #","60 - 99 Beds:") -> 60 - 99 Beds: | H7: =IF($B$2=1,IF(VLOOKUP($H$6,Data!$A$1:$IS$2000,17,FALSE)=0,"",VLOOKUP($H$6,Data!$A$1:$IS$2000,17,FALSE)),Pivot!B176) -> 457
A8: Licensed Bed Size | B8: =Pivot!B6 -> (All) | E8: =IF($B$2=1,"","Type of Care*") -> Type of Care* | G8: =IF($B$2=1,"","100 + Beds:") -> 100 + Beds: | H8: =IF($B$2=1,"",GETPIVOTDATA("Sum of 100+ Beds",Pivot!$A$10)) -> 354
A9: Residential Care | B9: =Pivot!B7 -> (All) | E9: =IF($B$2=1,"County","Skilled Nursing:") -> Skilled Nursing: | F9: =IF($B$2=1,VLOOKUP($H$6,Data!$A$1:$IS$2000,8,FALSE),Pivot!B178) -> 1049 | G9: =IF($B$2=1,"Report Period Begin","") | H9: =IF($B$2=1,VLOOKUP($H$6,Data!$A$1:$IS$2000,3,FALSE),"")
E10: =IF($B$2=1,"Type of Care","Intermediate Care:") -> Intermediate Care: | F10: =IF($B$2=1,VLOOKUP($H$6,Data!$A$1:$IS$1061,37,FALSE),Pivot!B179) -> 1 | G10: =IF($B$2=1,"Report Period End","") | H10: =IF($B$2=1,VLOOKUP($H$6,Data!$A$1:$IS$2000,4,FALSE),"")
E11: =IF($B$2=1,"License Category","Mentally Disordered:") -> Mentally Disordered: | F11: =IF($B$2=1,VLOOKUP($H$6,Data!$A$1:$IS$1061,9,FALSE),Pivot!B180) -> 23 | G11: =IF($B$2=1,"Days in Period","") | H11: =IF($B$2=1,VLOOKUP($H$6,Data!$A$1:$IS$2000,5,FALSE),"")
A12: Licensed Beds* | B12: *Excluding beds in suspense | E12: =IF($B$2=1,"Type of Control","Develop. Disabled:") -> Develop. Disabled: | F12: =IF($B$2=1,VLOOKUP($H$6,Data!$A$1:$IS$1061,10,FALSE),Pivot!B181) -> 7 | G12: =IF($B$2=1,"","License Category") -> License Category
A13: Average | B13: =Pivot!B13 -> 108060 | E13: =IF($B$2=1,"Parent Organization","Sub-Acute:") -> Sub-Acute: | F13: =IF($B$2=1,IF(VLOOKUP($H$6,Data!$A$1:$IS$1061,20,FALSE)=0,"",VLOOKUP($H$6,Data!$A$1:$IS$1061,20,FALSE)),Pivot!B182) -> 82 | G13: =IF($B$2=1,"","SNF (incl. MD):") -> SNF (incl. MD): | H13: =IF($B$2=1,"",GETPIVOTDATA("Sum of SNF Lic",Pivot!$A$10)) -> 987
A14: End of Period | B14: =Pivot!B14 -> 108060 | E14: =IF($B$2=1,"Related to Others?","Sub-Acute Pediatric:") -> Sub-Acute Pediatric: | F14: =IF($B$2=1,VLOOKUP($H$6,Data!$A$1:$IS$1061,19,FALSE),Pivot!B183) -> 4 | G14: =IF($B$2=1,"","ICF (incl. DD):") -> ICF (incl. DD): | H14: =IF($B$2=1,"",GETPIVOTDATA("Sum of ICF Lic",Pivot!$A$10)) -> 6
A15: Total Patient Days | B15: =Pivot!B15 -> 34576964 | E15: =IF($B$2=1,"","Transitional Inpat.:") -> Transitional Inpat.: | F15: =IF($B$2=1,"",GETPIVOTDATA("Sum of TI Care",Pivot!$A$10)) -> 0 | G15: =IF($B$2=1,"","SNF / Residential:") -> SNF / Residential: | H15: =IF($B$2=1,"",GETPIVOTDATA("Sum of SNF/Res Lic",Pivot!$A$10)) -> 83
A16: Occupancy Rate | B16: =IF(Pivot!B16=0,"",Pivot!B15/Pivot!B16) -> 0.88519681 | E16: =IF($B$2=1,"","Hospice:") -> Hospice: | F16: =IF($B$2=1,"",GETPIVOTDATA("Sum of Hosp Care",Pivot!$A$10)) -> 0 | G16: =IF($B$2=1,"","ICF / Residential:") -> ICF / Residential: | H16: =IF($B$2=1,"",GETPIVOTDATA("Sum of ICF/Res Lic",Pivot!$A$10)) -> 0
A17: Admissions | B17: =Pivot!B17 -> 348227 | E17: =IF($B$2=1,"","Other Routine:") -> Other Routine: | F17: =IF($B$2=1,"",GETPIVOTDATA("Sum of Other Care",Pivot!$A$10)) -> 0 | G17: =IF($B$2=1,"","Other Licensure:") -> Other Licensure: | H17: =IF($B$2=1,"",GETPIVOTDATA("Sum of Other Lic",Pivot!$A$10)) -> 0
A18: Discharges | B18: =Pivot!B18 -> 346685 | E18: =IF($B$2=1,"","*Counts facilities with multiple levels twice") -> *Counts facilities with multiple levels twice
A20: Patient Days & Gross | E20: Gross Inpatient | F20: Gross Outpatient | H20: Total Net
A21: Revenue by Payer | C21: Gross Routine | D21: Per Patient | E21: Ancillary | F21: Ancillary | G21: Deductions | H21: Patient
B22: Patient Days | C22: Revenue | D22: Day | E22: Revenue | F22: Revenue | G22: from Revenue | H22: Revenue*
A23: Medicare Fee-for-Service | B23: =Pivot!B19 -> 5656431 | C23: =GETPIVOTDATA("Sum of GR_RT_MCARE_FFS2",Pivot!$A$10) -> 3432419642 | D23: =IF(B23=0,0,C23/B23) -> 606.8172 | E23: =GETPIVOTDATA("Sum of GR_AN_MCARE_FFS_IP",Pivot!$A$10) -> 2996612048 | F23: =GETPIVOTDATA("Sum of GR_AN_MCARE_FFS_OP2",Pivot!$A$10) -> 15496751 | G23: =H43 -> 710886298 | H23: =C23+E23+F23-G23 -> 5733642143
A24: % of Total | B24: =IF(B23=0,0,B23/B39) -> 0.16358958 | C24: =IF(C23=0,0,C23/C39) -> 0.2177172 | E24: =IF(E23=0,0,E23/E39) -> 0.68944012 | F24: =IF(F23=0,0,F23/F39) -> 0.92627715 | G24: =IF(G23=0,0,G23/G39) -> 0.17648977 | H24: =IF(H23=0,0,H23/H39) -> 0.35611023
A25: Medicare Managed Care | B25: =Pivot!B20 -> 2216758 | C25: =GETPIVOTDATA("Sum of GR_RT_MCARE_MGD2",Pivot!$A$10) -> 1463761135 | D25: =IF(B25=0,0,C25/B25) -> 660.31616 | E25: =GETPIVOTDATA("Sum of GR_AN_MCARE_MGD_IP2",Pivot!$A$10) -> 773650540 | F25: =GETPIVOTDATA("Sum of GR_AN_MCARE_MGD_OP2",Pivot!$A$10) -> 1196555 | G25: =H44 -> 833510112 | H25: =C25+E25+F25-G25 -> 1405098118
A26: % of Total | B26: =IF(B25=0,0,B25/B39) -> 0.064110834 | C26: =IF(C25=0,0,C25/C39) -> 0.092845868 | E26: =IF(E25=0,0,E25/E39) -> 0.17799625 | F26: =IF(F25=0,0,F25/F39) -> 0.071520898 | G26: =IF(G25=0,0,G25/G39) -> 0.20693325 | H26: =IF(H25=0,0,H25/H39) -> 0.087269105
A27: MediCal Fee-for-Service | B27: =Pivot!B21 -> 3266548 | C27: =GETPIVOTDATA("Sum of GR_RT_MCAL_FFS2",Pivot!$A$10) -> 1345700735 | D27: =IF(B27=0,0,C27/B27) -> 411.96417 | E27: =GETPIVOTDATA("Sum of GR_AN_MCAL_FFS_IP2",Pivot!$A$10) -> 90681588 | F27: =GETPIVOTDATA("Sum of GR_AN_MCAL_FFS_OP",Pivot!$A$10) -> 0 | G27: =H45 -> 186335378 | H27: =C27+E27+F27-G27 -> 1250046945
A28: % of Total | B28: =IF(B27=0,0,B27/B39) -> 0.094471799 | C28: =IF(C27=0,0,C27/C39) -> 0.085357337 | E28: =IF(E27=0,0,E27/E39) -> 0.020863403 | F28: =IF(F27=0,0,F27/F39) -> 0 | G28: =IF(G27=0,0,G27/G39) -> 0.046260968 | H28: =IF(H27=0,0,H27/H39) -> 0.077639047
A29: MediCal Managed Care | B29: =Pivot!B22 -> 19260667 | C29: =GETPIVOTDATA("Sum of GR_RT_MCAL_MGD2",Pivot!$A$10) -> 7747475616 | D29: =IF(B29=0,0,C29/B29) -> 402.24337 | E29: =GETPIVOTDATA("Sum of GR_AN_MCAL_MGD_IP",Pivot!$A$10) -> 416072176 | F29: =GETPIVOTDATA("Sum of GR_AN_MCAL_MGD_OP",Pivot!$A$10) -> 0 | G29: =H46 -> 1893851407 | H29: =C29+E29+F29-G29 -> 6269696385
A30: % of Total | B30: =IF(B29=0,0,B29/B39) -> 0.55703754 | C30: =IF(C29=0,0,C29/C39) -> 0.49141973 | E30: =IF(E29=0,0,E29/E39) -> 0.095727057 | F30: =IF(F29=0,0,F29/F39) -> 0 | G30: =IF(G29=0,0,G29/G39) -> 0.47018124 | H30: =IF(H29=0,0,H29/H39) -> 0.38940398
A31: Commercial Coverage Fee-for-Service | B31: =GETPIVOTDATA("Sum of DAYS_CC_FFS2",Pivot!$A$10) -> 370809 | C31: =GETPIVOTDATA("Sum of GR_RT_CC_FFS2",Pivot!$A$10) -> 189505695 | D31: =IF(B31=0,0,C31/B31) -> 511.06013 | E31: =GETPIVOTDATA("Sum of GR_AN_CC_FFS_IP",Pivot!$A$10) -> 165372780 | F31: =GETPIVOTDATA("Sum of GR_AN_CC_FFS_OP",Pivot!$A$10) -> 80693 | G31: =H47 -> 119821231 | H31: =C31+E31+F31-G31 -> 235137937
A32: % of Total | B32: =IF(B31=0,0,B31/B39) -> 0.010724163 | C32: =IF(C31=0,0,C31/C39) -> 0.012020281 | E32: =IF(E31=0,0,E31/E39) -> 0.038047845 | F32: =IF(F31=0,0,F31/F39) -> 0.0048232098 | G32: =IF(G31=0,0,G31/G39) -> 0.029747685 | H32: =IF(H31=0,0,H31/H39) -> 0.01460416
A33: Commercial Coverage Managed Care | B33: =GETPIVOTDATA("Sum of DAYS_CC_MGD2",Pivot!$A$10) -> 904327 | C33: =GETPIVOTDATA("Sum of GR_RT_CC_MGD2",Pivot!$A$10) -> 422184905 | D33: =IF(B33=0,0,C33/B33) -> 466.84983 | E33: =GETPIVOTDATA("Sum of GR_AN_CC_MGD_IP",Pivot!$A$10) -> 328764116 | F33: =GETPIVOTDATA("Sum of GR_AN_CC_MGD_OP2",Pivot!$A$10) -> 115064 | G33: =H48 -> 212057402 | H33: =C33+E33+F33-G33 -> 539006683
A34: % of Total | B34: =IF(B33=0,0,B33/B39) -> 0.026154031 | C34: =IF(C33=0,0,C33/C39) -> 0.026779044 | E34: =IF(E33=0,0,E33/E39) -> 0.075639812 | F34: =IF(F33=0,0,F33/F39) -> 0.0068776451 | G34: =IF(G33=0,0,G33/G39) -> 0.052646904 | H34: =IF(H33=0,0,H33/H39) -> 0.033477115
A35: Self Pay | B35: =GETPIVOTDATA("Sum of DAY_SELF",Pivot!$A$10) -> 774017 | C35: =GETPIVOTDATA("Sum of GR_RT_SELF",Pivot!$A$10) -> 328302460 | D35: =IF(B35=0,0,C35/B35) -> 424.15407 | E35: =GETPIVOTDATA("Sum of GR_AN_SELF_IP",Pivot!$A$10) -> 26125257 | F35: =GETPIVOTDATA("Sum of GR_AN_SELF_OP",Pivot!$A$10) -> 64598 | G35: =H50+H51+H52 -> 8852591 | H35: =C35+E35+F35-G35 -> 345639724
A36: % of Total | B36: =IF(B35=0,0,B35/B39) -> 0.022385337 | C36: =IF(C35=0,0,C35/C39) -> 0.020824113 | E36: =IF(E35=0,0,E35/E39) -> 0.0060107215 | F36: =IF(F35=0,0,F35/F39) -> 0.0038611739 | G36: =IF(G35=0,0,G35/G39) -> 0.0021978082 | H36: =IF(H35=0,0,H35/H39) -> 0.021467305
A37: Other Payers | B37: =GETPIVOTDATA("Sum of DAY_OTH",Pivot!$A$10) -> 2127407 | C37: =GETPIVOTDATA("Sum of GR_RT_OTH",Pivot!$A$10) -> 836145515 | D37: =IF(B37=0,0,C37/B37) -> 393.03505 | E37: =GETPIVOTDATA("Sum of GR_AN_OTH_IP",Pivot!$A$10) -> 69426448 | F37: =GETPIVOTDATA("Sum of GR_AN_OTH_OP",Pivot!$A$10) -> 36839 | G37: =H49 -> 62603397 | H37: =C37+E37+F37-G37 -> 843005405
A38: % of Total | B38: =IF(B37=0,0,B37/B39) -> 0.061526715 | C38: =IF(C37=0,0,C37/C39) -> 0.053036424 | E38: =IF(E37=0,0,E37/E39) -> 0.015973165 | F38: =IF(F37=0,0,F37/F39) -> 0.0022019534 | G38: =IF(G37=0,0,G37/G39) -> 0.015542372 | H38: =IF(H37=0,0,H37/H39) -> 0.052358142
A39: Total All Payers | B39: =B23+B25+B27+B29+B31+B33+B35+B37 -> 34576964 | C39: =SUM(C23+C25+C27+C29+C31+C33+C35+C37) -> 15765495703 | D39: =IF(B39=0,0,C39/B39) -> 455.95373 | E39: =E23+E25+E27+E29+E37 -> 4346442800 | F39: =F23+F25+F27+F29+F37 -> 16730145 | G39: =(G23+G25+G27+G29+G31+G33+G35+G37) -> 4027917816 | H39: =C39+E39+F39-G39 -> 16100750832
H40: * Gross Revenue
H41: minus Deductions
A42: Patient Days & Gross Revenue | C42: Gross Routine | D42: Per Patient | F42: Deductions from Revenue
A43: Revenue | B43: Patient Days | C43: Revenue | D43: Day | F43: Contractual Adjustments - Medicare FFS | H43: =(GETPIVOTDATA("Sum of DFR_IP_MCARE_FFS_CONT_ADJ",Pivot!$A$10)+GETPIVOTDATA("Sum of DFR_OP_MCARE_FFS_CONT_ADJ",Pivot!$A$10)) -> 710886298
A44: Skilled Nursing | B44: =GETPIVOTDATA("Sum of DAY_SN",Pivot!$A$10) -> 32708093 | C44: =GETPIVOTDATA("Sum of GR_SN",Pivot!$A$10) -> 14640053186 | D44: =IF(B44=0,0,C44/B44) -> 447.59727 | F44: Contractual Adjustments - Medicare Mgd Care | H44: =(GETPIVOTDATA("Sum of DFR_IP_MCARE_MGD_CONT_ADJ",Pivot!$A$10)+GETPIVOTDATA("Sum of DFR_OP_MCARE_MGD_CONT_ADJ",Pivot!$A$10)) -> 833510112
A45: Intermediate Care | B45: =GETPIVOTDATA("Sum of DAY_IC",Pivot!$A$10) -> 11531 | C45: =GETPIVOTDATA("Sum of GR_IC",Pivot!$A$10) -> 1639841 | D45: =IF(B45=0,0,C45/B45) -> 142.21152 | F45: Contractual Adjustments - MediCal FFS | H45: =(GETPIVOTDATA("Sum of DFR_IP_MCAL_FFS_CONT_ADJ",Pivot!$A$10)+GETPIVOTDATA("Sum of DFR_OP_MCAL_FFS_CONT_ADJ",Pivot!$A$10)) -> 186335378
A46: Mentally Disordered | B46: =GETPIVOTDATA("Sum of DAY_MD",Pivot!$A$10) -> 769034 | C46: =GETPIVOTDATA("Sum of GR_MD",Pivot!$A$10) -> 257002219 | D46: =IF(B46=0,0,C46/B46) -> 334.18837 | F46: Contractual Adjustments - MediCal Mgd Care | H46: =GETPIVOTDATA("Sum of DFR_IP_MCAL_MGD_CONT_ADJ",Pivot!$A$10)+GETPIVOTDATA("Sum of DFR_OP_MCAL_MGD_CONT_ADJ",Pivot!$A$10) -> 1893851407
A47: Developmentally Disabled | B47: =GETPIVOTDATA("Sum of DAY_DD",Pivot!$A$10) -> 138892 | C47: =GETPIVOTDATA("Sum of GR_DD",Pivot!$A$10) -> 46442806 | D47: =IF(B47=0,0,C47/B47) -> 334.38071 | F47: Contractual Adjustments - Commercial Coverage FFS | H47: =GETPIVOTDATA("Sum of DFR_IP_CC_FFS_CONT_ADJ",Pivot!$A$10)+GETPIVOTDATA("Sum of DFR_OP_CC_FFS_CONT_ADJ",Pivot!$A$10) -> 119821231
A48: Sub-Acute Care | B48: =GETPIVOTDATA("Sum of DAY_SUBACU",Pivot!$A$10) -> 904781 | C48: =GETPIVOTDATA("Sum of GR_SUBACU",Pivot!$A$10) -> 749382412 | D48: =IF(B48=0,0,C48/B48) -> 828.24729 | F48: Contractual Adjustments - Commercial Coverage Mgd | H48: =GETPIVOTDATA("Sum of DFR_IP_CC_MGD_CONT_ADJ",Pivot!$A$10)+GETPIVOTDATA("Sum of DFR_OP_CC_MGD_CONT_ADJ",Pivot!$A$10) -> 212057402
A49: Sub- Acute - Pediatric | B49: =GETPIVOTDATA("Sum of DAY_SUBPED",Pivot!$A$10) -> 44633 | C49: =GETPIVOTDATA("Sum of GR_SUBPED",Pivot!$A$10) -> 70974239 | D49: =IF(B49=0,0,C49/B49) -> 1590.1741 | F49: Contractual Adjustments - Other Payers | H49: =GETPIVOTDATA("Sum of DFR_IP_OTHER_PAYERS_CONT_ADJ",Pivot!$A$10)+GETPIVOTDATA("Sum of DFR_OP_OTHER_PAYERS_CONT_ADJ",Pivot!$A$10) -> 62603397
A50: Transitional Inpatient Care | B50: =GETPIVOTDATA("Sum of DAY_TIC",Pivot!$A$10) -> 0 | C50: =GETPIVOTDATA("Sum of GR_TIC",Pivot!$A$10) -> 0 | D50: =IF(B50=0,0,C50/B50) -> 0 | F50: Charity Adjustments | H50: =GETPIVOTDATA("Sum of DFR_IP_SELF_PAY_CHARITY",Pivot!$A$10)+GETPIVOTDATA("Sum of DFR_OP_SELF_PAY_CHARITY",Pivot!$A$10)+GETPIVOTDATA("Sum of DFR_IP_OTHER_PAYERS_CHARITY",Pivot!$A$10)+GETPIVOTDATA("Sum of DFR_OP_OTHER_PAYERS_CHARITY",Pivot!$A$10) -> 192194
A51: Hospice Inpatient Care | B51: =GETPIVOTDATA("Sum of DAY_HOSPIC",Pivot!$A$10) -> 0 | C51: =GETPIVOTDATA("Sum of GR_HOSPIC",Pivot!$A$10) -> 0 | D51: =IF(B51=0,0,C51/B51) -> 0 | F51: Administrative Adjustments | H51: =GETPIVOTDATA("Sum of DFR_IP_SELF_PAY_ADM_ADJ",Pivot!$A$10)+GETPIVOTDATA("Sum of DFR_OP_SELF_PAY_ADM_ADJ",Pivot!$A$10)+GETPIVOTDATA("Sum of DFR_IP_OTHER_PAYERS_ADM_ADJ",Pivot!$A$10)+GETPIVOTDATA("Sum of DFR_OP_OTHER_PAYERS_ADM_ADJ",Pivot!$A$10) -> 3254567
A52: Other Routine Services | B52: =GETPIVOTDATA("Sum of DAY_OTH_RT",Pivot!$A$10) -> 0 | C52: =GETPIVOTDATA("Sum of GR_OTH_RT",Pivot!$A$10) -> 1000 | D52: =IF(B52=0,0,C52/B52) -> 0 | F52: Other Deductions from Revenue | H52: =GETPIVOTDATA("Sum of DFR_IP_SELF_PAY_OTH_DFR",Pivot!$A$10)+GETPIVOTDATA("Sum of DFR_OP_SELF_PAY_OTH_DFR",Pivot!$A$10)+GETPIVOTDATA("Sum of DFR_IP_OTHER_PAYERS_OTH_DFR",Pivot!$A$10)+GETPIVOTDATA("Sum of DFR_OP_OTHER_PAYERS_OTH_DFR",Pivot!$A$10) -> 5405830
A53: Total Routine Services | B53: =SUM(B44:B52) -> 34576964 | C53: =SUM(C44:C52) -> 15765495703 | D53: =IF(B53=0,0,C53/B53) -> 455.95373 | F53: Total Deductions from Revenue | H53: =SUM(H43:H52) -> 4027917816
A55: Health Care Expenses by Cost Center | D55: Per Patient | H55: Per Patient
C56: % of Total | D56: Day | F56: Income Statement | H56: Day
A57: Routine Services: | F57: Gross RoutineRevenue | G57: =C39 -> 15765495703 | H57: =IF(B$53=0,0,G57/B$53) -> 455.95373
A58: Skilled Nursing | B58: =GETPIVOTDATA("Sum of EXP_SN",Pivot!$A$10) -> 6111106482 | C58: =IF(B58=0,0,B58/B$101) -> 0.38130491 | D58: =IF(B44=0,0,B58/B44) -> 186.83775 | F58: Gross Ancillary Revenue | G58: =E39+F39 -> 4363172945 | H58: =IF(B$53=0,0,G58/B$53) -> 126.18728
A59: Intermediate Care | B59: =GETPIVOTDATA("Sum of EXP_IC",Pivot!$A$10) -> 821880 | C59: =IF(B59=0,0,B59/B$101) -> 5.1281528e-05 | D59: =IF(B45=0,0,B59/B45) -> 71.275692 | F59: - Deductions from Revenue | G59: =H53 -> 4027917816 | H59: =IF(B$53=0,0,G59/B$53) -> 116.49137
A60: Mentally Disordered | B60: =GETPIVOTDATA("Sum of EXP_MD",Pivot!$A$10) -> 113350522 | C60: =IF(B60=0,0,B60/B$101) -> 0.0070725507 | D60: =IF(B46=0,0,B60/B46) -> 147.39338 | F60: Net Patient Revenue | G60: =G57+G58-G59 -> 16100750832 | H60: =IF(B$53=0,0,G60/B$53) -> 465.64964
A61: Developmentally Disabled | B61: =GETPIVOTDATA("Sum of EXP_DD",Pivot!$A$10) -> 21887937 | C61: =IF(B61=0,0,B61/B$101) -> 0.0013657065 | D61: =IF(B47=0,0,B61/B47) -> 157.58962 | F61: + Other Operating Revenue | G61: =GETPIVOTDATA("Sum of OTH_OP_REV",Pivot!$A$10) -> 51145299 | H61: =IF(B$53=0,0,G61/B$53) -> 1.4791726
A62: Sub-Acute Care | B62: =GETPIVOTDATA("Sum of EXP_SUBACU",Pivot!$A$10) -> 354956468 | C62: =IF(B62=0,0,B62/B$101) -> 0.02214765 | D62: =IF(B48=0,0,B62/B48) -> 392.31203 | F62: Total Health Care Revenue | G62: =G60+G61 -> 16151896131 | H62: =IF(B$53=0,0,G62/B$53) -> 467.12881
A63: Sub- Acute - Pediatric | B63: =GETPIVOTDATA("Sum of EXP_SUBPED",Pivot!$A$10) -> 33736842 | C63: =IF(B63=0,0,B63/B$101) -> 0.0021050236 | D63: =IF(B49=0,0,B63/B49) -> 755.87216 | F63: - Health Care Expenses | G63: =B101 -> 16026823427 | H63: =IF(B$53=0,0,G63/B$53) -> 463.51159
A64: Transitional Inpatient Care | B64: =GETPIVOTDATA("Sum of EXP_TIC",Pivot!$A$10) -> 0 | C64: =IF(B64=0,0,B64/B$101) -> 0 | D64: =IF(B50=0,0,B64/B50) -> 0 | F64: Net from Health Operations | G64: =G62-G63 -> 125072704 | H64: =IF(B$53=0,0,G64/B$53) -> 3.6172263
A65: Hospice Inpatient Care | B65: =GETPIVOTDATA("Sum of EXP_HOSPIC",Pivot!$A$10) -> 0 | C65: =IF(B65=0,0,B65/B$101) -> 0 | D65: =IF(B51=0,0,B65/B51) -> 0 | F65: Nonhealth Rev & Exp, Net * | G65: =GETPIVOTDATA("Sum of NONHC_NET",Pivot!$A$10) -> 440598221 | H65: =IF(B$53=0,0,G65/B$53) -> 12.742536
A66: Other Routine Services | B66: =GETPIVOTDATA("Sum of EXP_OTH_RT",Pivot!$A$10) -> 244879 | C66: =IF(B66=0,0,B66/B$101) -> 1.5279322e-05 | D66: =IF(B52=0,0,B66/B52) -> 0 | F66: Income Taxes | G66: =Pivot!B105*-1 -> -37125319 | H66: =IF(B$53=0,0,G66/B$53) -> -1.0737009
A67: Total Routine Services | B67: =SUM(B58:B66) -> 6636105010 | C67: =IF(B67=0,0,B67/B$101) -> 0.4140624 | D67: =IF(B53=0,0,B67/B53) -> 191.92272 | F67: Extraordinary Items | G67: =GETPIVOTDATA("Sum of EXT_ITEM",Pivot!$A$10) -> -27853 | H67: =IF(B$53=0,0,G67/B$53) -> -0.00080553631
A68: Ancillary Services: | F68: Net Income | G68: =G64+G65+G66+G67 -> 528517753 | H68: =IF(B$53=0,0,G68/B$53) -> 15.285256
A69: Patient Supplies | B69: =GETPIVOTDATA("Sum of EXP_PSUPPL",Pivot!$A$10) -> 42469566 | C69: =IF(B69=0,0,B69/B$101) -> 0.0026499054 | D69: =IF(B$53=0,0,B69/B$53) -> 1.2282619 | F69: * Includes Revenues and Expenses related to Residential Care
A70: Special Support Surfaces | B70: =GETPIVOTDATA("Sum of EXP_SPSURF",Pivot!$A$10) -> 8859015 | C70: =IF(B70=0,0,B70/B$101) -> 0.00055276175 | D70: =IF(B$53=0,0,B70/B$53) -> 0.25621148
A71: Physical Therapy | B71: =GETPIVOTDATA("Sum of EXP_PT",Pivot!$A$10) -> 495788064 | C71: =IF(B71=0,0,B71/B$101) -> 0.030934893 | D71: =IF(B$53=0,0,B71/B$53) -> 14.338681 | F71: Balance Sheet - Unrestricted Fund *
A72: Respiratory Therapy | B72: =GETPIVOTDATA("Sum of EXP_RT",Pivot!$A$10) -> 46938397 | C72: =IF(B72=0,0,B72/B$101) -> 0.0029287399 | D72: =IF(B$53=0,0,B72/B$53) -> 1.3575049 | F72: Current Assets | G72: =GETPIVOTDATA("Sum of CUR_ASST",Pivot!$A$10) -> 7484195310
A73: Occupational Therapy | B73: =GETPIVOTDATA("Sum of EXP_OT",Pivot!$A$10) -> 402398152 | C73: =IF(B73=0,0,B73/B$101) -> 0.025107792 | D73: =IF(B$53=0,0,B73/B$53) -> 11.637753 | F73: Limited Use Assets | G73: =GETPIVOTDATA("Sum of ASST_LIMTD",Pivot!$A$10) -> 1457881408
A74: Speech Pathology | B74: =GETPIVOTDATA("Sum of EXP_SP",Pivot!$A$10) -> 103201501 | C74: =IF(B74=0,0,B74/B$101) -> 0.0064392986 | D74: =IF(B$53=0,0,B74/B$53) -> 2.9846895 | F74: Net PPE | G74: =GETPIVOTDATA("Sum of NET_PPE",Pivot!$A$10) -> 4049983564
A75: Pharmacy | B75: =GETPIVOTDATA("Sum of EXP_PHARM",Pivot!$A$10) -> 285716416 | C75: =IF(B75=0,0,B75/B$101) -> 0.017827389 | D75: =IF(B$53=0,0,B75/B$53) -> 8.2632014 | F75: Construction-in-Progress | G75: =GETPIVOTDATA("Sum of CONST_PROG",Pivot!$A$10) -> 333976335
A76: Laboratory | B76: =GETPIVOTDATA("Sum of EXP_LAB",Pivot!$A$10) -> 51398140 | C76: =IF(B76=0,0,B76/B$101) -> 0.0032070073 | D76: =IF(B$53=0,0,B76/B$53) -> 1.486485 | F76: Investments & Other Assets | G76: =GETPIVOTDATA("Sum of INV_OTH",Pivot!$A$10) -> 5174294990
A77: Home Health Services | B77: =GETPIVOTDATA("Sum of EXP_HMHLTH",Pivot!$A$10) -> 258037 | C77: =IF(B77=0,0,B77/B$101) -> 1.6100321e-05 | D77: =IF(B$53=0,0,B77/B$53) -> 0.0074626853 | F77: Intangible Assets | G77: =GETPIVOTDATA("Sum of INTAN_ASST",Pivot!$A$10) -> 1392938827
A78: Other Ancillary Services | B78: =GETPIVOTDATA("Sum of EXP_OTH_AN",Pivot!$A$10) -> 71732617 | C78: =IF(B78=0,0,B78/B$101) -> 0.0044757851 | D78: =IF(B$53=0,0,B78/B$53) -> 2.0745782 | F78: Total Assets | G78: =SUM(G72:G77) -> 19893270434
A79: Total Ancillary Services | B79: =SUM(B69:B78) -> 1508759905 | C79: =IF(B79=0,0,B79/B$101) -> 0.094139672 | D79: =IF(B$53=0,0,B79/B$53) -> 43.634829
A80: Support Services: | F80: Current Liabilities | G80: =GETPIVOTDATA("Sum of CUR_LIAB",Pivot!$A$10) -> 6014763140
A81: Plant Operations & Maint. | B81: =GETPIVOTDATA("Sum of EXP_POM",Pivot!$A$10) -> 561815648 | C81: =IF(B81=0,0,B81/B$101) -> 0.03505471 | D81: =IF(B$53=0,0,B81/B$53) -> 16.248264 | F81: Deferred Credits | G81: =GETPIVOTDATA("Sum of DEF_CRED",Pivot!$A$10) -> 2739002610
A82: Housekeeping | B82: =GETPIVOTDATA("Sum of EXP_HKP",Pivot!$A$10) -> 375825693 | C82: =IF(B82=0,0,B82/B$101) -> 0.023449793 | D82: =IF(B$53=0,0,B82/B$53) -> 10.869251 | F82: Net Long-Term Debt | G82: =GETPIVOTDATA("Sum of NET_LTDEBT",Pivot!$A$10) -> 4490015321
A83: Laundry and Linen | B83: =GETPIVOTDATA("Sum of EXP_LL",Pivot!$A$10) -> 181754100 | C83: =IF(B83=0,0,B83/B$101) -> 0.011340619 | D83: =IF(B$53=0,0,B83/B$53) -> 5.2565084 | F83: Total Liabilities | G83: =SUM(G80:G82) -> 13243781071
A84: Dietary | B84: =GETPIVOTDATA("Sum of EXP_DIET",Pivot!$A$10) -> 1064053122 | C84: =IF(B84=0,0,B84/B$101) -> 0.066392016 | D84: =IF(B$53=0,0,B84/B$53) -> 30.773469
A85: Social Services | B85: =GETPIVOTDATA("Sum of EXP_SS",Pivot!$A$10) -> 191077732 | C85: =IF(B85=0,0,B85/B$101) -> 0.011922371 | D85: =IF(B$53=0,0,B85/B$53) -> 5.526157 | F85: Equity | G85: =GETPIVOTDATA("Sum of EQUITY",Pivot!$A$10) -> 6651245357
A86: Activities | B86: =GETPIVOTDATA("Sum of EXP_ACTV",Pivot!$A$10) -> 209634013 | C86: =IF(B86=0,0,B86/B$101) -> 0.013080197 | D86: =IF(B$53=0,0,B86/B$53) -> 6.062823 | F86: Total Liabilities & Equity | G86: =GETPIVOTDATA("Sum of LIAB_EQ",Pivot!$A$10) -> 19895026428
A87: Inservice Educ. - Nursing | B87: =GETPIVOTDATA("Sum of EXP_INSV",Pivot!$A$10) -> 129039601 | C87: =IF(B87=0,0,B87/B$101) -> 0.008051477 | D87: =IF(B$53=0,0,B87/B$53) -> 3.7319529 | F87: * Includes Assets and Liabilites related to Residential Care
A88: Administration | B88: =GETPIVOTDATA("Sum of EXP_ADMN",Pivot!$A$10) -> 3589927857 | C88: =IF(B88=0,0,B88/B$101) -> 0.22399497 | D88: =IF(B$53=0,0,B88/B$53) -> 103.82426
A89: Total Support Services | B89: =SUM(B81:B88) -> 6303127766 | C89: =IF(B89=0,0,B89/B$101) -> 0.39328616 | D89: =IF(B$53=0,0,B89/B$53) -> 182.29269 | F89: Intercompany Receivables | G89: =(GETPIVOTDATA("Sum of REL_REC_CR",Pivot!$A$10)+GETPIVOTDATA("Sum of REL_REC_LT",Pivot!$A$10)) -> 4220159521
A90: Property: | F90: Intercompany Payables | G90: =(GETPIVOTDATA("Sum of REL_PAY_CR",Pivot!$A$10)+GETPIVOTDATA("Sum of REL_PAY_LT",Pivot!$A$10)) -> 1764414440
A91: Depreciation/Amortization | B91: =GETPIVOTDATA("Sum of EXP_DPREC",Pivot!$A$10) -> 135726758 | C91: =IF(B91=0,0,B91/B$101) -> 0.0084687249 | D91: =IF(B$53=0,0,B91/B$53) -> 3.9253521
A92: Leases and Rentals | B92: =GETPIVOTDATA("Sum of EXP_LEASE",Pivot!$A$10) -> 1033800633 | C92: =IF(B92=0,0,B92/B$101) -> 0.0645044 | D92: =IF(B$53=0,0,B92/B$53) -> 29.898537
A93: Property Taxes | B93: =GETPIVOTDATA("Sum of EXP_PRPTAX",Pivot!$A$10) -> 82503230 | C93: =IF(B93=0,0,B93/B$101) -> 0.0051478217 | D93: =IF(B$53=0,0,B93/B$53) -> 2.386075 | F93: Financial Ratios *
A94: Property Insurance | B94: =GETPIVOTDATA("Sum of EXP_PRPINS",Pivot!$A$10) -> 40820697 | C94: =IF(B94=0,0,B94/B$101) -> 0.0025470236 | D94: =IF(B$53=0,0,B94/B$53) -> 1.1805749 | F94: Current Ratio | H94: =IF(G80=0,0,G$72/G$80) -> 1.2443042
A95: Interest - P. P. & E. | B95: =GETPIVOTDATA("Sum of EXP_INTPPE",Pivot!$A$10) -> 8578304 | C95: =IF(B95=0,0,B95/B$101) -> 0.00053524668 | D95: =IF(B$53=0,0,B95/B$53) -> 0.24809304 | F95: Acid Test Ratio | H95: =IF(Profile!G80=0,0,Pivot!B$124/Profile!G$80) -> 0.19733942
A96: Total Property | B96: =SUM(B91:B95) -> 1301429622 | C96: =IF(B96=0,0,B96/B$101) -> 0.081203217 | D96: =IF(B$53=0,0,B96/B$53) -> 37.638632 | F96: Long-term Debt to Assets Rate | H96: =IF(Profile!G78=0,0,Pivot!B$125/Profile!G$78) -> 0.22911883
A97: Other Expenses | F97: Debt Service Coverage Ratio | H97: =IF((Pivot!B$126+Profile!B$95+Profile!B$98)=0,0,(G$68+B$95+B$98+B$91)/(Pivot!B$126+Profile!B$95+Profile!B$98)) -> -24.923638
A98: Interest - Other | B98: =GETPIVOTDATA("Sum of EXP_INTOTH",Pivot!$A$10) -> 31086583 | C98: =IF(B98=0,0,B98/B$101) -> 0.0019396597 | D98: =IF(B$53=0,0,B98/B$53) -> 0.89905473 | F98: Operating Margin | H98: =IF(G62=0,0,G$64/G$62) -> 0.0077435307
A99: Provision for Bad Debts | B99: =GETPIVOTDATA("Sum of EXP_BDEBT",Pivot!$A$10) -> 246314541 | C99: =IF(B99=0,0,B99/B$101) -> 0.015368893 | D99: =IF(B$53=0,0,B99/B$53) -> 7.1236602 | F99: Turnover on Operating Assets | H99: =IF((G72+G74)=0,0,G60/(G72+G74)) -> 1.3959165
A100: Total Other | B100: =SUM(B98:B99) -> 277401124 | C100: =IF(B100=0,0,B100/B$101) -> 0.017308553 | D100: =IF(B$53=0,0,B100/B$53) -> 8.0227149 | F100: Assets to Equity Ratio | H100: =IF(G85=0,0,G78/G85) -> 2.9909091
A101: Total Health Care Expenses | B101: =B67+B79+B89+B96+B100 -> 16026823427 | C101: =IF(B101=0,0,B101/B$101) -> 1 | D101: =IF(B$53=0,0,B101/B$53) -> 463.51159 | F101: Net PP&E Assets per Bed | H101: =IF(B14=0,0,(G74+G75)/B14) -> 40569.683
F102: * Includes Assets and Liabilites related to Residential Care
...

Sheet Patient Days Chart
A33: Profile Characteristics
A34: No. of Facilities | C34: =Profile!B$2 -> 1076
A35: Facility Name | C35: =Profile!B$3 -> (All)
A36: County | C36: =Profile!B$4 -> (All)
A37: HFPA | C37: =Profile!B$5 -> (All)
A38: Type of Care | C38: =Profile!B$6 -> (All)
A39: License Category | C39: =Profile!B$7 -> (All)
A40: Type of Control | C40: =Profile!B$8 -> (All)
A41: Licensed Bed Size | C41: =Profile!B$9 -> (All)
A42: Residential Care | C42: =Profile!B$10 -> 0

Sheet Revenue & Expense per Day Chart
A33: Profile Characteristics
A34: No. of Facilities | C34: =Profile!B$2 -> 1076
A35: Facility Name | C35: =Profile!B$3 -> (All)
A36: County | C36: =Profile!B$4 -> (All)
A37: HFPA | C37: =Profile!B$5 -> (All)
A38: Type of Care | C38: =Profile!B$6 -> (All)
A39: License Category | C39: =Profile!B$7 -> (All)
A40: Type of Control | C40: =Profile!B$8 -> (All)
A41: Licensed Bed Size | C41: =Profile!B$9 -> (All)
A42: Residential Care | C42: =Profile!B$10 -> 0

Sheet Revenue Chart
A33: Profile Characteristics
A34: No. of Facilities | C34: =Profile!B$2 -> 1076
A35: Facility Name | C35: =Profile!B$3 -> (All)
A36: County | C36: =Profile!B$4 -> (All)
A37: HFPA | C37: =Profile!B$5 -> (All)
A38: Type of Care | C38: =Profile!B$6 -> (All)
A39: License Category | C39: =Profile!B$7 -> (All)
A40: Type of Control | C40: =Profile!B$8 -> (All)
A41: Licensed Bed Size | C41: =Profile!B$9 -> (All)
A42: Residential Care | C42: =Profile!B$10 -> 0

Sheet Expense Chart
A33: Profile Characteristics
A34: No. of Facilities | C34: =Profile!B$2 -> 1076
A35: Facility Name | C35: =Profile!B$3 -> (All)
A36: County | C36: =Profile!B$4 -> (All)
A37: HFPA | C37: =Profile!B$5 -> (All)
A38: Type of Care | C38: =Profile!B$6 -> (All)
A39: License Category | C39: =Profile!B$7 -> (All)
A40: Type of Control | C40: =Profile!B$8 -> (All)
A41: Licensed Bed Size | C41: =Profile!B$9 -> (All)
A42: Residential Care | C42: =Profile!B$10 -> 0

Sheet Labor Chart
A33: Profile Characteristics
A34: No. of Facilities | C34: =Profile!B$2 -> 1076
A35: Facility Name | C35: =Profile!B$3 -> (All)
A36: County | C36: =Profile!B$4 -> (All)
A37: HFPA | C37: =Profile!B$5 -> (All)
A38: Type of Care | C38: =Profile!B$6 -> (All)
A39: License Category | C39: =Profile!B$7 -> (All)
A40: Type of Control | C40: =Profile!B$8 -> (All)
A41: Licensed Bed Size | C41: =Profile!B$9 -> (All)
A42: Residential Care | C42: =Profile!B$10 -> 0

Sheet Glossary
A1: Acid Test Ratio | B1: (See Ratios.)
A3: Activities | B3: The cost center which includes activity programs organized for the benefit of the patient, including social activities, religious programs, educational activities, and exercise activities.
A5: Administration | B5: The cost center which includes the overall management and administration of the institution, general patient accounting, communication systems, data processing, patient admissions, public relations, professional liability and non-property-related insurance, licenses and taxes, medical record activities, and procurement of supplies and equipment.
A7: Admissions | B7: The number of patients formally admitted to the facility, or transferred from a residential care unit of the facility. Does not include patients returning to the facility under a bed-hold or leave, where a bed has been held open specifically for the patient's return.
A9: Ancillary Services | B9: The group of cost centers which includes diagnostic or therapeutic services performed by specific departments of the long-term care facility (or under contract) that are not part of the general or routine patient care. Ancillary services are those special services for which charges are customarily made in addition to routine charges and include patient supplies, pharmacy, laboratory, physical therapy, and home health services.
A11: Assets | B11: Physical objects (tangible) or rights (intangible) having economic value to their owner; items or sources of wealth expressed, for accounting purposes, in terms of their cost, depreciated cost, or less frequently, some other value; hence all costs benefiting a future period.
B13: a. Current Assets - The sum of all assets that are reasonably expected to be realized in cash, sold, or consumed within one year after the balance sheet due date.
B15: b. Assets Whose Use is Limited - Assets whose use is limited either by the governing board, trust agreements, or other outside parties.
B17: c. Net Property, Plant, and Equipment - The amount invested in property, plant, and equipment less accumulated depreciation (includes construction in progress).
B19: d. Investments and Other Assets - The sum of investments in property, plant, and equipment, other investments, receivables from related parties, and noncurrent deposits and other assets.
B21: e. Intangible Assets - The sum of unamortized goodwill, loan and organizational costs, and other intangible assets.
A23: Assets to Equity Ratio | B23: (See Ratios)
A25: Balance Sheet | B25: A statement that summarizes the assets, liabilities, and equity of the facility at the end of the report period.
A27: Bed Size | B27: The average number of licensed beds for a long-term care facility.
A29: Bed Size Group | B29: Based on the number of beds licensed by the California Department of Health Services' Licensing and Certification Division. For the aggregate profiles, long-term care facilities are assigned to one of three groups: 1 through 59, 60 through 99, and 100+ beds. These groupings coincide with reimbursement rates and/or staffing requirements.
A31: Congregate Living Health Facility (CLHF) | B31: As licensed by the Department of Health Services' Licensing and Certification Division, CLHFs provide care to patients with terminal or life-threatening illness, or with catastrophic and severe injury. CLHFs provide care in a non-institutional, homelike setting.
A33: Contractual Adjustments - Managed Care | B33: The difference between gross routine and ancillary revenues for Managed Care patients (billed at the facility’s full established rates) and the amounts received or to be received.
A35: Contractual Adjustments - Medicare | B35: The difference between gross routine and ancillary revenues for Medicare patients (billed at the facility’s full established rates) and the amounts received or to be received.
A37: Contractual Adjustments – Medi-Cal | B37: The difference between gross routine and ancillary revenues for Medi-Cal patients (billed at the facility’s full established rates) and the amounts received or to be received.
A39: Contractual Adjustments - Other | B39: The difference between gross routine and ancillary revenues for Other Payer patients (billed at the facility’s full established rates) and the amounts received or to be received.
A41: Cost Center | B41: An organizational department or unit performing functional services within the hospital. Some cost centers generate patient revenue and are classified as revenue-producing cost centers, such as Skilled Nursing and Physical Therapy. Other cost centers do not generate patient revenue and are classified as non-revenue producing cost centers, such as Housekeeping and Administration.
A43: Current Ratio | B43: (See Ratios.)
A45: Debt Service Coverage Ratio | B45: (See Ratios.)
... A115: Liabilities | B115: Amounts owed by the facility (debtor) to another entity (creditor), payable in money, or in goods and services.
B117: a. Deferred Credits: Revenue received or recorded before it is earned, such as deferred income taxes or deferred third-party income.
B119: b. Net Long-term Debt: Liabilities which are not expected to be satisfied within one year of the end of the reporting period. This amount reflects the reduction for that portion of the debt which is expected to be satisfied the next year. Includes mortgage notes, capitalized lease obligations, bonds payable, and long-term related party payables.
B121: c. Current Liabilities: Short-term debt or obligations that, according to reasonable expectations, are to be satisfied within a normal operating cycle, or one year, whichever is longer. Examples include accounts payable, accrued compensation and related liabilities, short-term related party payables, and the current maturities on long-term debt.
B123: d. Total Liabilities: The sum of current liabilities, deferred income, and net long-term debt.
A125: License Category | B125: As licensed by the Department of Health Services' Licensing and Certification Division, either Skilled Nursing Facility (SNF), Intermediate Care Facility (ICF), or Congregate Living Health Facility (CLHF) (not included in this file). SNF/RES and ICF/RES indicate facilities that are licensed for skilled nursing or intermediate care, but are an integral part of a residential care facility.
A127: Licensed Beds | B127: The average number of beds licensed by the Department of Health Services, less those beds in suspense, during the reporting period.
A129: Long-term Debt to Assets Rate | B129: (See Ratios.)
A131: Managed Care | B131: Groups that have a contractual relationship with the facility such as HMO's, PPO's or others. Patients enrolled in managed care plans funded by Medicare and Medi-Cal or other government programs are included here.
A133: Medi-Cal | B133: The federally-aided, State operated and administered Medicaid program which provides medical benefits for certain low-income persons. Data related to Medi-Cal patients enrolled in health maintenance organizations (HMOs) are not included in the Medi-Cal payer category, but are part of the "Other Payer" category.
A135: Medicare | B135: A federal health insurance program designed to underwrite the medical costs of persons 65 and over, and some qualified persons under 65. Data related to Medi-Care patients enrolled in health maintenance organizations (HMOs) are not included in the Medi-Care payer category, but are part of the "Other Payer" category.
A137: Mentally Disordered (MD) | B137: A person with a chronic psychiatric impairment and whose adaptive functioning is moderately impaired. Also used to describe the nursing care given to such a person.
A139: Net Income (Loss) | B139: The amount of income from operations plus nonhealth care revenue net of nonhealth care expense, less provision for income taxes and extraordinary items. (Often called “the bottom line.”)
A141: Net Patient Services Revenue | B141: The difference between gross routine and ancillary services revenue (recorded at the facility’s full established rates) and deductions from revenue.
A143: Net PP&E Assets per Bed | B143: (See Ratios.)
A145: Nonhealth Care Revenue and Expenses | B145: Revenues and expenses not directly related to patient services. This includes residential care revenue and expense, and nonoperating gains and losses.
A147: Not-for-Profit | B147: Ownership group which includes all church-related and other facilities that are corporations organized and operated under a policy by which no stockholder or trustee shares in the profits or losses of the enterprise.
... A177: Ratios | B177: A comparison of related pieces of financial and/or utilization data that are usually expressed as a percentage or a fraction.
B179: a. Acid Test Ratio - Cash plus marketable securities divided by total current liabilities. This ratio shows the amount of cash and marketable securities per dollar of current liabilities. It is a stricter test of liquidity than the current ratio as it excludes from the numerator any assets which cannot be immediately realized to cover current liabilities. Higher values indicate that more liquid resources are available to meet current liabilities.
B181: b. Assets to Equity Ratio - Total assets divided by total equity. This ratio indicates the extent to which equity levels are used to support assets and generate future earnings. If the value is too high, the facility may be undercapitalized; if too low, the facility may be overcapitalized. A value of 4 or 5 is a well-capitalized condition.
B183: c. Current Ratio - Total current assets divided by total current liabilities. This ratio shows the dollar amount of current assets per dollar of current liabilities. It is a gross indicator of the facility’s liquidity. Usually a ratio of 2.0 or more indicates a healthy liquidity position.
B185: d. Debt Service Coverage Ratio - The sum of net income, interest expense, and depreciation and amortization, divided by the sum of current maturities of long-term debt and interest expense. This ratio indicates the facility’s ability to meet its principal and interest payments on long-term debt. A value of 1.00 or more means that the facility is meeting its debt requirements.
B187: e. Long-term Debt to Assets Rate - Net long-term debt divided by total assets and multiplied by 100. This ratio indicates the proportion of total assets that is financed by long-term debt.
B189: f. Net PPE Assets Per Bed - Net property, plant, and equipment, plus construction-in-progress, divided by available beds. This ratio indicates the property, plant, and equipment associated with each available bed.
B191: g. Operating Margin - Income (loss) from health care operations divided by total health care revenue (the sum of net routine services revenue, ancillary services revenue, and other operating revenue). This ratio indicates the percentage of health care revenue which remains as income after operating expenses have been deducted.
B193: h. Turnover of Operating Assets - The sum of net routine services revenue and net ancillary services revenue divided by the sum of current assets and net property, plant, and equipment. This ratio indicates how well operating assets are used to generate patient revenue.
A196: Report Period End | B196: The reporting period ends: (a) at the close of the facility's annual accounting period (fiscal year), (b) on the last day of patient care when the facility closes or moves, or (c) on the last day of licensure of the entity relinquishing the license when there is a change in licensee.
A198: Residential Care (RES) | B198: The provision of room and board, personal services, supervision and assistance in transportation, guidance, and training to sustain the person in the activities of daily living. Medication and nursing are not included. Also referred to as Assisted Living and Board and Care.
A200: Return on Equity | B200: (See Ratios.)
A202: Routine Services | B202: The cost centers which include care given to persons who are partially or totally unable to care for themselves, have health or mental problems and require convalescent and/or restorative services. Included are the following nursing services: skilled nursing care, intermediate care, mentally disordered care, developmentally disabled care, sub-acute care, hospice inpatient services, and other routine services. Also included are consultation and evaluation services.
A204: Self Pay | B204: Patients who are financially responsible for their own care and who are not covered by a third-party payer program.
A206: Skilled Nursing (SN) | B206: A level of nursing and supportive care provided by licensed nurses to patients who need 24-hour nursing service on an extended basis.
A208: Social Services | B208: Cost center which obtains, analyzes, and interprets social and economic information to assist in diagnosis, treatment, and rehabilitation of patients.
A210: Sub-Acute Care (SA) | B210: Sub-Acute Care refers to the care provided to patients in the unit identified in a contract with the Department of Health Services to provide sub-acute Care to Medi-Cal beneficiaries. It is a level of nursing and supportive care services for patients who have a fragile medical condition. Such care is more intensive than skilled nursing care but less intensive than the usual medical, surgical, and pediatric acute care requirements.
A212: Sub-Acute Care - Pediatric (SP) | B212: Sub-Acute Care – Pediatric refers to the care provided to patients in the unit identified in a contract with the Department of Health Services to provide pediatric sub-acute care to Medi-Cal beneficiaries. A level of nursing and supportive care services for pediatric patients under 21 years of age, provided to patients who require intensive licensed nursing care and use a medical technology that compensates for the loss of a vital bodily function. Such care is more intensive than skilled nursing care but less intensive than the usual medical, surgical, and pediatric acute care requirements.
A214: Support Services | B214: The cost center group which includes services performed by specific departments of the long-term care facility that are not nursing or ancillary services, such as: Plant Operations and Maintenance, Housekeeping, Laundry and Linen, Dietary, Social Services, Activities, Inservice Education-Nursing and Administration.
A216: Temporary Nursing (Registry) Services | B216: Nursing obtained through a nurse registry or other temporary help agency.
A218: Total Health Care Expenses | B218: The cost incurred in the provision of health care services to patients in a long-term care facility.
... A228: Type of Care | B228: Indicates one or more of the following types of care offered by a facility:
B230: SN Skilled Nursing
B231: IC Intermediate Care
B232: MD Mentally Disordered
B233: DD Developmentally Disabled
B234: SA Sub-Acute Care
B235: SP Sub Acute Care-Pediatric
B236: TI Transitional Inpatient Care
B237: HI Hospice Inpatient Care
B238: OR Other Routine Services
B239: RES Residential Care
A241: Type of Control | B241: Not-for-profit (church-related), investor-owned (corporation, division, proprietorship, or partnership), or governmental (city/county, district, or state).

Sheet Chart DB
B1: MCare FFS | C1: MCare MC | D1: MCal FFS | E1: MCal MC | F1: CC FFS | G1: CC MC | H1: Self Pay | I1: Other Payers | J1: Total
A2: Patient Days | B2: =Profile!B23 -> 5656431 | C2: =Profile!B25 -> 2216758 | D2: =Profile!B27 -> 3266548 | E2: =Profile!B29 -> 19260667 | F2: =Profile!B31 -> 370809 | G2: =Profile!B33 -> 904327 | H2: =Profile!B35 -> 774017 | I2: =Profile!B37 -> 2127407 | J2: =Profile!B39 -> 34576964
B4: MCare FFS | C4: MCare MC | D4: MCal FFS | E4: MCal MC | F4: CC FFS | G4: CC MC | H4: Self Pay | I4: Other Payers | J4: Total
A5: Gross Revenue | B5: =Profile!C23+Profile!E23+Profile!F23 -> 6444528441 | C5: =Profile!C25+Profile!E25+Profile!F25 -> 2238608230 | D5: =Profile!C27+Profile!E27+Profile!F27 -> 1436382323 | E5: =Profile!C29+Profile!E29+Profile!F29 -> 8163547792 | F5: =Profile!C31+Profile!E31+Profile!F31 -> 354959168 | G5: =Profile!C33+Profile!E33+Profile!F33 -> 751064085 | H5: =Profile!C35+Profile!E35+Profile!F35 -> 354492315 | I5: =Profile!C37+Profile!E37+Profile!F37 -> 905608802 | J5: =Profile!C39+Profile!E39+Profile!F39 -> 20128668648
A6: Net Revenue | B6: =B5-Profile!H43 -> 5733642143 | C6: =C5-Profile!H44 -> 1405098118 | D6: =D5-Profile!H45 -> 1250046945 | E6: =E5-Profile!H46 -> 6269696385 | F6: =F5-Profile!H47 -> 235137937 | G6: =G5-Profile!H48 -> 539006683 | H6: =H5-Profile!H50-Profile!H51-Profile!H52 -> 345639724 | I6: =I5-Profile!H49 -> 843005405 | J6: =J5-Profile!H53 -> 16100750832
B9: MCare FFS | C9: MCare MC | D9: MCal FFS | E9: MCal MC | F9: CC FFS | G9: CC MC | H9: Self Pay | I9: Other Payers | J9: Total
A10: Gross Routine Revenue per Patient Day | B10: =Profile!D23 -> 606.8172 | C10: =Profile!D25 -> 660.31616 | D10: =Profile!D27 -> 411.96417 | E10: =Profile!D29 -> 402.24337 | F10: =Profile!D31 -> 511.06013 | G10: =Profile!D33 -> 466.84983 | H10: =Profile!D35 -> 424.15407 | I10: =Profile!D37 -> 393.03505 | J10: =Profile!D39 -> 455.95373
B12: Routine Care | C12: Ancillary Care | D12: Support Services | E12: Administration | F12: Property | G12: Other | H12: Total
A13: Expenses | B13: =Profile!B67 -> 6636105010 | C13: =Profile!B79 -> 1508759905 | D13: =Profile!B89-Profile!B88 -> 2713199909 | E13: =Profile!B88 -> 3589927857 | F13: =Profile!B96 -> 1301429622 | G13: =Profile!B100 -> 277401124 | H13: =Profile!B101 -> 16026823427
B15: Routine Nursing | C15: Ancillary | D15: Support Services | E15: Administration | F15: Temporary Nursing | G15: Total
A16: Hours per Patient Day | B16: =Profile!G116 -> 4.123917 | C16: =Profile!G124 -> 0.27219715 | D16: =Profile!G134-Profile!G133 -> 1.6029171 | E16: =Profile!G133 -> 0.52127038 | F16: =Profile!G141 -> 0.18968062 | G16: =Profile!G136+Profile!G141 -> 6.7099823
B18: Routine Care Expense | C18: Ancillary Care Expense | D18: Support Services Expense | E18: Admin. Expense | F18: Property Expense | G18: Other Expenses | H18: Total Expense | I18: Net Patient Revenue
A19: Per Patient Day | B19: =B13/$J2 -> 191.92272 | C19: =C13/J2 -> 43.634829 | D19: =D13/$J2 -> 78.468425 | E19: =E13/$J2 -> 103.82426 | F19: =F13/$J2 -> 37.638632 | G19: =G13/$J2 -> 8.0227149 | H19: =H13/$J2 -> 463.51159 | I19: =J6/J2 -> 465.64964

Sheet Data
A1: FAC_NO | B1: FAC_NAME | C1: BEG_DATE | D1: END_DATE | E1: DAY_PER | F1: DATA_IND | G1: ResCare | H1: County | I1: License Category | J1: TYPE_CNTRL | K1: HSA | L1: HFPA | M1: PHONE | N1: ADDRESS | O1: CITY | P1: ZIP_CODE | Q1: MCAL_PRO# | R1: ADMINIS | S1: RELATED | T1: PARENT | U1: BED_END | V1: BED_AVG | W1: Bed Size | X1: Licensed Bed Days | Y1: DAY_TOTL | Z1: OCCUP | AA1: ADMITS | AB1: DISCHS | AC1: DAYS_MCARE_FFS | AD1: DAYS_MCARE_MGD | AE1: DAYS_MCAL_FFS | AF1: DAYS_MCAL_MGD | AG1: DAYS_CC_FFS | AH1: DAYS_CC_MGD | AI1: DAY_SELF | AJ1: DAY_OTH | AK1: Type of Care | AL1: DAY_SN | AM1: DAY_IC | AN1: DAY_MD | AO1: DAY_DD | AP1: DAY_SUBACU | AQ1: DAY_SUBPED | AR1: DAY_TIC | AS1: DAY_HOSPIC | AT1: DAY_OTH_RT | AU1: GR_RT_TOTL | AV1: GR_AN_TOTL | AW1: DFR_TOTL | AX1: OTH_OP_REV | AY1: TOT_HC_REV | AZ1: TOT_HC_EXP | BA1: NET_FRM_HC | BB1: NONHC_NET | BC1: INC_TAX | BD1: EXT_ITEM | BE1: NET_INCOME | BF1: GR_RT_MCARE_FFS | BG1: GR_RT_MCARE_MGD | BH1: GR_RT_MCAL_FFS | BI1: GR_RT_MCAL_MGD | BJ1: GR_RT_CC_FFS | BK1: GR_RT_CC_MGD | BL1: GR_RT_SELF | BM1: GR_RT_OTH | BN1: GR_SN | BO1: GR_IC | BP1: GR_MD | BQ1: GR_DD | BR1: GR_SUBACU | BS1: GR_SUBPED | BT1: GR_TIC | BU1: GR_HOSPIC | BV1: GR_OTH_RT | BW1: GR_AN_MCARE_FFS_IP | BX1: GR_AN_MCARE_FFS_OP | BY1: GR_AN_MCARE_MGD_IP | BZ1: GR_AN_MCARE_MGD_OP | CA1: GR_AN_MCAL_FFS_IP | CB1: GR_AN_MCAL_FFS_OP | CC1: GR_AN_MCAL_MGD_IP | CD1: GR_AN_MCAL_MGD_OP | CE1: GR_AN_CC_FFS_IP | CF1: GR_AN_CC_FFS_OP | CG1: GR_AN_CC_MGD_IP | CH1: GR_AN_CC_MGD_OP | CI1: GR_AN_SELF_IP | CJ1: GR_AN_SELF_OP | CK1: GR_AN_OTH_IP | CL1: GR_AN_OTH_OP | CM1: GR_PSUPPLY | CN1: GR_SPSURF | CO1: GR_PT | CP1: GR_RT | CQ1: GR_OT | CR1: GR_SP | CS1: GR_PHARM | CT1: GR_LAB | CU1: GR_HMHLTH | CV1: GR_OTH_AN | CW1: DFR_IP_MCARE_FFS_CHARITY | CX1: DFR_OP_MCARE_FFS_CHARITY | CY1: DFR_IP_MCARE_MGD_CHARITY | CZ1: DFR_OP_MCARE_MGD_CHARITY | DA1: DFR_IP_MCAL_FFS_CHARITY | DB1: DFR_OP_MCAL_FFS_CHARITY | DC1: DFR_IP_MCAL_MGD_CHARITY | DD1: DFR_OP_MCAL_MGD_CHARITY | DE1: DFR_IP_CC_FFS_CHARITY | DF1: DFR_OP_CC_FFS_CHARITY | DG1: DFR_IP_CC_MGD_CHARITY | DH1: DFR_OP_CC_MGD_CHARITY | DI1: DFR_IP_SELF_PAY_CHARITY | DJ1: DFR_OP_SELF_PAY_CHARITY | DK1: DFR_IP_OTHER_PAYERS_CHARITY | DL1: DFR_OP_OTHER_PAYERS_CHARITY | DM1: DFR_IP_MCARE_FFS_ADM_ADJ | DN1: DFR_OP_MCARE_FFS_ADM_ADJ | DO1: DFR_IP_MCARE_MGD_ADM_ADJ | DP1: DFR_OP_MCARE_MGD_ADM_ADJ | DQ1: DFR_IP_MCAL_FFS_ADM_ADJ | DR1: DFR_OP_MCAL_FFS_ADM_ADJ | DS1: DFR_IP_MCAL_MGD_ADM_ADJ | DT1: DFR_OP_MCAL_MGD_ADM_ADJ | DU1: DFR_IP_CC_FFS_ADM_ADJ | DV1: DFR_OP_CC_FFS_ADM_ADJ | DW1: DFR_IP_CC_MGD_ADM_ADJ | DX1: DFR_OP_CC_MGD_ADM_ADJ | DY1: DFR_IP_SELF_PAY_ADM_ADJ | DZ1: DFR_OP_SELF_PAY_ADM_ADJ | EA1: DFR_IP_OTHER_PAYERS_ADM_ADJ | EB1: DFR_OP_OTHER_PAYERS_ADM_ADJ | EC1: DFR_IP_MCARE_FFS_CONT_ADJ | ED1: DFR_OP_MCARE_FFS_CONT_ADJ | EE1: DFR_IP_MCARE_MGD_CONT_ADJ | EF1: DFR_OP_MCARE_MGD_CONT_ADJ | EG1: DFR_IP_MCAL_FFS_CONT_ADJ | EH1: DFR_OP_MCAL_FFS_CONT_ADJ | EI1: DFR_IP_MCAL_MGD_CONT_ADJ | EJ1: DFR_OP_MCAL_MGD_CONT_ADJ | EK1: DFR_IP_CC_FFS_CONT_ADJ | EL1: DFR_OP_CC_FFS_CONT_ADJ | EM1: DFR_IP_CC_MGD_CONT_ADJ | EN1: DFR_OP_CC_MGD_CONT_ADJ | EO1: DFR_IP_OTHER_PAYERS_CONT_ADJ | EP1: DFR_OP_OTHER_PAYERS_CONT_ADJ | EQ1: DFR_IP_MCARE_FFS_OTH_DFR | ER1: DFR_OP_MCARE_FFS_OTH_DFR | ES1: DFR_IP_MCARE_MGD_OTH_DFR | ET1: DFR_OP_MCARE_MGD_OTH_DFR | EU1: DFR_IP_MCAL_FFS_OTH_DFR | EV1: DFR_OP_MCAL_FFS_OTH_DFR | EW1: DFR_IP_MCAL_MGD_OTH_DFR | EX1: DFR_OP_MCAL_MGD_OTH_DFR | EY1: DFR_IP_CC_FFS_OTH_DFR | EZ1: DFR_OP_CC_FFS_OTH_DFR | FA1: DFR_IP_CC_MGD_OTH_DFR | FB1: DFR_OP_CC_MGD_OTH_DFR | FC1: DFR_IP_SELF_PAY_OTH_DFR | FD1: DFR_OP_SELF_PAY_OTH_DFR | FE1: DFR_IP_OTHER_PAYERS_OTH_DFR | FF1: DFR_OP_OTHER_PAYERS_OTH_DFR | FG1: EXP_SAL | FH1: EXP_BEN | FI1: EXP_OTHER | FJ1: WORK_COMP | FK1: EXP_SN | FL1: EXP_IC | FM1: EXP_MD | FN1: EXP_DD | FO1: EXP_SUBACU | FP1: EXP_SUBPED | FQ1: EXP_TIC | FR1: EXP_HOSPIC | FS1: EXP_OTH_RT | FT1: EXP_PSUPPL | FU1: EXP_SPSURF | FV1: EXP_PT | FW1: EXP_RT | FX1: EXP_OT | FY1: EXP_SP | FZ1: EXP_PHARM | GA1: EXP_LAB | GB1: EXP_HMHLTH | GC1: EXP_OTH_AN | GD1: EXP_POM | GE1: EXP_HKP | GF1: EXP_LL | GG1: EXP_DIET | GH1: EXP_SS | GI1: EXP_ACTV | GJ1: EXP_INSV | GK1: EXP_ADMN | GL1: EXP_DPREC | GM1: EXP_LEASE | GN1: EXP_PRPTAX | GO1: EXP_PRPINS | GP1: EXP_INTPPE | GQ1: EXP_INTOTH | GR1: EXP_BDEBT | GS1: CUR_ASST | GT1: ASST_LIMTD | GU1: NET_PPE | GV1: CONST_PROG | GW1: INV_OTH | GX1: INTAN_ASST | GY1: TOT_ASST | GZ1: CUR_LIAB | HA1: DEF_CRED | HB1: NET_LTDEBT | HC1: EQUITY | HD1: LIAB_EQ | HE1: REL_REC_CR | HF1: REL_REC_LT | HG1: REL_PAY_CR | HH1: REL_PAY_LT | HI1: LAND&IMP | HJ1: BLDGS&IMP | HK1: LEASE_IMP | HL1: EQUIPMENT | HM1: TOT_PPE | HN1: ACC_DEPREC | HO1: MORT_PAY | HP1: CAP_LEASE | HQ1: BOND_PAY | HR1: TOT_LTDEBT | HS1: CUR_MAT | HT1: ACID_RATIO | HU1: Cash & Securities | HV1: PRDHR_MGT | HW1: PRDHR_GNP | HX1: PRDHR_RN | HY1: PRDHR_LVN | HZ1: PRDHR_NA | IA1: PRDHR_TSP | IB1: PRDHR_PSY | IC1: PRDHR_OTH | ID1: PRDHR_AN | IE1: PRDHR_POM | IF1: PRDHR_HKP | IG1: PRDHR_LL | IH1: PRDHR_DIET | II1: PRDHR_SS | IJ1: PRDHR_ACTV | IK1: PRDHR_INSV | IL1: PRDHR_ADMN | IM1: PRDHR_TOTL | IN1: TMP_HR_GNP | IO1: TMP_HR_RN | IP1: TMP_HR_LVN | IQ1: TMP_HR_NA | IR1: TMP_HR_PSY | IS1: TMP_HR_OTH | IT1: TMP_HR_TOT | IU1: S&W_MGT | IV1: S&W_GNP | IW1: S&W_RN | IX1: S&W_LVN | IY1: S&W_NA | IZ1: S&W_TSP | JA1: S&W_PSY | JB1: S&W_OTH | JC1: S&W_ANC | JD1: S&W_POM | JE1: S&W_HKP | JF1: S&W_LL | JG1: S&W_DIET | JH1: S&W_SS | JI1: S&W_ACTV | JJ1: S&W_INSV | JK1: S&W_ADMN | JL1: S&W_TOTL | JM1: TMP_PD_GNP | JN1: TMP_PD_RN | JO1: TMP_PD_LVN | JP1: TMP_PD_NA | JQ1: TMP_PD_PSY | JR1: TMP_PD_OTH | JS1: TMP_PD_TOT | JT1: HRS_SUP&MGMT_ANCILLARY | JU1: HRS_RN_ANCILLARY | JV1: HRS_LVN_ANCILLARY | JW1: HRS_NA_ANCILLARY | JX1: HRS_TECH/SPEC_ANCILLARY | JY1: HRS_OTHER_ANCILLARY | JZ1: S&W_SUP&MGMT_ANCILLARY | KA1: S&W_RN_ANCILLARY | KB1: S&W_LVN_ANCILLARY | KC1: S&W_NA_ANCILLARY | KD1: S&W_TECH/SPEC_ANCILLARY | KE1: S&W_OTHER_ANCILLARY | KF1: EMP_TOTAL_AVG | KG1: EMP_TOTAL_TOTAL | KH1: EMP_TOTAL_CONT | KI1: EMP_NRSG_AVG | KJ1: EMP_NRSG_TOTAL | KK1: EMP_NRSG_CONT | KL1: EMP_NA_AVG | KM1: EMP_NA_TOTAL | KN1: EMP_NA_CONT | KO1: Investor | KP1: Not-for-profit | KQ1: Governmental | KR1: 1-59 Beds | KS1: 60-99 Beds | KT1: 100+ Beds | KU1: SN Care | KV1: IC Care | KW1: MD Care | KX1: DD Care | KY1: SA Care | KZ1: SAP Care | LA1: TI Care | LB1: Hosp Care | LC1: Other Care | LD1: SNF Lic | LE1: ICF Lic | LF1: SNF/Res Lic | LG1: ICF/Res Lic | LH1: Other Lic
A2: 206010734 | B2: CROWN BAY NURSING AND REHABILITATION CENTER | C2: 45292 | D2: 45657 | E2: 366 | F2: In Process | G2: No | H2: Alameda | I2: SNF | J2: Investor Owned | K2: 05 - East Bay | L2: 0417 | M2: 510-521-5765 | N2: 508 WESTLINE DRIVE | O2: ALAMEDA | P2: 94501 | Q2: ZZR06103H | R2: RUBY SINGH | S2: Yes | U2: 151 | V2: 151 | W2: 100+ | X2: 55266 | Y2: 43622 | Z2: 186.38 | AA2: 516 | AB2: 409 | AC2: 2219 | AE2: 13071 | AF2: 19847 | AH2: 6287 | AI2: 950 | AJ2: 1248 | AK2: Skilled Nursing Care Only | AL2: 43622 | AU2: 16180094 | AV2: 3077943 | AW2: -442223 | AX2: 4892 | AY2: 19705152 | AZ2: 20843140 | BA2: -1137988 | BB2: 225160 | BE2: -912828 | BF2: 750500 | BH2: 5032335 | BI2: 7641095 | BK2: 2053700 | BL2: 304844 | BM2: 397620 | BN2: 16180094 | BW2: 930586 | CA2: 12686 | CC2: 19266 | CG2: 2108636 | CI2: 6769 | CM2: 4189 | CN2: 0 | CO2: 1014780 | CP2: 0 | CQ2: 887722 | CR2: 68437 | CS2: 956381 | CT2: 107388 | CV2: 39046 | DM2: -21087 | EC2: -783300 | EG2: -1692785 | EI2: 2160066 | EM2: -84632 | EO2: -20485 | FG2: 9513509 | FH2: 2527692 | FI2: 8801939 | FK2: 9380484 | FT2: 909 | FU2: 11363 | FV2: 546539 | FX2: 394128 | FY2: 44160 | FZ2: 292592 | GA2: 61802 | GC2: 28815 | GD2: 680161 | GE2: 779061 | GF2: 247793 | GG2: 1567644 | GH2: 189105 | GI2: 345997 | GJ2: 252899 | GK2: 3964205 | GL2: 18960 | GM2: 1132834 | GN2: 139280 | GO2: 31727 | GQ2: 337036 | GR2: 395646 | GS2: 5112726 | GT2: 30596 | GU2: 80550 | GV2: 66883 | GW2: 4223208 | GY2: 9513963 | GZ2: 4040784 | HC2: 5473179 | HD2: 9513963 | HF2: 4223208 | HI2: 0 | HK2: 92241 | HL2: 387575 | HM2: 479816 | HN2: -399266 | HT2: -0.01 | HU2: -40407.84 | HV2: 1771 | HW2: 0 | HX2: 9783 | HY2: 48888 | HZ2: 94509 | IA2: 0 | IB2: 0 | IC2: 5979 | IE2: 3683 | IF2: 25630 | IG2: 6091 | IH2: 29229 | II2: 3889 | IJ2: 11816 | IK2: 4226 | IL2: 16919 | IM2: 262413 | IN2: 0 | IO2: 1236 | IP2: 0 | IQ2: 22511 | IR2: 0 | IS2: 19697 | IT2: 43444 | IU2: 136779 | IV2: 0 | IW2: 762963 | IX2: 2414139 | IY2: 2972129 | IZ2: 0 | JA2: 0 | JB2: 355287 | JD2: 105847 | JE2: 565624 | JF2: 120567 | JG2: 717972 | JH2: 150485 | JI2: 272209 | JJ2: 194869 | JK2: 744639 | JL2: 9513509 | JM2: 0 | JN2: 49459 | JO2: 0 | JP2: 450215 | JQ2: 0 | JR2: 984827 | JS2: 1484501 | KF2: 156 | KG2: 234 | KH2: 104 | KI2: 98 | KJ2: 157 | KK2: 60 | KL2: 57 | KM2: 91 | KN2: 29 | KO2: 1 | KP2: 0 | KQ2: 0 | KR2: 0 | KS2: 0 | KT2: 1 | KU2: 1 | KV2: 0 | KW2: 0 | KX2: 0 | KY2: 0 | KZ2: 0 | LA2: 0 | LB2: 0 | LC2: 0 | LD2: 1 | LE2: 0 | LF2: 0 | LG2: 0 | LH2: 0
A3: 206010744 | B3: ASHBY CARE CENTER | C3: 45292 | D3: 45657 | E3: 366 | F3: In Process | G3: No | H3: Alameda | I3: SNF | J3: Investor Owned | K3: 05 - East Bay | L3: 0415 | M3: 510-841-9494 | N3: 2270 ASHBY AVENUE | O3: BERKELEY | P3: 94705 | Q3: LTM90004I | R3: RUBY SANTIAGO | S3: No | U3: 31 | V3: 31 | W3: 1-59 | X3: 11346 | Y3: 10576 | Z3: 218.69 | AA3: 16 | AB3: 17 | AC3: 301 | AE3: 9541 | AG3: 2 | AI3: 732 | AK3: Skilled Nursing Care Only | AL3: 10576 | AU3: 2409403 | AV3: 64939 | AW3: -147199 | AY3: 2621541 | AZ3: 2585336 | BA3: 36205 | BC3: 848 | BE3: 35357 | BF3: 107280 | BH3: 2073971 | BJ3: 440 | BL3: 227712 | BN3: 2409403 | BW3: 58171 | CA3: 1922 | CE3: 1475 | CI3: 3371 | CM3: 1813 | CN3: 0 | CO3: 45116 | CP3: 0 | CQ3: 0 | CR3: 0 | CS3: 15885 | CT3: 2125 | CV3: 0 | EC3: -167856 | EG3: 21900 | EK3: -1243 | FG3: 1198696 | FH3: 161375 | FI3: 1225265 | FJ3: 65951 | FK3: 1208858 | FV3: 11956 | FX3: 24667 | FY3: 2940 | FZ3: 15677 | GA3: 3274 | GC3: 1792 | GD3: 162230 | GE3: 60261 | GF3: 27086 | GG3: 233049 | GH3: 612 | GI3: 661 | GJ3: 10856 | GK3: 463757 | GL3: 637 | GM3: 227207 | GN3: 544 | GO3: 9417 | GQ3: 1379 | GR3: 118476 | GS3: 897299 | GU3: 4130 | GX3: 175000 | GY3: 1076429 | GZ3: 1500473 | HC3: -424044 | HD3: 1076429 | HG3: 658189 | HI3: 0 | HL3: 63178 | HM3: 63178 | HN3: -59048 | HT3: 0.07 | HU3: 105033.11 | HV3: 2080 | HW3: 0 | HX3: 4404 | HY3: 3925 | HZ3: 16682 | IA3: 0 | IB3: 0 | IC3: 200 | IE3: 2494 | IF3: 1348 | IG3: 1044 | IH3: 4906 | II3: 20 | IJ3: 20 | IK3: 144 | IL3: 2580 | IM3: 39847 | IN3: 0 | IO3: 0 | IP3: 0 | IQ3: 2763 | IR3: 0 | IS3: 0 | IT3: 2763 | IU3: 96000 | IV3: 0 | IW3: 207115 | IX3: 161182 | IY3: 457782 | IZ3: 0 | JA3: 0 | JB3: 8000 | JD3: 50214 | JE3: 26354 | JF3: 18332 | JG3: 116633 | JH3: 580 | JI3: 580 | JJ3: 9554 | JK3: 46370 | JL3: 1198696 | JM3: 0 | JN3: 0 | JO3: 0 | JP3: 120221 | JQ3: 0 | JR3: 0 | JS3: 120221 | KF3: 22 | KG3: 30 | KH3: 19 | KI3: 16 | KJ3: 23 | KK3: 15 | KL3: 11 | KM3: 16 | KN3: 10 | KO3: 1 | KP3: 0 | KQ3: 0 | KR3: 1 | KS3: 0 | KT3: 0 | KU3: 1 | KV3: 0 | KW3: 0 | KX3: 0 | KY3: 0 | KZ3: 0 | LA3: 0 | LB3: 0 | LC3: 0 | LD3: 1 | LE3: 0 | LF3: 0 | LG3: 0 | LH3: 0
A4: 206010747 | B4: BANCROFT HEALTHCARE CENTER | C4: 45292 | D4: 45657 | E4: 366 | F4: In Process | G4: No | H4: Alameda | I4: SNF | J4: Investor Owned | K4: 05 - East Bay | L4: 0421 | M4: 510-483-1680 | N4: 1475 BANCROFT AVENUE | O4: SAN LEANDRO | P4: 94577-5105 | Q4: ZZR05107F | R4: JEFFREY TONG | S4: Yes | U4: 36 | V4: 36 | W4: 1-59 | X4: 13176 | Y4: 12251 | Z4: 218.14 | AA4: 100 | AB4: 53 | AC4: 592 | AE4: 819 | AF4: 10501 | AI4: 339 | AK4: Skilled Nursing Care Only | AL4: 12251 | AU4: 5208005 | AV4: 455982 | AW4: 1736094 | AX4: 43071 | AY4: 3970964 | AZ4: 4920136 | BA4: -949172 | BB4: 639118 | BE4: -310054 | BF4: 224825 | BH4: 424150 | BI4: 4414050 | BL4: 144980 | BN4: 5208005 | BW4: 320313 | CA4: 24220 | CC4: 77207 | CI4: 34242 | CM4: 87432 | CN4: 0 | CO4: 208780 | CP4: 0 | CQ4: 33287 | CR4: 25199 | CS4: 90331 | CT4: 7917 | CV4: 3036 | EC4: -101761 | EG4: 213476 | EI4: 1624379 | FG4: 2364132 | FH4: 417402 | FI4: 2138602 | FJ4: 31490 | FK4: 2100483 | FT4: 2776 | FV4: 70735 | FX4: 13085 | FY4: 10793 | FZ4: 24423 | GA4: 2887 | GC4: 1664 | GD4: 190685 | GE4: 130087 | GF4: 34949 | GG4: 360249 | GH4: 60842 | GI4: 48474 | GK4: 922565 | GL4: 32156 | GM4: 854561 | GN4: 32043 | GO4: 13020 | GP4: 751 | GR4: 12908 | GS4: 998313 | GT4: 1343698 | GU4: 59651 | GX4: 80000 | GY4: 2481662 | GZ4: 777488 | HC4: 1704174 | HD4: 2481662 | HG4: 395000 | HI4: 0 | HL4: 308704 | HM4: 308704 | HN4: -249053 | HT4: 1.30 | HU4: 1010734.4 | HV4: 2449 | HW4: 0 | HX4: 1400 | HY4: 12218 | HZ4: 25847 | IA4: 0 | IB4: 0 | IC4: 1434 | IE4: 2003 | IF4: 4022 | IG4: 1529 | IH4: 8842 | II4: 1726 | IJ4: 1883 | IL4: 6541 | IM4: 69894 | IN4: 0 | IO4: 8 | IP4: 23 | IQ4: 2483 | IR4: 0 | IS4: 0 | IT4: 2514 | IU4: 134719 | IV4: 0 | IW4: 67615 | IX4: 507371 | IY4: 772131 | IZ4: 0 | JA4: 0 | JB4: 137865 | JD4: 37578 | JE4: 87436 | JF4: 24842 | JG4: 199614 | JH4: 51285 | JI4: 39632 | JK4: 304044 | JL4: 2364132 | JM4: 0 | JN4: 552 | JO4: 2201 | JP4: 89707 | JQ4: 0 | JR4: 0 | JS4: 92460 | KF4: 41 | KG4: 65 | KH4: 31 | KI4: 23 | KJ4: 37 | KK4: 14 | KL4: 12 | KM4: 23 | KN4: 5 | KO4: 1 | KP4: 0 | KQ4: 0 | KR4: 1 | KS4: 0 | KT4: 0 | KU4: 1 | KV4: 0 | KW4: 0 | KX4: 0 | KY4: 0 | KZ4: 0 | LA4: 0 | LB4: 0 | LC4: 0 | LD4: 1 | LE4: 0 | LF4: 0 | LG4: 0 | LH4: 0
A5: 206010749 | B5: ST. FRANCIS HEALTHCARE CENTER | C5: 45292 | D5: 45657 | E5: 366 | F5: In Process | G5: No | H5: Alameda | I5: SNF | J5: Investor Owned | K5: 05 - East Bay | L5: 0421 | M5: 510-785-3630 | N5: 718 BARTLETT AVE | O5: HAYWARD | P5: 94541-0000 | Q5: 1164984381 | R5: STEVEN STOCK | S5: Yes | U5: 62 | V5: 62 | W5: 60-99 | X5: 22692 | Y5: 18376 | Z5: 189.99 | AA5: 252 | AB5: 270 | AC5: 6230 | AD5: 3049 | AE5: 1013 | AF5: 6326 | AI5: 22 | AJ5: 1736 | AK5: Skilled Nursing Care Only | AL5: 18376 | AU5: 16683100 | AV5: 4307758 | AW5: 8453965 | AX5: 9015 | AY5: 12545908 | AZ5: 11939020 | BA5: 606888 | BB5: -2 | BE5: 606886 | BF5: 7787500 | BG5: 3763650 | BH5: 557150 | BI5: 3607900 | BL5: 12100 | BM5: 954800 | BN5: 16683100 | BW5: 3170668 | BY5: 1132951 | CA5: 325 | CC5: 225 | CI5: 3589 | CM5: 8412 | CN5: 30114 | CO5: 1446300 | CP5: 3310 | CQ5: 1463550 | CR5: 372900 | CS5: 621636 | CT5: 291972 | CV5: 69564 | EC5: 3417964 | EE5: 2850651 | EG5: 206278 | EI5: 1543301 | EO5: 435771 | FG5: 5150068 | FH5: 1333734 | FI5: 5455218 | FJ5: 128614 | FK5: 4460677 | FT5: 3091 | FU5: 20076 | FV5: 619001 | FW5: 2988 | FX5: 461309 | FY5: 130134 | FZ5: 270525 | GA5: 123812 | GC5: 85297 | GD5: 354494 | GE5: 430339 | GF5: 94686 | GG5: 681026 | GH5: 81556 | GI5: 153411 | GJ5: 119887 | GK5: 2505590 | GL5: 44188 | GM5: 581852 | GN5: 51535 | GO5: 57272 | GQ5: 8450 | GR5: 597824 | GS5: 9580861 | GU5: 866918 | GV5: 8796 | GY5: 10456575 | GZ5: 1470531 | HC5: 8986044 | HD5: 10456575 | HE5: 7879801 | HI5: 0 | HK5: 802239 | HL5: 219109 | HM5: 1021348 | HN5: -154430 | HT5: 0.00 | HU5: 0 | HV5: 2040 | HW5: 0 | HX5: 11846 | HY5: 18321 | HZ5: 44421 | IA5: 0 | IB5: 0 | IC5: 0 | ID5: 10235 | IE5: 2038 | IF5: 11515 | IG5: 5347 | IH5: 15202 | II5: 1683 | IJ5: 4656 | IK5: 2113 | IL5: 12412 | IM5: 141829 | IN5: 0 | IO5: 606 | IP5: 902 | IQ5: 9161 | IR5: 0 | IS5: 0 | IT5: 10669 | IU5: 219849 | IV5: 0 | IW5: 630271 | IX5: 782456 | IY5: 1209088 | IZ5: 0 | JA5: 0 | JB5: 0 | JC5: 656053 | JD5: 56680 | JE5: 268089 | JF5: 63404 | JG5: 362048 | JH5: 53038 | JI5: 104931 | JJ5: 96551 | JK5: 647610 | JL5: 5150068 | JM5: 0 | JN5: 49295 | JO5: 60030 | JP5: 384470 | JQ5: 0 | JR5: 0 | JS5: 493795 | JY5: 10235 | KE5: 656053 | KF5: 85 | KG5: 167 | KH5: 42 | KI5: 53 | KJ5: 114 | KK5: 20 | KL5: 27 | KM5: 59 | KN5: 11 | KO5: 1 | KP5: 0 | KQ5: 0 | KR5: 0 | KS5: 1 | KT5: 0 | KU5: 1 | KV5: 0 | KW5: 0 | KX5: 0 | KY5: 0 | KZ5: 0 | LA5: 0 | LB5: 0 | LC5: 0 | LD5: 1 | LE5: 0 | LF5: 0 | LG5: 0 | LH5: 0
A6: 206010750 | B6: VISTA POST ACUTE | C6: 45292 | D6: 45657 | E6: 366 | F6: In Process | G6: No | H6: Alameda | I6: SNF | J6: Investor Owned | K6: 05 - East Bay | L6: 0421 | M6: 510-537-6700 | N6: 3269 D STREET | O6: HAYWARD | P6: 94541 | Q6: 1790261014 | R6: SARAH R WILCOX | S6: Yes | U6: 71 | V6: 71 | W6: 60-99 | X6: 25986 | Y6: 24750 | Z6: 219.24 | AA6: 150 | AB6: 132 | AC6: 2974 | AE6: 1055 | AF6: 15274 | AH6: 2562 | AJ6: 2885 | AK6: Skilled Nursing Care Only | AL6: 24750 | AU6: 9532768 | AV6: 2328491 | AW6: 102827 | AX6: 50513 | AY6: 11808945 | AZ6: 10316222 | BA6: 1492723 | BB6: 19671 | BE6: 1512394 | BF6: 1145473 | BH6: 406346 | BI6: 5882970 | BK6: 986786 | BM6: 1111193 | BN6: 9532768 | BW6: 1697566 | CA6: 36403 | CC6: 527025 | CG6: 67497 | CM6: 2723 | CN6: 21698 | CO6: 413509 | CP6: 599188 | CQ6: 667620 | CR6: 323185 | CS6: 147118 | CT6: 79106 | CV6: 74344 | EC6: -686718 | EG6: 753262 | EI6: -1968452 | EM6: 893542 | EO6: 1111193 | FG6: 5201664 | FH6: 947217 | FI6: 4167341 | FJ6: 197252 | FK6: 4492989 | FV6: 236383 | FX6: 231210 | FY6: 64308 | FZ6: 81697 | GA6: 39588 | GC6: 18108 | GD6: 527485 | GE6: 129938 | GF6: 117533 | GG6: 701777 | GH6: 52137 | GI6: 43325 | GK6: 2527131 | GL6: 6116 | GM6: 604135 | GN6: 85083 | GO6: 91000 | GR6: 266279 | GS6: 7988421 | GU6: 201092 | GY6: 8189513 | GZ6: 4179632 | HC6: 4009881 | HD6: 8189513 | HE6: 5344060 | HG6: 2220610 | HI6: 0 | HK6: 198670 | HL6: 51842 | HM6: 250512 | HN6: -49420 | HT6: 0.18 | HU6: 752333.76 | HV6: 1588 | HW6: 0 | HX6: 7517 | HY6: 24191 | HZ6: 65710 | IA6: 0 | IB6: 0 | IC6: 2093 | ID6: 6341 | IE6: 9634 | IF6: 6159 | IG6: 4297 | IH6: 15867 | II6: 1231 | IJ6: 563 | IL6: 12154 | IM6: 157345 | IN6: 0 | IO6: 0 | IP6: 0 | IQ6: 0 | IR6: 0 | IS6: 0 | IT6: 0 | IU6: 136994 | IV6: 0 | IW6: 417527 | IX6: 1047972 | IY6: 1689431 | IZ6: 0 | JA6: 0 | JB6: 105190 | JC6: 342328 | JD6: 197637 | JE6: 108710 | JF6: 77375 | JG6: 314662 | JH6: 43190 | JI6: 10137 | JK6: 710511 | JL6: 5201664 | JM6: 0 | JN6: 0 | JO6: 0 | JP6: 0 | JQ6: 0 | JR6: 0 | JS6: 0 | JY6: 6341 | KE6: 342328 | KF6: 94 | KG6: 145 | KH6: 54 | KI6: 65 | KJ6: 101 | KK6: 35 | KL6: 43 | KM6: 65 | KN6: 23 | KO6: 1 | KP6: 0 | KQ6: 0 | KR6: 0 | KS6: 1 | KT6: 0 | KU6: 1 | KV6: 0 | KW6: 0 | KX6: 0 | KY6: 0 | KZ6: 0 | LA6: 0 | LB6: 0 | LC6: 0 | LD6: 1 | LE6: 0 | LF6: 0 | LG6: 0 | LH6: 0
A7: 206010757 | B7: BERKELEY PINES SKILLED NURSING CENTER | C7: 45292 | D7: 45657 | E7: 366 | F7: In Process | G7: No | H7: Alameda | I7: SNF | J7: Investor Owned | K7: 05 - East Bay | L7: 0415 | M7: 510-649-6670 | N7: 2223 ASHBY AVENUE | O7: BERKELEY | P7: 94705-0000 | Q7: ZZR05892J | R7: ALFREDO MACASIEB | S7: Yes | U7: 36 | V7: 36 | W7: 1-59 | X7: 13176 | Y7: 12809 | Z7: 228.08 | AA7: 36 | AB7: 24 | AC7: 518 | AE7: 879 | AF7: 11111 | AI7: 301 | AK7: Skilled Nursing Care Only | AL7: 12809 | AU7: 3842700 | AV7: 199752 | AW7: -165402 | AX7: 265303 | AY7: 4473157 | AZ7: 4921639 | BA7: -448482 | BE7: -448482 | BF7: 103800 | BH7: 277200 | BI7: 3367200 | BL7: 94500 | BN7: 3842700 | BW7: 153935 | CA7: 1150 | CC7: 44347 | CI7: 320 | CM7: 11070 | CN7: 0 | CO7: 46800 | CP7: 0 | CQ7: 82961 | CR7: 18028 | CS7: 34553 | CT7: 6340 | CV7: 0 | EC7: -112473 | EG7: -85875 | EI7: 32946 | FG7: 2277186 | FH7: 530957 | FI7: 2113496 | FJ7: 35288 | FK7: 1982292 | FT7: 512 | FV7: 14698 | FX7: 23044 | FY7: 6406 | FZ7: 14464 | GA7: 4237 | GD7: 250150 | GE7: 128988 | GF7: 78467 | GG7: 484622 | GH7: 14817 | GI7: 55290 | GK7: 964719 | GL7: 8892 | GM7: 832500 | GN7: 42012 | GO7: 15529 | GS7: 1877986 | GW7: -695336 | GY7: 1182650 | GZ7: 461503 | HC7: 721147 | HD7: 1182650 | HF7: -697836 | HG7: 70000 | HI7: 0 | HK7: 77864 | HL7: 48001 | HM7: 125865 | HN7: -125865 | HT7: 2.00 | HU7: 923006 | HV7: 1960 | HW7: 0 | HX7: 1659 | HY7: 10275 | HZ7: 28082 | IA7: 0 | IB7: 0 | IC7: 605 | IE7: 1896 | IF7: 4806 | IG7: 2768 | IH7: 12846 | II7: 403 | IJ7: 2199 | IL7: 7304 | IM7: 74803 | IN7: 0 | IO7: 77 | IP7: 126 | IQ7: 2292 | IR7: 0 | IS7: 0 | IT7: 2495 | IU7: 96587 | IV7: 0 | IW7: 76022 | IX7: 465197 | IY7: 773899 | IZ7: 0 | JA7: 0 | JB7: 20893 | JD7: 53088 | JE7: 92380 | JF7: 52609 | JG7: 267761 | JH7: 11966 | JI7: 45070 | JK7: 321714 | JL7: 2277186 | JM7: 0 | JN7: 5471 | JO7: 7728 | JP7: 84201 | JQ7: 0 | JR7: 0 | JS7: 97400 | KF7: 45 | KG7: 69 | KH7: 31 | KI7: 26 | KJ7: 44 | KK7: 17 | KL7: 18 | KM7: 30 | KN7: 11 | KO7: 1 | KP7: 0 | KQ7: 0 | KR7: 1 | KS7: 0 | KT7: 0 | KU7: 1 | KV7: 0 | KW7: 0 | KX7: 0 | KY7: 0 | KZ7: 0 | LA7: 0 | LB7: 0 | LC7: 0 | LD7: 1 | LE7: 0 | LF7: 0 | LG7: 0 | LH7: 0
A8: 206010770 | B8: VALLEY POINTE NURSING & REHABILITATION CENTER | C8: 45292 | D8: 45657 | E8: 366 | F8: In Process | G8: No | H8: Alameda | I8: SNF | J8: Investor Owned | K8: 05 - East Bay | L8: 0421 | M8: 510-538-8464 | N8: 20090 STANTON AVE | O8: CASTRO VALLEY | P8: 94546-5203 | Q8: 1669859567 | R8: ABRAHAM OYLER | S8: Yes | U8: 50 | V8: 50 | W8: 1-59 | X8: 18300 | Y8: 16458 | Z8: 211 | AA8: 289 | AB8: 283 | AC8: 6837 | AD8: 2905 | AE8: 743 | AF8: 5422 | AI8: 57 | AJ8: 494 | AK8: Skilled Nursing Care Only | AL8: 16458 | AU8: 16018252 | AV8: 4508687 | AW8: 7962824 | AX8: 7497 | AY8: 12571612 | AZ8: 11078706 | BA8: 1492906 | BB8: -1 | BE8: 1492905 | BF8: 8546250 | BG8: 3631250 | BH8: 407700 | BI8: 3202562 | BL8: 32650 | BM8: 197840 | BN8: 16018252 | BW8: 3284577 | BY8: 1202215 | CC8: 20831 | CI8: 1064 | CM8: 0 | CN8: 0 | CO8: 1468950 | CP8: 0 | CQ8: 1184900 | CR8: 337800 | CS8: 1221540 | CT8: 216183 | CV8: 79314 | EC8: 3942638 | EE8: 2755681 | EG8: 93054 | EI8: 1163416 | EO8: 8035 | FG8: 4990167 | FH8: 1519213 | FI8: 4569326 | FJ8: 192546 | FK8: 4177339 | FV8: 570165 | FW8: 484 | FX8: 374108 | FY8: 82195 | FZ8: 276978 | GA8: 92695 | GC8: 41104 | GD8: 424838 | GE8: 233937 | GF8: 67037 | GG8: 682023 | GH8: 81802 | GI8: 113630 | GJ8: 110979 | GK8: 2590348 | GL8: 86274 | GM8: 695861 | GN8: 58972 | GO8: 13398 | GQ8: 6815 | GR8: 297724 | GS8: 17821868 | GU8: 460238 | GY8: 18282106 | GZ8: 1427627 | HC8: 16854479 | HD8: 18282106 | HE8: 15679963 | HI8: 0 | HK8: 789800 | HL8: 216862 | HM8: 1006662 | HN8: -546424 | HT8: 0.00 | HU8: 0 | HV8: 1841 | HW8: 0 | HX8: 17002 | HY8: 14186 | HZ8: 40124 | IA8: 0 | IB8: 0 | IC8: 0 | ID8: 9615 | IE8: 2177 | IF8: 7969 | IG8: 3727 | IH8: 15460 | II8: 2009 | IJ8: 3957 | IK8: 1694 | IL8: 17198 | IM8: 136959 | IN8: 0 | IO8: 18 | IP8: 635 | IQ8: 994 | IR8: 0 | IS8: 0 | IT8: 1647 | IU8: 188093 | IV8: 0 | IW8: 920646 | IX8: 603445 | IY8: 1048350 | IZ8: 0 | JA8: 0 | JB8: 0 | JC8: 583473 | JD8: 53989 | JE8: 143127 | JF8: 57525 | JG8: 337339 | JH8: 63931 | JI8: 62862 | JJ8: 87106 | JK8: 840281 | JL8: 4990167 | JM8: 0 | JN8: 1915 | JO8: 47698 | JP8: 38996 | JQ8: 0 | JR8: 0 | JS8: 88609 | JY8: 9615 | KE8: 583473 | KF8: 83 | KG8: 143 | KH8: 49 | KI8: 52 | KJ8: 96 | KK8: 26 | KL8: 24 | KM8: 39 | KN8: 15 | KO8: 1 | KP8: 0 | KQ8: 0 | KR8: 1 | KS8: 0 | KT8: 0 | KU8: 1 | KV8: 0 | KW8: 0 | KX8: 0 | KY8: 0 | KZ8: 0 | LA8: 0 | LB8: 0 | LC8: 0 | LD8: 1 | LE8: 0 | LF8: 0 | LG8: 0 | LH8: 0
A9: 206010774 | B9: EAST BAY POST ACUTE | C9: 45292 | D9: 45657 | E9: 366 | F9: In Process | G9: No | H9: Alameda | I9: SNF | J9: Investor Owned | K9: 05 - East Bay | L9: 0421 | M9: 510-537-1234 | N9: 20259 LAKE CHABOT ROAD | O9: CASTRO VALLEY | P9: 94546 | Q9: 1811366586 | R9: ABRAHAM OYLER | S9: Yes | U9: 91 | V9: 91 | W9: 60-99 | X9: 33306 | Y9: 27963 | Z9: 196.98 | AA9: 237 | AB9: 229 | AC9: 3148 | AD9: 4058 | AE9: 1712 | AF9: 18400 | AH9: 304 | AI9: 14 | AJ9: 327 | AK9: Skilled Nursing Care Only | AL9: 27963 | AU9: 23460125 | AV9: 3035336 | AW9: 12801163 | AX9: 15632 | AY9: 13709930 | AZ9: 15182185 | BA9: -1472255 | BB9: -1 | BE9: -1472256 | BF9: 3935000 | BG9: 4643575 | BH9: 1278550 | BI9: 13103550 | BK9: 256850 | BL9: 10450 | BM9: 232150 | BN9: 23460125 | BW9: 1525949 | BY9: 1376690 | CA9: 8370 | CC9: 31280 | CG9: 89222 | CI9: 3825 | CM9: 1053 | CN9: 0 | CO9: 1086450 | CP9: 245750 | CQ9: 898150 | CR9: 346050 | CS9: 286778 | CT9: 123553 | CV9: 47552 | EC9: 1574153 | EE9: 3094045 | EG9: 1211957 | EI9: 6687788 | EM9: 112214 | EO9: 121006 | FG9: 6178909 | FH9: 1646683 | FI9: 7356593 | FJ9: 250901 | FK9: 6252908 | FT9: 725 | FV9: 505726 | FX9: 317222 | FY9: 73737 | FZ9: 180763 | GA9: 61383 | GC9: 102406 | GD9: 396923 | GE9: 646056 | GF9: 139661 | GG9: 986448 | GH9: 153629 | GI9: 141048 | GJ9: 131103 | GK9: 3257072 | GL9: 247707 | GM9: 771882 | GN9: 113359 | GO9: 18685 | GQ9: 12403 | GR9: 671339 | GS9: 2564233 | GU9: 1057209 | GV9: 22403 | GX9: 90000 | GY9: 3733845 | GZ9: 1935251 | HC9: 1798594 | HD9: 3733845 | HE9: 784179 | HI9: 0 | HK9: 1122373 | HL9: 662959 | HM9: 1785332 | HN9: -728123 | HT9: 0.00 | HU9: 0 | HV9: 2057 | HW9: 0 | HX9: 14032 | HY9: 34470 | HZ9: 50905 | IA9: 0 | IB9: 0 | IC9: 0 | ID9: 6426 | IE9: 3094 | IF9: 24857 | IG9: 1914 | IH9: 18269 | II9: 3504 | IJ9: 4420 | IK9: 2042 | IL9: 14790 | IM9: 180780 | IN9: 0 | IO9: 9 | IP9: 4107 | IQ9: 11941 | IR9: 0 | IS9: 0 | IT9: 16057 | IU9: 185296 | IV9: 0 | IW9: 768691 | IX9: 1533784 | IY9: 1394163 | IZ9: 0 | JA9: 0 | JB9: 0 | JC9: 412672 | JD9: 79286 | JE9: 484232 | JF9: 37150 | JG9: 435812 | JH9: 116433 | JI9: 98351 | JJ9: 97131 | JK9: 535908 | JL9: 6178909 | JM9: 0 | JN9: 844 | JO9: 275092 | JP9: 461730 | JQ9: 0 | JR9: 0 | JS9: 737666 | JY9: 6426 | KE9: 412672 | KF9: 101 | KG9: 217 | KH9: 40 | KI9: 64 | KJ9: 144 | KK9: 25 | KL9: 31 | KM9: 65 | KN9: 14 | KO9: 1 | KP9: 0 | KQ9: 0 | KR9: 0 | KS9: 1 | KT9: 0 | KU9: 1 | KV9: 0 | KW9: 0 | KX9: 0 | KY9: 0 | KZ9: 0 | LA9: 0 | LB9: 0 | LC9: 0 | LD9: 1 | LE9: 0 | LF9: 0 | LG9: 0 | LH9: 0
A10: 206010797 | B10: FREMONT HEALTHCARE CENTER | C10: 45292 | D10: 45657 | E10: 366 | F10: In Process | G10: No | H10: Alameda | I10: SNF | J10: Investor Owned | K10: 05 - East Bay | L10: 0421 | M10: 510-792-3743 | N10: 39022 PRESIDIO WAY | O10: FREMONT | P10: 94538 | Q10: 1194120600 | R10: ESPENITO CARAMBA | S10: Yes | T10: NATIONAL SENIOR CARE, INC. | U10: 115 | V10: 115 | W10: 100+ | X10: 42090 | Y10: 38410 | Z10: 153.92 | AA10: 189 | AB10: 185 | AC10: 5092 | AD10: 2703 | AE10: 3202 | AF10: 26572 | AI10: 203 | AJ10: 638 | AK10: Skilled Nursing Care Only | AL10: 38410 | AU10: 19179169 | AV10: 4081339 | AW10: 6005857 | AX10: 36 | AY10: 17254687 | AZ10: 17762298 | BA10: -507611 | BB10: 12426 | BE10: -495185 | BF10: 2765881 | BG10: 1498811 | BH10: 1696192 | BI10: 12857721 | BL10: 44849 | BM10: 315715 | BN10: 19179169 | BW10: 2862729 | BY10: 1080795 | CA10: 66382 | CC10: 67311 | CI10: -614 | CK10: 4736 | CM10: 0 | CN10: 0 | CO10: 1563808 | CP10: 0 | CQ10: 1856685 | CR10: 90760 | CS10: 481276 | CT10: 78161 | CV10: 10649 | EC10: 290624 | EE10: 1085957 | EG10: 277199 | EI10: 4237702 | EO10: 114372 | FE10: 3 | FG10: 6546468 | FH10: 2195567 | FI10: 9020263 | FJ10: 188957 | FK10: 8120481 | FT10: 103356 | FV10: 381581 | FW10: 7714 | FX10: 463978 | FY10: 9551 | FZ10: 194808 | GA10: 78717 | GC10: 38796 | GD10: 533629 | GE10: 542390 | GF10: 137069 | GG10: 1109699 | GH10: 171577 | GI10: 152793 | GK10: 3842154 | GL10: 95884 | GM10: 1068065 | GN10: 165461 | GO10: 146720 | GP10: 52161 | GR10: 345714 | GS10: 2366546 | GU10: 733156 | GV10: 41255 | GW10: 354549 | GY10: 3495506 | GZ10: 1584822 | HA10: 267943 | HC10: 1642741 | HD10: 3495506 | HG10: -1170561 | HI10: 0 | HJ10: 2327088 | HK10: 1062394 | HL10: 1120546 | HM10: 4510028 | HN10: -3776872 | HT10: 0.00 | HU10: 0 | HV10: 8586 | HW10: 0 | HX10: 21495 | HY10: 19717 | HZ10: 63693 | IA10: 0 | IB10: 0 | IC10: 5253 | IE10: 3649 | IF10: 18054 | IG10: 3782 | IH10: 20520 | II10: 3806 | IJ10: 4405 | IL10: 18476 | IM10: 191436 | IN10: 0 | IO10: 250 | IP10: 1454 | IQ10: 35519 | IR10: 0 | IS10: 0 | IT10: 37223 | IU10: 547110 | IV10: 0 | IW10: 1193352 | IX10: 895583 | IY10: 1830586 | IZ10: 0 | JA10: 0 | JB10: 190987 | JD10: 91208 | JE10: 365914 | JF10: 78713 | JG10: 488528 | JH10: 129120 | JI10: 110287 | JK10: 625080 | JL10: 6546468 | JM10: 0 | JN10: 19038 | JO10: 99611 | JP10: 1587118 | JQ10: 0 | JR10: 0 | JS10: 1705767 | KF10: 135 | KG10: 168 | KH10: 106 | KI10: 80 | KJ10: 108 | KK10: 58 | KL10: 47 | KM10: 67 | KN10: 31 | KO10: 1 | KP10: 0 | KQ10: 0 | KR10: 0 | KS10: 0 | KT10: 1 | KU10: 1 | KV10: 0 | KW10: 0 | KX10: 0 | KY10: 0 | KZ10: 0 | LA10: 0 | LB10: 0 | LC10: 0 | LD10: 1 | LE10: 0 | LF10: 0 | LG10: 0 | LH10: 0
A11: 206010798 | B11: DRIFTWOOD HEALTHCARE CENTER - HAYWARD | C11: 45292 | D11: 45657 | E11: 366 | F11: In Process | G11: No | H11: Alameda | I11: SNF | J11: Investor Owned | K11: 05 - East Bay | L11: 0421 | M11: 510-785-2880 | N11: 19700 HESPERIAN BLVD. | O11: HAYWARD | P11: 94541 | Q11: 1871881557 | R11: ERIKA AGAPAY | S11: Yes | T11: NATIONAL SENIOR CARE, INC. | U11: 88 | V11: 88 | W11: 60-99 | X11: 32208 | Y11: 28051 | Z11: 146.89 | AA11: 102 | AB11: 99 | AC11: 1682 | AD11: 2601 | AE11: 3876 | AF11: 19415 | AI11: 316 | AJ11: 161 | AK11: Mixed Care | AL11: 19818 | AP11: 8233 | AU11: 19837459 | AV11: 4546424 | AW11: 9617409 | AX11: 34 | AY11: 14766508 | AZ11: 15608435 | BA11: -841927 | BB11: 17057 | BE11: -824870 | BF11: 1372360 | BG11: 1767991 | BH11: 2853116 | BI11: 13357878 | BL11: 412257 | BM11: 73857 | BN11: 9346330 | BR11: 10491129 | BW11: 2171305 | BY11: 1785889 | CA11: 213406 | CC11: 376037 | CI11: -948 | CK11: 735 | CM11: 0 | CN11: -948 | CO11: 2411448 | CP11: 0 | CQ11: 985320 | CR11: 786880 | CS11: 300075 | CT11: 56003 | CV11: 7646 | EC11: 1159419 | EE11: 1681013 | EG11: 1387305 | EI11: 5407602 | EO11: -17934 | FE11: 4 | FG11: 6490283 | FH11: 2179252 | FI11: 6938900 | FJ11: 181703 | FK11: 4793994 | FO11: 2977225 | FT11: 224778 | FU11: 515 | FV11: 410117 | FW11: 508393 | FX11: 155920 | FY11: 126543 | FZ11: 103390 | GA11: 50765 | GC11: 57038 | GD11: 407385 | GE11: 466566 | GF11: 257684 | GG11: 1000999 | GH11: 91402 | GI11: 152511 | GK11: 3035647 | GL11: 121475 | GM11: 61842 | GN11: 97354 | GO11: 190989 | GP11: 20769 | GR11: 295134 | GS11: 3182386 | GU11: 418039 | GV11: -466215 | GW11: 268637 | GY11: 3402847 | GZ11: 2241315 | HA11: 361263 | HC11: 800269 | HD11: 3402847 | HG11: -180466 | HI11: 0 | HJ11: 722119 | HK11: 773758 | HL11: 1102035 | HM11: 2597912 | HN11: -2179873 | HT11: 0.00 | HU11: 0 | HV11: 7341 | HW11: 0 | HX11: 13810 | HY11: 42235 | HZ11: 54862 | IA11: 0 | IB11: 0 | IC11: 4117 | IF11: 13141 | IG11: 8582 | IH11: 17805 | II11: 1974 | IJ11: 5509 | IL11: 14593 | IM11: 183969 | IN11: 0 | IO11: 711 | IP11: 5287 | IQ11: 16984 | IR11: 0 | IS11: 8632 | IT11: 31614 | IU11: 492641 | IV11: 0 | IW11: 762510 | IX11: 1934178 | IY11: 1516138 | IZ11: 0 | JA11: 0 | JB11: 157813 | JE11: 301428 | JF11: 166228 | JG11: 438580 | JH11: 70006 | JI11: 112004 | JK11: 538757 | JL11: 6490283 | JM11: 0 | JN11: 50683 | JO11: 286842 | JP11: 659136 | JQ11: 0 | JR11: 431600 | JS11: 1428261 | KF11: 229 | KG11: 254 | KH11: 197 | KI11: 162 | KJ11: 178 | KK11: 140 | KL11: 67 | KM11: 75 | KN11: 58 | KO11: 1 | KP11: 0 | KQ11: 0 | KR11: 0 | KS11: 1 | KT11: 0 | KU11: 1 | KV11: 0 | KW11: 0 | KX11: 0 | KY11: 1 | KZ11: 0 | LA11: 0 | LB11: 0 | LC11: 0 | LD11: 1 | LE11: 0 | LF11: 0 | LG11: 0 | LH11: 0
A12: 206010806 | B12: HAYWARD HEALTHCARE AND WELLNESS CENTER | C12: 45170 | D12: 45535 | E12: 366 | F12: In Process | G12: No | H12: Alameda | I12: SNF | J12: Investor Owned | K12: 05 - East Bay | L12: 0421 | M12: 510-783-4811 | N12: 1805 WEST STREET | O12: HAYWARD | P12: 94545 | Q12: 1639401227 | R12: DATT, LALEEN | S12: Yes | U12: 99 | V12: 99 | W12: 60-99 | X12: 36234 | Y12: 33904 | Z12: 93.57 | AA12: 419 | AB12: 392 | AC12: 3882 | AE12: 2704 | AF12: 21971 | AG12: 3849 | AI12: 1019 | AJ12: 479 | AK12: Skilled Nursing Care Only | AL12: 33904 | AU12: 16600635 | AV12: 6559432 | AW12: 7070998 | AY12: 16089069 | AZ12: 16118662 | BA12: -29593 | BB12: 420112 | BC12: 12590 | BE12: 377929 | BF12: 3493800 | BH12: 881114 | BI12: 8272082 | BJ12: 3463527 | BL12: 334669 | BM12: 155443 | BN12: 16600635 | BW12: 2931962 | CA12: 48067 | CC12: 794131 | CE12: 2779125 | CI12: 5259 | CK12: 888 | CM12: 23087 | CN12: 53078 | CO12: 2269157 | CP12: 0 | CQ12: 1634344 | CR12: 718586 | CS12: 1279240 | CT12: 387798 | CV12: 194142 | DY12: 1719 | EC12: 1548086 | EG12: 141468 | EI12: 2148492 | EK12: 3213367 | EO12: 17866 | FG12: 7538249 | FH12: 1767568 | FI12: 6812845 | FJ12: 303529 | FK12: 6769717 | FT12: 10244 | FU12: 25197 | FV12: 496492 | FX12: 417112 | FY12: 107870 | FZ12: 415710 | GA12: 59616 | GC12: 93041 | GD12: 812649 | GE12: 369179 | GF12: 113211 | GG12: 964388 | GH12: 164316 | GI12: 245111 | GJ12: 130957 | GK12: 3034114 | GL12: 53783 | GM12: 1499297 | GN12: 96977 | GO12: 15738 | GQ12: 1189 | GR12: 222754 | GS12: 8428310 | GU12: 132901 | GV12: 386698 | GW12: 9883535 | GY12: 18831444 | GZ12: 14033450 | HC12: 4797994 | HD12: 18831444 | HE12: 4461513 | HG12: 1057558 | HI12: 0 | HJ12: 3400 | HK12: 498595 | HL12: 404342 | HM12: 906337 | HN12: -773436 | HT12: 0.01 | HU12: 140334.5 | HV12: 2024 | HW12: 0 | HX12: 13588 | HY12: 29202 | HZ12: 70485 | IA12: 0 | IB12: 0 | IC12: 6281 | ID12: 12201 | IE12: 5919 | IF12: 13345 | IG12: 4295 | IH12: 22928 | II12: 4289 | IJ12: 8374 | IK12: 2220 | IL12: 18411 | IM12: 213562 | IN12: 0 | IO12: 25 | IP12: 2001 | IQ12: 7656 | IR12: 0 | IS12: 0 | IT12: 9682 | IU12: 186678 | IV12: 0 | IW12: 710181 | IX12: 1393934 | IY12: 2048151 | IZ12: 0 | JA12: 0 | JB12: 294789 | JC12: 599531 | JD12: 156259 | JE12: 246518 | JF12: 77840 | JG12: 538370 | JH12: 133562 | JI12: 197344 | JJ12: 111261 | JK12: 843831 | JL12: 7538249 | JM12: 0 | JN12: 1918 | JO12: 108340 | JP12: 300178 | JQ12: 0 | JR12: 0 | JS12: 410436 | JY12: 12201 | KE12: 599531 | KF12: 156 | KG12: 254 | KH12: 93 | KI12: 80 | KJ12: 132 | KK12: 51 | KL12: 47 | KM12: 76 | KN12: 31 | KO12: 1 | KP12: 0 | KQ12: 0 | KR12: 0 | KS12: 1 | KT12: 0 | KU12: 1 | KV12: 0 | KW12: 0 | KX12: 0 | KY12: 0 | KZ12: 0 | LA12: 0 | LB12: 0 | LC12: 0 | LD12: 1 | LE12: 0 | LF12: 0 | LG12: 0 | LH12: 0
A13: 206010807 | B13: ELMWOOD CARE CENTER | C13: 45292 | D13: 45657 | E13: 366 | F13: In Process | G13: No | H13: Alameda | I13: SNF | J13: Investor Owned | K13: 05 - East Bay | L13: 0415 | M13: 510-665-2800 | N13: 2829 SHATTUCK AVENUE | O13: BERKELEY | P13: 94705 | Q13: 1023183662 | R13: GURBINDER KAUR | S13: Yes | U13: 77 | V13: 77 | W13: 60-99 | X13: 28182 | Y13: 25950 | Z13: 211.96 | AA13: 485 | AB13: 491 | AC13: 1786 | AD13: 534 | AE13: 1841 | AF13: 14297 | AH13: 5834 | AI13: 474 | AJ13: 1184 | AK13: Skilled Nursing Care Only | AL13: 25950 | AU13: 11679317 | AV13: 2670444 | AW13: 1514914 | AX13: 745 | AY13: 12835592 | AZ13: 11997177 | BA13: 838415 | BB13: 140313 | BC13: -27766 | BE13: 1006494 | BF13: 803825 | BG13: 240338 | BH13: 828579 | BI13: 6434651 | BK13: 2625708 | BL13: 213333 | BM13: 532883 | BN13: 11679317 | BW13: 509545 | BY13: 64462 | CA13: 26096 | CC13: 75141 | CG13: 1970342 | CI13: 24049 | CK13: 809 | CM13: 31891 | CN13: 0 | CO13: 1081974 | CP13: 0 | CQ13: 773910 | CR13: 130614 | CS13: 456568 | CT13: 134468 | CV13: 61019 | EC13: -620986 | EE13: 138303 | EG13: 227282 | EI13: 1625049 | EM13: -42277 | EO13: 187543 | FG13: 3758235 | FH13: 887555 | FI13: 7351387 | FJ13: 124084 | FK13: 5029721 | FT13: 24163 | FU13: 12489 | FV13: 553421 | FX13: 347902 | FY13: 67052 | FZ13: 264403 | GA13: 83355 | GC13: 41585 | GD13: 436899 | GE13: 304921 | GF13: 88200 | GG13: 715756 | GH13: 108524 | GI13: 153850 | GJ13: 28378 | GK13: 2770189 | GL13: 87491 | GM13: 554400 | GN13: 79557 | GO13: 10169 | GR13: 234752 | GS13: 7230765 | GU13: 524785 | GY13: 7755550 | GZ13: 1572532 | HC13: 6183018 | HD13: 7755550 | HI13: 0 | HK13: 711450 | HL13: 374632 | HM13: 1086082 | HN13: -561297 | HT13: 2.35 | HU13: 3695450.2 | HV13: 1770 | HW13: 0 | HX13: 12708 | HY13: 19127 | HZ13: 21761 | IA13: 0 | IB13: 0 | IC13: 2878 | IE13: 2007 | IF13: 9750 | IG13: 3098 | IH13: 13303 | II13: 2596 | IJ13: 2652 | IK13: 844 | IL13: 12436 | IM13: 104930 | IN13: 0 | IO13: 2298 | IP13: 3135 | IQ13: 43342 | IR13: 0 | IS13: 0 | IT13: 48775 | IU13: 137428 | IV13: 0 | IW13: 732242 | IX13: 843382 | IY13: 540313 | IZ13: 0 | JA13: 0 | JB13: 152353 | JD13: 54281 | JE13: 190694 | JF13: 61903 | JG13: 314243 | JH13: 82263 | JI13: 78319 | JJ13: 23402 | JK13: 547412 | JL13: 3758235 | JM13: 0 | JN13: 147905 | JO13: 165703 | JP13: 1432976 | JQ13: 0 | JR13: 0 | JS13: 1746584 | KF13: 65 | KG13: 134 | KH13: 44 | KI13: 33 | KJ13: 79 | KK13: 26 | KL13: 16 | KM13: 41 | KN13: 10 | KO13: 1 | KP13: 0 | KQ13: 0 | KR13: 0 | KS13: 1 | KT13: 0 | KU13: 1 | KV13: 0 | KW13: 0 | KX13: 0 | KY13: 0 | KZ13: 0 | LA13: 0 | LB13: 0 | LC13: 0 | LD13: 1 | LE13: 0 | LF13: 0 | LG13: 0 | LH13: 0
A14: 206010808 | B14: BAY AREA HEALTHCARE CENTER | C14: 45292 | D14: 45657 | E14: 366 | F14: In Process | G14: No | H14: Alameda | I14: SNF | J14: Investor Owned | K14: 05 - East Bay | L14: 0417 | M14: 510-536-6512 | N14: 1833 10TH AVE | O14: OAKLAND | P14: 94606-3023 | Q14: 1639431471 | R14: SHIRLY MA | S14: No | U14: 99 | V14: 99 | W14: 60-99 | X14: 36234 | Y14: 23514 | Z14: 148.45 | AA14: 364 | AB14: 368 | AC14: 268 | AD14: 6521 | AE14: 1474 | AF14: 13927 | AG14: 85 | AH14: 855 | AI14: 384 | AK14: Mixed Care | AL14: 12474 | AP14: 11040 | AU14: 28310162 | AV14: 2788841 | AW14: 11906589 | AX14: 90501 | AY14: 19282915 | AZ14: 19223828 | BA14: 59087 | BE14: 59087 | BF14: 202045 | BG14: 8220069 | BH14: 1828581 | BI14: 16607261 | BJ14: 155250 | BK14: 1102930 | BL14: 194026 | BN14: 6687534 | BR14: 21622628 | BW14: 82933 | BY14: 1843567 | CA14: 60612 | CC14: 542083 | CE14: 20242 | CG14: 229062 | CI14: 10342 | CM14: 648633 | CN14: 0 | CO14: 706839 | CP14: 0 | CQ14: 725040 | CR14: 67850 | CS14: 495285 | CT14: 97088 | CV14: 48106 | DY14: 350 | EC14: -20370 | EE14: 1679024 | EG14: 1002698 | EI14: 8807958 | EK14: 43741 | EM14: 393188 | FG14: 9798987 | FH14: 3279464 | FI14: 6145377 | FJ14: 174898 | FK14: 3419731 | FO14: 6239242 | FT14: 637243 | FV14: 318534 | FX14: 378913 | FY14: 55030 | FZ14: 332966 | GA14: 70553 | GC14: 39966 | GD14: 794026 | GE14: 400617 | GF14: 195989 | GG14: 961747 | GH14: 464521 | GI14: 169498 | GJ14: 251568 | GK14: 3597004 | GL14: 364925 | GM14: 146096 | GN14: 107779 | GO14: 39701 | GQ14: 238039 | GR14: 140 | GS14: 13248774 | GU14: 5245634 | GW14: 14164 | GX14: 38565 | GY14: 18547137 | GZ14: 2334314 | HB14: 4353754 | HC14: 11859069 | HD14: 18547137 | HE14: 3872269 | HI14: 1009522 | HJ14: 5750647 | HL14: 3079463 | HM14: 9839632 | HN14: -4593998 | HR14: 4353754 | HT14: 1.46 | HU14: 3408098.4 | HV14: 1955 | HW14: 0 | HX14: 37309 | HY14: 44652 | HZ14: 85048 | IA14: 0 | IB14: 0 | IC14: 3841 | IE14: 7436 | IF14: 12688 | IG14: 5909 | IH14: 19141 | II14: 8960 | IJ14: 4326 | IK14: 5429 | IL14: 20748 | IM14: 257442 | IN14: 0 | IO14: 1151 | IP14: 0 | IQ14: 0 | IR14: 0 | IS14: 0 | IT14: 1151 | IU14: 152974 | IV14: 0 | IW14: 2076113 | IX14: 2081124 | IY14: 2588785 | IZ14: 0 | JA14: 0 | JB14: 142293 | JD14: 258385 | JE14: 288632 | JF14: 129344 | JG14: 523021 | JH14: 336663 | JI14: 117747 | JJ14: 193940 | JK14: 909966 | JL14: 9798987 | JM14: 0 | JN14: 68699 | JO14: 0 | JP14: 0 | JQ14: 0 | JR14: 0 | JS14: 68699 | KF14: 168 | KG14: 221 | KH14: 146 | KI14: 113 | KJ14: 157 | KK14: 95 | KL14: 50 | KM14: 64 | KN14: 47 | KO14: 1 | KP14: 0 | KQ14: 0 | KR14: 0 | KS14: 1 | KT14: 0 | KU14: 1 | KV14: 0 | KW14: 0 | KX14: 0 | KY14: 1 | KZ14: 0 | LA14: 0 | LB14: 0 | LC14: 0 | LD14: 1 | LE14: 0 | LF14: 0 | LG14: 0 | LH14: 0
A15: 206010815 | B15: CRESTWOOD TREATMENT CENTER - FREMONT | C15: 45292 | D15: 45657 | E15: 366 | F15: In Process | G15: No | H15: Alameda | I15: SNF | J15: Investor Owned | K15: 05 - East Bay | L15: 0421 | M15: 510-793-8383 | N15: 2171 MOWRY AVENUE | O15: FREMONT | P15: 94538 | Q15: 1942228838 | R15: KULBINDER HANS | S15: Yes | T15: CRESTWOOD BEHAVIORAL HEALTH, INC. | U15: 88 | V15: 88 | W15: 60-99 | X15: 32208 | Y15: 20446 | Z15: 63.48 | AA15: 45 | AB15: 39 | AE15: 1033 | AF15: 19249 | AJ15: 164 | AK15: Skilled Nursing Care Only | AL15: 20446 | AU15: 9390700 | AV15: 13817 | AW15: -3509756 | AX15: 15191 | AY15: 12929464 | AZ15: 13074156 | BA15: -144692 | BB15: 492186 | BE15: 347494 | BH15: 474280 | BI15: 8842330 | BM15: 74090 | BN15: 9390700 | CA15: 812 | CC15: 13005 | CM15: 0 | CN15: 0 | CO15: 0 | CP15: 0 | CQ15: 0 | CR15: 0 | CS15: 1745 | CT15: 8598 | CV15: 3474 | EG15: -3615230 | EI15: 100562 | EO15: 4912 | FG15: 6651306 | FH15: 2692871 | FI15: 3729979 | FJ15: 184580 | FK15: 4848547 | FZ15: 12983 | GA15: 8590 | GC15: 616553 | GD15: 592589 | GE15: 828549 | GF15: 143225 | GG15: 1278861 | GH15: 128286 | GI15: 988826 | GJ15: 107260 | GK15: 2383904 | GL15: 268087 | GM15: 789006 | GN15: 26063 | GO15: 24949 | GQ15: 27790 | GR15: 88 | GS15: 2715112 | GU15: 1248474 | GY15: 3963586 | GZ15: 1489217 | HC15: 2474369 | HD15: 3963586 | HG15: 380555 | HI15: 0 | HK15: 2713922 | HL15: 1471236 | HM15: 4185158 | HN15: -2936684 | HT15: 0 | HU15: 0 | HV15: 1719 | HW15: 0 | HX15: 10531 | HY15: 19880 | HZ15: 68262 | IA15: 0 | IB15: 0 | IC15: 0 | ID15: 10902 | IE15: 5922 | IF15: 25311 | IG15: 3709 | IH15: 28178 | II15: 1792 | IJ15: 29867 | IK15: 1748 | IL15: 12720 | IM15: 220541 | IN15: 0 | IO15: 0 | IP15: 0 | IQ15: 0 | IR15: 0 | IS15: 0 | IT15: 0 | IU15: 106388 | IV15: 0 | IW15: 540811 | IX15: 802212 | IY15: 1941358 | IZ15: 0 | JA15: 0 | JB15: 0 | JC15: 394307 | JD15: 183120 | JE15: 558830 | JF15: 82060 | JG15: 667820 | JH15: 91394 | JI15: 686709 | JJ15: 74899 | JK15: 521398 | JL15: 6651306 | JM15: 0 | JN15: 0 | JO15: 0 | JP15: 0 | JQ15: 0 | JR15: 0 | JS15: 0 | JY15: 10902 | KE15: 394307 | KF15: 117 | KG15: 123 | KH15: 110 | KI15: 56 | KJ15: 59 | KK15: 52 | KL15: 31 | KM15: 34 | KN15: 27 | KO15: 1 | KP15: 0 | KQ15: 0 | KR15: 0 | KS15: 1 | KT15: 0 | KU15: 1 | KV15: 0 | KW15: 0 | KX15: 0 | KY15: 0 | KZ15: 0 | LA15: 0 | LB15: 0 | LC15: 0 | LD15: 1 | LE15: 0 | LF15: 0 | LG15: 0 | LH15: 0
A16: 206010824 | B16: WINDSOR POST ACUTE CARE CENTER OF HAYWARD | C16: 45292 | D16: 45657 | E16: 366 | F16: In Process | G16: No | H16: Alameda | I16: SNF | J16: Investor Owned | K16: 05 - East Bay | L16: 0421 | M16: 510-782-8424 | N16: 25919 GADING ROAD | O16: HAYWARD | P16: 94544 | Q16: 1417275959 | R16: PRESTON FOO | S16: Yes | T16: WINDSOR HAYSAC HOLDINGS, LLC | U16: 99 | V16: 99 | W16: 60-99 | X16: 36234 | Y16: 32226 | Z16: 211.37 | AA16: 511 | AB16: 485 | AC16: 2339 | AD16: 256 | AE16: 4030 | AF16: 16158 | AH16: 7372 | AI16: 93 | AJ16: 1978 | AK16: Skilled Nursing Care Only | AL16: 32226 | AU16: 11343552 | AV16: 2160379 | AW16: -1680420 | AX16: 15434 | AY16: 15199785 | AZ16: 15802048 | BA16: -602263 | BB16: 1590549 | BE16: 988286 | BF16: 823328 | BG16: 90112 | BH16: 1418560 | BI16: 5687616 | BK16: 2594944 | BL16: 32736 | BM16: 696256 | BN16: 11343552 | BW16: 464464 | CA16: 9375 | CC16: 60689 | CG16: 1620547 | CI16: 2929 | CK16: 2375 | CM16: 5603 | CN16: 581 | CO16: 854175 | CP16: 0 | CQ16: 837675 | CR16: 128680 | CS16: 258585 | CT16: 44543 | CV16: 30537 | DY16: -112979 | EC16: -1209774 | EG16: 103171 | EI16: 757917 | EM16: -1306709 | EO16: 87954 | FG16: 5985677 | FH16: 1215202 | FI16: 8601169 | FJ16: 137702 | FK16: 5701625 | FT16: 7388 | FU16: 2721 | FV16: 449496 | FX16: 451608 | FY16: 58435 | FZ16: 256601 | GA16: 48804 | GC16: 37315 | GD16: 509714 | GE16: 336511 | GF16: 221055 | GG16: 929933 | GH16: 87235 | GI16: 92360 | GJ16: 55115 | GK16: 3516214 | GL16: 281737 | GM16: 1745803 | GN16: 141101 | GO16: 57402 | GQ16: 96195 | GR16: 717680 | GS16: 5547872 | GU16: 532471 | GV16: 11258 | GW16: 3132105 | GX16: 14297648 | GY16: 23521354 | GZ16: 9524864 | HB16: 13603584 | HC16: 392906 | HD16: 23521354 | HF16: 3019602 | HG16: 6497258 | HI16: 105962 | HK16: 1307140 | HL16: 268782 | HM16: 1681884 | HN16: -1149413 | HP16: 13399421 | HR16: 13603584 | HT16: 0.01 | HU16: 95248.64 | HV16: 1968 | HW16: 0 | HX16: 14211 | HY16: 25962 | HZ16: 72511 | IA16: 0 | IB16: 0 | IC16: 3814 | IE16: 2870 | IH16: 18882 | II16: 1961 | IJ16: 3399 | IK16: 929 | IL16: 16040 | IM16: 162547 | IN16: 0 | IO16: 0 | IP16: 0 | IQ16: 0 | IR16: 0 | IS16: 0 | IT16: 0 | IU16: 170966 | IV16: 0 | IW16: 857829 | IX16: 1227084 | IY16: 2160275 | IZ16: 0 | JA16: 0 | JB16: 180839 | JD16: 84441 | JG16: 406876 | JH16: 59074 | JI16: 73399 | JJ16: 46467 | JK16: 718427 | JL16: 5985677 | JM16: 0 | JN16: 0 | JO16: 0 | JP16: 0 | JQ16: 0 | JR16: 0 | JS16: 0 | KF16: 95 | KG16: 158 | KH16: 60 | KI16: 64 | KJ16: 104 | KK16: 42 | KL16: 36 | KM16: 52 | KN16: 28 | KO16: 1 | KP16: 0 | KQ16: 0 | KR16: 0 | KS16: 1 | KT16: 0 | KU16: 1 | KV16: 0 | KW16: 0 | KX16: 0 | KY16: 0 | KZ16: 0 | LA16: 0 | LB16: 0 | LC16: 0 | LD16: 1 | LE16: 0 | LF16: 0 | LG16: 0 | LH16: 0
A17: 206010825 | B17: THE VINEYARDS HEALTHCARE CENTER | C17: 45292 | D17: 45657 | E17: 366 | F17: In Process | G17: No | H17: Alameda | I17: SNF | J17: Investor Owned | K17: 05 - East Bay | L17: 0419 | M17: 925-443-1800 | N17: 75 FENTON ST | O17: LIVERMORE | P17: 94550 | Q17: 1477077816 | R17: LISA FOSTER | S17: Yes | U17: 83 | V17: 83 | W17: 60-99 | X17: 30378 | Y17: 28075 | Z17: 218.23 | AA17: 434 | AB17: 423 | AC17: 5171 | AE17: 3166 | AF17: 13965 | AH17: 4624 | AI17: 197 | AJ17: 952 | AK17: Skilled Nursing Care Only | AL17: 28075 | AU17: 11416062 | AV17: 3525033 | AW17: 38563 | AX17: 55463 | AY17: 14957995 | AZ17: 13874810 | BA17: 1083185 | BB17: -18710 | BC17: 13390 | BE17: 1051085 | BF17: 2102670 | BH17: 1287382 | BI17: 5678550 | BK17: 1880245 | BL17: 80106 | BM17: 387109 | BN17: 11416062 | BW17: 649258 | CA17: 397515 | CC17: 1753414 | CG17: 580580 | CI17: 24735 | CK17: 119531 | CM17: 45093 | CN17: 58225 | CO17: 1202475 | CP17: 104030 | CQ17: 1255467 | CR17: 148797 | CS17: 635879 | CT17: 45005 | CV17: 30062 | EC17: -9074287 | EG17: 1166946 | EI17: 5678550 | EM17: 1880245 | EO17: 387109 | FG17: 6171311 | FH17: 1789565 | FI17: 5913934 | FJ17: 174616 | FK17: 5362995 | FT17: 21106 | FU17: 26700 | FV17: 512258 | FW17: 18864 | FX17: 357851 | FY17: 74644 | FZ17: 307284 | GA17: 25171 | GC17: 33358 | GD17: 420049 | GE17: 272434 | GF17: 81521 | GG17: 1001432 | GH17: 180135 | GI17: 177890 | GJ17: 226931 | GK17: 2930077 | GL17: 223576 | GM17: 1224398 | GN17: 109195 | GO17: 41026 | GR17: 245915 | GS17: 7042545 | GU17: 536003 | GV17: 30000 | GW17: 16418839 | GY17: 24027387 | GZ17: 9179286 | HB17: 9691165 | HC17: 5156936 | HD17: 24027387 | HF17: 6813973 | HI17: 0 | HK17: 662451 | HL17: 151952 | HM17: 814403 | HN17: -278400 | HP17: 9577211 | HR17: 9691165 | HT17: 0.37 | HU17: 3396335.8 | HV17: 1686 | HW17: 0 | HX17: 6077 | HY17: 23364 | HZ17: 67418 | IA17: 0 | IB17: 0 | IC17: 4900 | ID17: 12496 | IE17: 2460 | IF17: 8797 | IG17: 2120 | IH17: 18573 | II17: 5163 | IJ17: 5507 | IK17: 3638 | IL17: 13797 | IM17: 175996 | IN17: 0 | IO17: 8 | IP17: 2583 | IQ17: 318 | IR17: 0 | IS17: 0 | IT17: 2909 | IU17: 148434 | IV17: 0 | IW17: 332616 | IX17: 1033006 | IY17: 1955294 | IZ17: 0 | JA17: 0 | JB17: 300631 | JC17: 712070 | JD17: 67724 | JE17: 185833 | JF17: 44835 | JG17: 496519 | JH17: 96548 | JI17: 134583 | JJ17: 176662 | JK17: 486556 | JL17: 6171311 | JM17: 0 | JN17: 840 | JO17: 187180 | JP17: 14302 | JQ17: 0 | JR17: 0 | JS17: 202322 | JY17: 12496 | KE17: 712070 | KF17: 156 | KG17: 225 | KH17: 117 | KI17: 113 | KJ17: 157 | KK17: 87 | KL17: 58 | KM17: 77 | KN17: 46 | KO17: 1 | KP17: 0 | KQ17: 0 | KR17: 0 | KS17: 1 | KT17: 0 | KU17: 1 | KV17: 0 | KW17: 0 | KX17: 0 | KY17: 0 | KZ17: 0 | LA17: 0 | LB17: 0 | LC17: 0 | LD17: 1 | LE17: 0 | LF17: 0 | LG17: 0 | LH17: 0
A18: 206010831 | B18: SAGE POST ACUTE | C18: 45292 | D18: 45657 | E18: 366 | F18: In Process | G18: No | H18: Alameda | I18: SNF | J18: Investor Owned | K18: 05 - East Bay | L18: 0421 | M18: 510-538-3866 | N18: 1832 B. STREET | O18: HAYWARD | P18: 94541-3140 | Q18: 1518282490 | R18: SELVINA ANBURAJ | S18: No | U18: 99 | V18: 99 | W18: 60-99 | X18: 36234 | Y18: 21457 | AC18: 464 | AD18: 3192 | AE18: 1312 | AF18: 14202 | AH18: 565 | AJ18: 1722 | AK18: Skilled Nursing Care Only | AL18: 21457 | AU18: 7941646 | AV18: 713671 | AW18: 1025861 | AY18: 7629456 | AZ18: 8957347 | BA18: -1327891 | BB18: 891459 | BE18: -436432 | BF18: 171475 | BG18: 1058217 | BH18: 5722500 | BI18: 367704 | BM18: 621750 | BN18: 7941646 | BW18: 150391 | CA18: 199527 | CC18: 357913 | CK18: 5840 | CM18: 0 | CN18: 0 | CO18: 300187 | CP18: 0 | CQ18: 245400 | CR18: 20350 | CS18: 121897 | CT18: 22846 | CV18: 2991 | EC18: -177030 | EG18: 1577713 | EI18: -374822 | FG18: 3903093 | FH18: 944563 | FI18: 4109691 | FJ18: 216521 | FK18: 3584732 | FV18: 301581 | FX18: 241110 | FY18: 22056 | FZ18: 88576 | GA18: 26701 | GC18: 8134 | GD18: 453879 | GE18: 412505 | GF18: 69010 | GG18: 608078 | GH18: 57809 | GI18: 239982 | GJ18: 84562 | GK18: 2087633 | GL18: 14803 | GM18: 523912 | GN18: 91502 | GO18: 40782 | GS18: 4057388 | GU18: 113358 | GY18: 4170746 | GZ18: 4798745 | HC18: -627999 | HD18: 4170746 | HH18: 3114657 | HI18: 0 | HK18: 271898 | HL18: 650973 | HM18: 922871 | HN18: -809513 | HR18: 3114657 | HS18: -3114657 | HT18: 0.10 | HU18: 479874.5 | HV18: 2080 | HW18: 0 | HX18: 10724 | HY18: 13387 | HZ18: 48097 | IA18: 0 | IB18: 0 | IC18: 3915 | IE18: 2293 | IF18: 19571 | IG18: 2676 | IH18: 14229 | II18: 1892 | IJ18: 8663 | IK18: 1705 | IL18: 13348 | IM18: 142580 | IN18: 0 | IO18: 31 | IP18: 3189 | IQ18: 11868 | IR18: 0 | IS18: 0 | IT18: 15088 | IU18: 101273 | IV18: 0 | IW18: 482587 | IX18: 441763 | IY18: 1058148 | IZ18: 0 | JA18: 0 | JB18: 169755 | JD18: 61901 | JE18: 319984 | JF18: 49512 | JG18: 339926 | JH18: 43509 | JI18: 190587 | JJ18: 69902 | JK18: 574246 | JL18: 3903093 | JM18: 0 | JN18: 1680 | JO18: 143511 | JP18: 356048 | JQ18: 0 | JR18: 0 | JS18: 501239 | KF18: 83 | KG18: 107 | KH18: 60 | KI18: 33 | KJ18: 48 | KK18: 19 | KL18: 25 | KM18: 37 | KN18: 13 | KO18: 1 | KP18: 0 | KQ18: 0 | KR18: 0 | KS18: 1 | KT18: 0 | KU18: 1 | KV18: 0 | KW18: 0 | KX18: 0 | KY18: 0 | KZ18: 0 | LA18: 0 | LB18: 0 | LC18: 0 | LD18: 1 | LE18: 0 | LF18: 0 | LG18: 0 | LH18: 0
A19: 206010832 | B19: HAYWARD HILLS HEALTH CARE CENTER | C19: 45292 | D19: 45657 | E19: 366 | F19: In Process | G19: No | H19: Alameda | I19: SNF | J19: Investor Owned | K19: 05 - East Bay | L19: 0421 | M19: 510-538-4424 | N19: 1768 B STREET | O19: HAYWARD | P19: 94541 | Q19: 1801868302 | R19: KATHLEEN LOVATO | S19: Yes | T19: NATIONAL SENIOR CARE, INC. | U19: 74 | V19: 74 | W19: 60-99 | X19: 27084 | Y19: 24863 | Z19: 154.83 | AA19: 118 | AB19: 111 | AC19: 2666 | AD19: 1389 | AE19: 3012 | AF19: 17491 | AI19: 7 | AJ19: 298 | AK19: Skilled Nursing Care Only | AL19: 24863 | AU19: 11422008 | AV19: 3299135 | AW19: 3276025 | AX19: 8 | AY19: 11445126 | AZ19: 12164183 | BA19: -719057 | BB19: 6606 | BE19: -712451 | BF19: 1241113 | BG19: 634938 | BH19: 1399584 | BI19: 8008087 | BL19: 3386 | BM19: 134900 | BN19: 11422008 | BW19: 2201727 | BY19: 1052976 | CA19: 6920 | CC19: 36486 | CI19: 176 | CK19: 850 | CM19: 0 | CN19: 0 | CO19: 1647567 | CP19: 0 | CQ19: 1260375 | CR19: 117400 | CS19: 197127 | CT19: 72758 | CV19: 3908 | EC19: 576668 | EE19: 696548 | EG19: 278748 | EI19: 1698096 | EO19: 25968 | FE19: -3 | FG19: 3924193 | FH19: 1544377 | FI19: 6695613 | FJ19: 130294 | FK19: 5335369 | FT19: 45963 | FU19: -1569 | FV19: 326104 | FW19: 2458 | FX19: 263540 | FY19: 16255 | FZ19: 102116 | GA19: 46285 | GC19: 29824 | GD19: 427148 | GE19: 373793 | GF19: 159728 | GG19: 852371 | GH19: 97819 | GI19: 161314 | GK19: 2356886 | GL19: 79591 | GM19: 918447 | GN19: 80711 | GO19: 213587 | GP19: 47407 | GR19: 229036 | GS19: 2698870 | GU19: 790670 | GV19: 1149956 | GW19: 187792 | GY19: 4827288 | GZ19: 1960160 | HA19: 246047 | HC19: 2621081 | HD19: 4827288 | HG19: -168422 | HI19: 0 | HJ19: 2445783 | HK19: 819440 | HL19: 804462 | HM19: 4069685 | HN19: -3279015 | HT19: 0.00 | HU19: 0 | HV19: 3508 | HW19: 0 | HX19: 10141 | HY19: 17291 | HZ19: 33593 | IA19: 0 | IB19: 0 | IC19: 2798 | IE19: 1129 | IF19: 10355 | IG19: 5275 | IH19: 17377 | II19: 1848 | IJ19: 4826 | IL19: 11538 | IM19: 119679 | IN19: 0 | IO19: 942 | IP19: 4719 | IQ19: 29623 | IR19: 0 | IS19: 0 | IT19: 35284 | IU19: 246157 | IV19: 0 | IW19: 572058 | IX19: 792224 | IY19: 917945 | IZ19: 0 | JA19: 0 | JB19: 106649 | JD19: 36952 | JE19: 227036 | JF19: 102280 | JG19: 401310 | JH19: 71165 | JI19: 111123 | JK19: 339294 | JL19: 3924193 | JM19: 0 | JN19: 73365 | JO19: 323717 | JP19: 1081337 | JQ19: 0 | JR19: 0 | JS19: 1478419 | KF19: 91 | KG19: 121 | KH19: 79 | KI19: 50 | KJ19: 70 | KK19: 41 | KL19: 26 | KM19: 36 | KN19: 22 | KO19: 1 | KP19: 0 | KQ19: 0 | KR19: 0 | KS19: 1 | KT19: 0 | KU19: 1 | KV19: 0 | KW19: 0 | KX19: 0 | KY19: 0 | KZ19: 0 | LA19: 0 | LB19: 0 | LC19: 0 | LD19: 1 | LE19: 0 | LF19: 0 | LG19: 0 | LH19: 0
A20: 206010845 | B20: REDWOOD HEALTHCARE CENTER | C20: 45292 | D20: 45657 | E20: 366 | F20: In Process | G20: No | H20: Alameda | I20: SNF | J20: Investor Owned | K20: 05 - East Bay | L20: 0417 | M20: 510-533-9970 | N20: 3145 HIGH STREET | O20: OAKLAND | P20: 94619 | Q20: 1184173056 | R20: EVA CHAVARRIA | S20: Yes | U20: 44 | V20: 44 | W20: 1-59 | X20: 16104 | Y20: 15651 | Z20: 228.02 | AA20: 84 | AB20: 85 | AC20: 2330 | AD20: 243 | AE20: 1447 | AF20: 11087 | AH20: 140 | AI20: 5 | AJ20: 399 | AK20: Skilled Nursing Care Only | AL20: 15651 | AU20: 5764228 | AV20: 591652 | AW20: -1195822 | AX20: 6987 | AY20: 7558689 | AZ20: 7537813 | BA20: 20876 | BB20: 4738 | BC20: 25180 | BE20: 434 | BF20: 891934 | BG20: 80812 | BH20: 615932 | BI20: 3979025 | BK20: 46558 | BL20: 1910 | BM20: 148057 | BN20: 5764228 | BW20: 480360 | BY20: 38697 | CA20: 10968 | CC20: 35770 | CG20: 22295 | CI20: 251 | CK20: 3311 | CM20: 131 | CN20: 1447 | CO20: 154852 | CP20: 0 | CQ20: 277843 | CR20: 83269 | CS20: 66922 | CT20: 4756 | CV20: 2432 | EC20: -1172705 | EE20: -40289 | EG20: 32137 | EI20: 2285 | EM20: -23212 | EO20: 5962 | FG20: 3419203 | FH20: 915781 | FI20: 3202829 | FJ20: 156501 | FK20: 3170747 | FT20: 486 | FU20: 4783 | FV20: 128240 | FX20: 161214 | FY20: 48946 | FZ20: 67648 | GA20: 5649 | GC20: 4630 | GD20: 285645 | GE20: 182957 | GF20: 125179 | GG20: 534899 | GH20: 157281 | GI20: 104640 | GJ20: 110020 | GK20: 1901233 | GL20: 20519 | GM20: 366256 | GN20: 37231 | GO20: 7836 | GR20: 111774 | GS20: 1967951 | GU20: 50602 | GV20: 8250 | GW20: 2884019 | GX20: 459270 | GY20: 5370092 | GZ20: 3555272 | HC20: 1814820 | HD20: 5370092 | HF20: 2807056 | HI20: 0 | HK20: 27382 | HL20: 77642 | HM20: 105024 | HN20: -54422 | HT20: 0.00 | HU20: 0 | HV20: 2157 | HW20: 0 | HX20: 6679 | HY20: 14223 | HZ20: 41584 | IA20: 0 | IB20: 0 | IC20: 1696 | IE20: 2141 | IH20: 12304 | II20: 2565 | IJ20: 3955 | IK20: 1985 | IL20: 8799 | IM20: 98088 | IN20: 0 | IO20: 0 | IP20: 0 | IQ20: 0 | IR20: 0 | IS20: 0 | IT20: 0 | IU20: 168874 | IV20: 0 | IW20: 379127 | IX20: 635289 | IY20: 1117734 | IZ20: 0 | JA20: 0 | JB20: 84792 | JD20: 73101 | JG20: 271554 | JH20: 107562 | JI20: 79453 | JJ20: 91523 | JK20: 410194 | JL20: 3419203 | JM20: 0 | JN20: 0 | JO20: 0 | JP20: 0 | JQ20: 0 | JR20: 0 | JS20: 0 | KF20: 61 | KG20: 79 | KH20: 44 | KI20: 43 | KJ20: 54 | KK20: 32 | KL20: 23 | KM20: 26 | KN20: 18 | KO20: 1 | KP20: 0 | KQ20: 0 | KR20: 1 | KS20: 0 | KT20: 0 | KU20: 1 | KV20: 0 | KW20: 0 | KX20: 0 | KY20: 0 | KZ20: 0 | LA20: 0 | LB20: 0 | LC20: 0 | LD20: 1 | LE20: 0 | LF20: 0 | LG20: 0 | LH20: 0
A21: 206010848 | B21: OAKLAND HEALTHCARE AND WELLNESS CENTER | C21: 45170 | D21: 45535 | E21: 366 | F21: In Process | G21: No | H21: Alameda | I21: SNF | J21: Investor Owned | K21: 05 - East Bay | L21: 0417 | M21: 510-250-8000 | N21: 3030 WEBSTER ST | O21: OAKLAND | P21: 94609 | Q21: 16959693745 | R21: SINGH, RUBY BHULLER | S21: Yes | U21: 98 | V21: 98 | W21: 60-99 | X21: 35868 | Y21: 33896 | Z21: 94.5 | AA21: 259 | AB21: 211 | AC21: 4263 | AE21: 3414 | AF21: 22509 | AG21: 1154 | AI21: 73 | AJ21: 2483 | AK21: Skilled Nursing Care Only | AL21: 33896 | AU21: 17347250 | AV21: 4809378 | AW21: 6037176 | AY21: 16119452 | AZ21: 15235798 | BA21: 883654 | BB21: 516643 | BC21: 12590 | BE21: 1387707 | BF21: 3836700 | BH21: 1312350 | BI21: 9590750 | BJ21: 1038600 | BL21: 29650 | BM21: 1539200 | BN21: 17347250 | BW21: 3034003 | CA21: 16757 | CC21: 595786 | CE21: 682170 | CK21: 480662 | CM21: 2390 | CN21: 147252 | CO21: 1178344 | CP21: 0 | CQ21: 1519916 | CR21: 1117721 | CS21: 732259 | CT21: 51886 | CV21: 59610 | EC21: 1668364 | EG21: 387776 | EI21: 2882596 | EK21: 667363 | EO21: 431077 | FG21: 6646665 | FH21: 1758842 | FI21: 6830291 | FJ21: 256429 | FK21: 6458777 | FT21: 9536 | FU21: 68187 | FV21: 254413 | FX21: 334362 | FY21: 126301 | FZ21: 242547 | GA21: 30260 | GC21: 44050 | GD21: 724619 | GE21: 442827 | GF21: 61294 | GG21: 937949 | GH21: 138199 | GI21: 133408 | GJ21: 121299 | GK21: 2984951 | GL21: 92227 | GM21: 1702526 | GN21: 82072 | GO21: 18459 | GQ21: 3624 | GR21: 223911 | GS21: 7863005 | GU21: 252131 | GV21: 379561 | GW21: 13277317 | GY21: 21772014 | GZ21: 17780382 | HC21: 3991632 | HD21: 21772014 | HE21: 3950294 | HG21: 906135 | HI21: 0 | HK21: 867357 | HL21: 626532 | HM21: 1493889 | HN21: -1241758 | HT21: 0.03 | HU21: 533411.46 | HV21: 1872 | HW21: 0 | HX21: 9344 | HY21: 31390 | HZ21: 59845 | IA21: 0 | IB21: 0 | IC21: 5026 | ID21: 9515 | IE21: 1748 | IF21: 16183 | IG21: 1860 | IH21: 19522 | II21: 3809 | IJ21: 4087 | IK21: 1898 | IL21: 15206 | IM21: 181305 | IN21: 0 | IO21: 259 | IP21: 1185 | IQ21: 12298 | IR21: 0 | IS21: 0 | IT21: 13742 | IU21: 181505 | IV21: 0 | IW21: 547716 | IX21: 1461940 | IY21: 1826101 | IZ21: 0 | JA21: 0 | JB21: 250716 | JC21: 460740 | JD21: 60372 | JE21: 298023 | JF21: 33503 | JG21: 439594 | JH21: 109022 | JI21: 106787 | JJ21: 90690 | JK21: 779956 | JL21: 6646665 | JM21: 0 | JN21: 18802 | JO21: 72940 | JP21: 446240 | JQ21: 0 | JR21: 0 | JS21: 537982 | JY21: 9515 | KE21: 460740 | KF21: 133 | KG21: 187 | KH21: 88 | KI21: 74 | KJ21: 104 | KK21: 50 | KL21: 38 | KM21: 56 | KN21: 28 | KO21: 1 | KP21: 0 | KQ21: 0 | KR21: 0 | KS21: 1 | KT21: 0 | KU21: 1 | KV21: 0 | KW21: 0 | KX21: 0 | KY21: 0 | KZ21: 0 | LA21: 0 | LB21: 0 | LC21: 0 | LD21: 1 | LE21: 0 | LF21: 0 | LG21: 0 | LH21: 0
A22: 206010851 | B22: BELLAKEN SKILLED NURSING CENTER | C22: 45292 | D22: 45657 | E22: 366 | F22: In Process | G22: Yes | H22: Alameda | I22: SNF/RES | J22: Investor Owned | K22: 05 - East Bay | L22: 0417 | M22: 510-536-1838 | N22: 2780 26TH AVENUE | O22: OAKLAND | P22: 94601-1911 | Q22: LTC55767F | R22: JEFFREY TONG | S22: Yes | U22: 61 | V22: 61 | W22: 60-99 | X22: 22326 | Y22: 21835 | Z22: 229.46 | AA22: 150 | AB22: 67 | AC22: 3478 | AD22: 52 | AE22: 843 | AF22: 16498 | AI22: 964 | AK22: Skilled Nursing Care Only | AL22: 21835 | AU22: 8412003 | AV22: 2193246 | AW22: 1174639 | AX22: 119563 | AY22: 9550173 | AZ22: 10335157 | BA22: -784984 | BB22: 902433 | BC22: 12 | BE22: 117437 | BF22: 1339030 | BH22: 311651 | BI22: 6387382 | BL22: 373940 | BN22: 8412003 | BW22: 1949282 | CA22: 50974 | CC22: 157829 | CI22: 35161 | CM22: 132242 | CN22: 4837 | CO22: 653544 | CP22: 0 | CQ22: 997002 | CR22: 162770 | CS22: 193113 | CT22: 29357 | CV22: 20381 | EC22: -639032 | EG22: 140347 | EI22: 1673324 | FG22: 5387062 | FH22: 945337 | FI22: 6402716 | FJ22: 59734 | FK22: 4079568 | FT22: 16257 | FU22: 2469 | FV22: 176248 | FX22: 281280 | FY22: 36360 | FZ22: 64877 | GA22: 13397 | GC22: 10337 | GD22: 528586 | GE22: 250977 | GF22: 85881 | GG22: 406094 | GH22: 147166 | GI22: 110111 | GJ22: 43857 | GK22: 1790160 | GL22: 44799 | GM22: 2111829 | GN22: 31508 | GO22: 37116 | GR22: 66280 | GS22: 3487413 | GU22: 297116 | GV22: 29661 | GW22: 4805 | GY22: 3818995 | GZ22: 1581599 | HC22: 2237396 | HD22: 3818995 | HI22: 324694 | HK22: 575259 | HL22: 643758 | HM22: 1543711 | HN22: -1246595 | HT22: 1.10 | HU22: 1739758.9 | HV22: 1991 | HW22: 0 | HX22: 6089 | HY22: 18858 | HZ22: 54286 | IA22: 0 | IB22: 0 | IC22: 7885 | IE22: 3233 | IF22: 9858 | IG22: 3626 | IH22: 10650 | II22: 4180 | IJ22: 3609 | IK22: 624 | IL22: 15316 | IM22: 140205 | IN22: 0 | IO22: 979 | IP22: 996 | IQ22: 3350 | IR22: 0 | IS22: 0 | IT22: 5325 | IU22: 104241 | IV22: 0 | IW22: 576574 | IX22: 775661 | IY22: 1347914 | IZ22: 0 | JA22: 0 | JB22: 211141 | JD22: 166008 | JE22: 197346 | JF22: 66628 | JG22: 217546 | JH22: 123492 | JI22: 88431 | JJ22: 35964 | JK22: 592975 | JL22: 4503921 | JM22: 0 | JN22: 107009 | JO22: 57506 | JP22: 123700 | JQ22: 0 | JR22: 0 | JS22: 288215 | KF22: 99 | KG22: 126 | KH22: 71 | KI22: 51 | KJ22: 68 | KK22: 28 | KL22: 32 | KM22: 47 | KN22: 12 | KO22: 1 | KP22: 0 | KQ22: 0 | KR22: 0 | KS22: 1 | KT22: 0 | KU22: 1 | KV22: 0 | KW22: 0 | KX22: 0 | KY22: 0 | KZ22: 0 | LA22: 0 | LB22: 0 | LC22: 0 | LD22: 0 | LE22: 0 | LF22: 1 | LG22: 0 | LH22: 0
A23: 206010854 | B23: ALL SAINTS SUBACUTE & TRANSITIONAL CARE | C23: 45292 | D23: 45657 | E23: 366 | F23: In Process | G23: No | H23: Alameda | I23: SNF | J23: Investor Owned | K23: 05 - East Bay | L23: 0421 | M23: 510-481-3200 | N23: 1652 MONO AVE | O23: SAN LEANDRO | P23: 94578-0000 | Q23: 1205213204 | R23: KALEB HATCH | S23: Yes | U23: 70 | V23: 70 | W23: 60-99 | X23: 25620 | Y23: 23299 | Z23: 209.34 | AA23: 99 | AB23: 112 | AC23: 1782 | AD23: 865 | AE23: 3097 | AF23: 16577 | AI23: 299 | AJ23: 679 | AK23: Mixed Care | AL23: 7406 | AP23: 15893 | AU23: 42962350 | AV23: 2229042 | AW23: 30050542 | AX23: 6521 | AY23: 15147371 | AZ23: 18125456 | BA23: -2978085 | BB23: -4 | BE23: -2978089 | BF23: 2380500 | BG23: 1713600 | BH23: 5895850 | BI23: 31005200 | BL23: 627900 | BM23: 1339300 | BN23: 10328250 | BR23: 32634100 | BW23: 900589 | BY23: 378048 | CA23: 166354 | CC23: 740847 | CI23: 1870 | CK23: 41334 | CM23: 67873 | CN23: 98360 | CO23: 327360 | CP23: 981207 | CQ23: 179235 | CR23: 123600 | CS23: 395707 | CT23: 34450 | CV23: 21250 | EC23: 606196 | EE23: 484358 | EG23: 4803473 | EI23: 23029277 | EO23: 1127238 | FG23: 8612145 | FH23: 2372834 | FI23: 7140477 | FJ23: 301544 | FK23: 1962881 | FO23: 6432855 | FT23: 31830 | FU23: 16863 | FV23: 157809 | FW23: 1136835 | FX23: 56591 | FY23: 37660 | FZ23: 121388 | GA23: 20547 | GC23: 100711 | GD23: 443732 | GE23: 532607 | GF23: 151372 | GG23: 681822 | GH23: 67569 | GI23: 210818 | GJ23: 114673 | GK23: 4414728 | GL23: 29120 | GM23: 974205 | GN23: 91897 | GO23: 48401 | GQ23: 9404 | GR23: 279138 | GS23: 5134034 | GU23: 149864 | GY23: 5283898 | GZ23: 4989698 | HC23: 294200 | HD23: 5283898 | HG23: 1190323 | HI23: 0 | HK23: 179619 | HL23: 133525 | HM23: 313144 | HN23: -163280 | HT23: 0.00 | HU23: 0 | HV23: 1721 | HW23: 0 | HX23: 31347 | HY23: 51074 | HZ23: 62348 | IA23: 0 | IB23: 0 | IC23: 0 | ID23: 18903 | IE23: 2420 | IF23: 18169 | IG23: 4731 | IH23: 11489 | II23: 1608 | IJ23: 4447 | IK23: 1734 | IL23: 16987 | IM23: 226978 | IN23: 0 | IO23: 0 | IP23: 1472 | IQ23: 11177 | IR23: 0 | IS23: 0 | IT23: 12649 | IU23: 165900 | IV23: 0 | IW23: 1615950 | IX23: 2244527 | IY23: 1750480 | IZ23: 0 | JA23: 0 | JB23: 0 | JC23: 829678 | JD23: 50749 | JE23: 362547 | JF23: 97857 | JG23: 334054 | JH23: 53959 | JI23: 148443 | JJ23: 87349 | JK23: 870652 | JL23: 8612145 | JM23: 0 | JN23: 0 | JO23: 92288 | JP23: 423934 | JQ23: 0 | JR23: 0 | JS23: 516222 | JY23: 18903 | KE23: 829678 | KF23: 134 | KG23: 297 | KH23: 64 | KI23: 99 | KJ23: 243 | KK23: 39 | KL23: 37 | KM23: 76 | KN23: 21 | KO23: 1 | KP23: 0 | KQ23: 0 | KR23: 0 | KS23: 1 | KT23: 0 | KU23: 1 | KV23: 0 | KW23: 0 | KX23: 0 | KY23: 1 | KZ23: 0 | LA23: 0 | LB23: 0 | LC23: 0 | LD23: 1 | LE23: 0 | LF23: 0 | LG23: 0 | LH23: 0
A24: 206010855 | B24: JONES CONVALESCENT HOSPITAL | C24: 45292 | D24: 45657 | E24: 366 | F24: In Process | G24: Yes | H24: Alameda | I24: SNF/RES | J24: Investor Owned | K24: 05 - East Bay | L24: 0421 | M24: 510-483-6200 | N24: 524 CALLAN AVENUE | O24: SAN LEANDRO | P24: 94577 | Q24: 1659495604 | R24: DELLA DE LEON | S24: Yes | U24: 25 | V24: 25 | W24: 1-59 | X24: 9150 | Y24: 8504 | Z24: 213.94 | AA24: 66 | AB24: 67 | AC24: 354 | AD24: 116 | AE24: 962 | AF24: 5715 | AH24: 656 | AI24: 373 | AJ24: 328 | AK24: Skilled Nursing Care Only | AL24: 8504 | AU24: 3271148 | AV24: 235633 | AW24: 320924 | AX24: 434 | AY24: 3186291 | AZ24: 3839969 | BA24: -653678 | BB24: 551071 | BC24: -5994 | BE24: -96613 | BF24: 136170 | BG24: 44620 | BH24: 370043 | BI24: 2198332 | BK24: 252337 | BL24: 143478 | BM24: 126168 | BN24: 3271148 | BW24: 72014 | BY24: 12295 | CA24: 1520 | CC24: 35999 | CG24: 108543 | CI24: 4378 | CK24: 884 | CM24: 11428 | CN24: 1291 | CO24: 94528 | CP24: 0 | CQ24: 50960 | CR24: 4663 | CS24: 48578 | CT24: 17459 | CV24: 6726 | EC24: -92403 | EE24: -8245 | EG24: 42248 | EI24: 751462 | EM24: -219509 | EO24: -152629 | FG24: 1690512 | FH24: 313804 | FI24: 1835653 | FJ24: 37458 | FK24: 1359755 | FS24: 244879 | FT24: 8875 | FV24: 66394 | FX24: 31734 | FY24: 7575 | FZ24: 31993 | GA24: 12204 | GC24: 4925 | GD24: 253447 | GE24: 82565 | GF24: 47333 | GG24: 394079 | GH24: 43413 | GI24: 57037 | GJ24: 16098 | GK24: 807601 | GL24: 20429 | GM24: 308100 | GN24: 20931 | GO24: 8256 | GR24: 12346 | GS24: 1600339 | GU24: 69678 | GY24: 1670017 | GZ24: 617067 | HC24: 1052950 | HD24: 1670017 | HI24: 0 | HK24: 224196 | HL24: 240858 | HM24: 465054 | HN24: -395376 | HT24: 1.39 | HU24: 857723.13 | HV24: 2024 | HW24: 0 | HX24: 2025 | HY24: 6424 | HZ24: 17733 | IA24: 0 | IB24: 0 | IC24: 0 | IE24: 1021 | IF24: 2262 | IG24: 2262 | IH24: 9814 | II24: 907 | IJ24: 1843 | IK24: 335 | IL24: 4101 | IM24: 50751 | IN24: 0 | IO24: 0 | IP24: 1206 | IQ24: 3463 | IR24: 0 | IS24: 0 | IT24: 4669 | IU24: 144654 | IV24: 0 | IW24: 99007 | IX24: 273018 | IY24: 427073 | IZ24: 0 | JA24: 0 | JB24: 0 | JD24: 32216 | JE24: 42617 | JF24: 42617 | JG24: 197694 | JH24: 31831 | JI24: 39494 | JJ24: 13500 | JK24: 174237 | JL24: 1517958 | JM24: 0 | JN24: 0 | JO24: 64364 | JP24: 113220 | JQ24: 0 | JR24: 0 | JS24: 177584 | KF24: 38 | KG24: 82 | KH24: 22 | KI24: 17 | KJ24: 29 | KK24: 13 | KL24: 9 | KM24: 16 | KN24: 7 | KO24: 1 | KP24: 0 | KQ24: 0 | KR24: 1 | KS24: 0 | KT24: 0 | KU24: 1 | KV24: 0 | KW24: 0 | KX24: 0 | KY24: 0 | KZ24: 0 | LA24: 0 | LB24: 0 | LC24: 0 | LD24: 0 | LE24: 0 | LF24: 1 | LG24: 0 | LH24: 0
A25: 206010863 | B25: KYAKAMEENA CARE CENTER | C25: 45292 | D25: 45657 | E25: 366 | F25: In Process | G25: No | H25: Alameda | I25: SNF | J25: Investor Owned | K25: 05 - East Bay | L25: 0415 | M25: 510-843-2131 | N25: 2131 CARLETON STREET | O25: BERKELEY | P25: 94704 | Q25: 1912072554 | R25: SEYNA SMITH | S25: Yes | U25: 60 | V25: 60 | W25: 60-99 | X25: 21960 | Y25: 20505 | Z25: 214.94 | AA25: 191 | AB25: 196 | AC25: 641 | AD25: 334 | AE25: 1052 | AF25: 13973 | AH25: 2734 | AI25: 75 | AJ25: 1696 | AK25: Skilled Nursing Care Only | AL25: 20505 | AU25: 7751710 | AV25: 821190 | AW25: 718844 | AX25: 1813 | AY25: 7855869 | AZ25: 7959291 | BA25: -103422 | BB25: 81235 | BC25: -106849 | BE25: 84662 | BF25: 242324 | BG25: 126265 | BH25: 397698 | BI25: 5282353 | BK25: 1033561 | BL25: 28353 | BM25: 641156 | BN25: 7751710 | BW25: 175780 | BY25: 43202 | CA25: 47842 | CC25: 70275 | CG25: 478775 | CI25: 3231 | CK25: 2085 | CM25: 15657 | CN25: 764 | CO25: 233645 | CP25: 0 | CQ25: 247773 | CR25: 51440 | CS25: 225294 | CT25: 29734 | CV25: 16883 | EC25: -332577 | EE25: 10105 | EG25: -22670 | EI25: 1646205 | EM25: -339648 | EO25: -242571 | FG25: 2854494 | FH25: 822525 | FI25: 4282272 | FJ25: 76984 | FK25: 3506440 | FT25: 11628 | FU25: 8154 | FV25: 165572 | FX25: 163502 | FY25: 31486 | FZ25: 150156 | GA25: 18784 | GC25: 11100 | GD25: 246599 | GE25: 202448 | GF25: 112627 | GG25: 645923 | GH25: 155965 | GI25: 133130 | GJ25: 32842 | GK25: 1764841 | GL25: 60494 | GM25: 360000 | GN25: 58049 | GO25: 10744 | GR25: 108807 | GS25: 4236442 | GU25: 126003 | GW25: 4150 | GY25: 4366595 | GZ25: 1078899 | HC25: 3287696 | HD25: 4366595 | HI25: 0 | HK25: 248818 | HL25: 248619 | HM25: 497437 | HN25: -371434 | HT25: 2.20 | HU25: 2373577.8 | HV25: 1939 | HW25: 0 | HX25: 6782 | HY25: 11473 | HZ25: 25200 | IA25: 0 | IB25: 0 | IC25: 1945 | IE25: 2007 | IF25: 5167 | IG25: 3565 | IH25: 13652 | II25: 4273 | IJ25: 3583 | IK25: 579 | IL25: 6959 | IM25: 87124 | IN25: 0 | IO25: 765 | IP25: 3238 | IQ25: 27377 | IR25: 0 | IS25: 0 | IT25: 31380 | IU25: 134575 | IV25: 0 | IW25: 358718 | IX25: 512217 | IY25: 613563 | IZ25: 0 | JA25: 0 | JB25: 106495 | JD25: 53986 | JE25: 103371 | JF25: 77312 | JG25: 316388 | JH25: 130843 | JI25: 74076 | JJ25: 26668 | JK25: 346282 | JL25: 2854494 | JM25: 0 | JN25: 51566 | JO25: 175009 | JP25: 939961 | JQ25: 0 | JR25: 0 | JS25: 1166536 | KF25: 50 | KG25: 104 | KH25: 31 | KI25: 25 | KJ25: 75 | KK25: 16 | KL25: 15 | KM25: 47 | KN25: 8 | KO25: 1 | KP25: 0 | KQ25: 0 | KR25: 0 | KS25: 1 | KT25: 0 | KU25: 1 | KV25: 0 | KW25: 0 | KX25: 0 | KY25: 0 | KZ25: 0 | LA25: 0 | LB25: 0 | LC25: 0 | LD25: 1 | LE25: 0 | LF25: 0 | LG25: 0 | LH25: 0
A26: 206010866 | B26: LAKE PARK HEALTHCARE CENTER | C26: 45292 | D26: 45657 | E26: 366 | F26: In Process | G26: No | H26: Alameda | I26: SNF | J26: Investor Owned | K26: 05 - East Bay | L26: 0417 | M26: 510-835-5511 | N26: 1850 ALICE STREET | O26: OAKLAND | P26: 94612 | Q26: 1023759362 | R26: ADAM BROWN | S26: Yes | U26: 35 | V26: 35 | W26: 1-59 | X26: 12810 | Y26: 8107 | Z26: 144.77 | AA26: 236 | AB26: 226 | AC26: 5198 | AD26: 1278 | AI26: 1631 | AK26: Skilled Nursing Care Only | AL26: 8107 | AU26: 4151006 | AV26: 2436052 | AW26: -1535701 | AX26: 308 | AY26: 8123067 | AZ26: 6381797 | BA26: 1741270 | BB26: 1 | BE26: 1741271 | BF26: 2662800 | BG26: 650406 | BL26: 837800 | BN26: 4151006 | BW26: 1913954 | BY26: 520619 | CI26: 1479 | CM26: 41739 | CN26: 979 | CO26: 784500 | CP26: 0 | CQ26: 830300 | CR26: 124800 | CS26: 565653 | CT26: 40717 | CV26: 47364 | EC26: -1342818 | EE26: -193314 | EO26: 431 | FG26: 2210314 | FH26: 434664 | FI26: 3736819 | FJ26: 48581 | FK26: 2129869 | FT26: 8285 | FV26: 288909 | FX26: 234352 | FY26: 36646 | FZ26: 196683 | GA26: 24339 | GC26: 24526 | GD26: 236480 | GE26: 76011 | GF26: 52554 | GG26: 422847 | GH26: 126680 | GI26: 63087 | GJ26: 82349 | GK26: 1543664 | GL26: 17928 | GM26: 527775 | GN26: 95314 | GO26: 24253 | GR26: 169246 | GS26: 1594196 | GU26: 131253 | GV26: 4387 | GW26: 916875 | GX26: 6807840 | GY26: 9454551 | GZ26: 745851 | HB26: 6841915 | HC26: 1866785 | HD26: 9454551 | HF26: 864375 | HI26: 0 | HK26: 70755 | HL26: 83441 | HM26: 154196 | HN26: -22943 | HR26: 6841915 | HT26: 0 | HU26: 0 | HV26: 2088 | HW26: 0 | HX26: 6420 | HY26: 4352 | HZ26: 16987 | IA26: 0 | IB26: 0 | IC26: 2073 | ID26: 5778 | IH26: 1093 | II26: 1974 | IJ26: 1591 | IK26: 1233 | IL26: 7528 | IM26: 51117 | IN26: 0 | IO26: 79 | IP26: 2716 | IQ26: 6762 | IR26: 0 | IS26: 0 | IT26: 9557 | IU26: 164924 | IV26: 0 | IW26: 380431 | IX26: 224794 | IY26: 457029 | IZ26: 0 | JA26: 0 | JB26: 134523 | JC26: 304542 | JG26: 43501 | JH26: 52613 | JI26: 43041 | JJ26: 70301 | JK26: 334615 | JL26: 2210314 | JM26: 0 | JN26: 4340 | JO26: 122208 | JP26: 236675 | JQ26: 0 | JR26: 0 | JS26: 363223 | JY26: 5778 | KE26: 304542 | KF26: 36 | KG26: 66 | KH26: 17 | KI26: 29 | KJ26: 54 | KK26: 14 | KL26: 14 | KM26: 25 | KN26: 8 | KO26: 1 | KP26: 0 | KQ26: 0 | KR26: 1 | KS26: 0 | KT26: 0 | KU26: 1 | KV26: 0 | KW26: 0 | KX26: 0 | KY26: 0 | KZ26: 0 | LA26: 0 | LB26: 0 | LC26: 0 | LD26: 1 | LE26: 0 | LF26: 0 | LG26: 0 | LH26: 0
A27: 206010874 | B27: AVONDALE VILLA POST-ACUTE | C27: 45292 | D27: 45657 | E27: 366 | F27: In Process | G27: No | H27: Alameda | I27: SNF | J27: Investor Owned | K27: 05 - East Bay | L27: 0419 | M27: 925-447-2280 | N27: 788 HOLMES ST | O27: LIVERMORE | P27: 94550 | Q27: 1255963781 | R27: ISABEL PODEROSO | S27: Yes | U27: 37 | V27: 37 | W27: 1-59 | X27: 13542 | Y27: 12253 | Z27: 213.65 | AA27: 141 | AB27: 140 | AC27: 3502 | AE27: 820 | AF27: 5326 | AH27: 947 | AI27: 594 | AJ27: 1064 | AK27: Skilled Nursing Care Only | AL27: 12253 | AU27: 4305301 | AV27: 1272972 | AW27: -1354375 | AX27: 26261 | AY27: 6958909 | AZ27: 6001490 | BA27: 957419 | BB27: -4525 | BC27: 18380 | BE27: 934514 | BF27: 1230487 | BH27: 288121 | BI27: 1871381 | BK27: 332745 | BL27: 208712 | BM27: 373855 | BN27: 4305301 | BW27: 363825 | CA27: 85191 | CC27: 553320 | CG27: 98385 | CI27: 61711 | CK27: 110540 | CM27: 8557 | CN27: 30965 | CO27: 437531 | CP27: 6912 | CQ27: 487182 | CR27: 56178 | CS27: 201364 | CT27: 23272 | CV27: 21011 | DY27: 1 | EC27: -4182997 | EG27: 250640 | EI27: 1871381 | EM27: 332745 | EO27: 373855 | FG27: 2794923 | FH27: 629747 | FI27: 2576820 | FJ27: 66136 | FK27: 2478733 | FT27: 4083 | FU27: 17561 | FV27: 130147 | FW27: 5942 | FX27: 114040 | FY27: 19938 | FZ27: 112869 | GA27: 11636 | GC27: 11255 | GD27: 184591 | GE27: 239845 | GF27: 10383 | GG27: 551560 | GH27: 74041 | GI27: 36451 | GJ27: 44483 | GK27: 1265142 | GL27: 138699 | GM27: 332400 | GN27: 16003 | GO27: 9460 | GR27: 192228 | GS27: 3778432 | GU27: 6629 | GW27: 2317122 | GY27: 6102183 | GZ27: 1478257 | HB27: 2314074 | HC27: 2309852 | HD27: 6102183 | HE27: 2360174 | HG27: 921071 | HI27: 0 | HL27: 30321 | HM27: 30321 | HN27: -23692 | HO27: 2314074 | HR27: 2314074 | HT27: 0.02 | HU27: 29565.14 | HV27: 1626 | HW27: 0 | HX27: 3068 | HY27: 9460 | HZ27: 26650 | IA27: 0 | IB27: 0 | IC27: 3244 | ID27: 8928 | IE27: 911 | IF27: 6809 | IG27: 27 | IH27: 11293 | II27: 6298 | IJ27: 635 | IK27: 1409 | IL27: 4896 | IM27: 85254 | IN27: 0 | IO27: 0 | IP27: 589 | IQ27: 1763 | IR27: 0 | IS27: 0 | IT27: 2352 | IU27: 147822 | IV27: 0 | IW27: 171968 | IX27: 413125 | IY27: 875767 | IZ27: 0 | JA27: 0 | JB27: 128219 | JC27: 237359 | JD27: 22948 | JE27: 166053 | JF27: 674 | JG27: 313623 | JH27: 34596 | JI27: 24211 | JJ27: 33107 | JK27: 225451 | JL27: 2794923 | JM27: 0 | JN27: 0 | JO27: 30753 | JP27: 92783 | JQ27: 0 | JR27: 0 | JS27: 123536 | JY27: 8928 | KE27: 237359 | KF27: 60 | KG27: 69 | KH27: 50 | KI27: 40 | KJ27: 46 | KK27: 33 | KL27: 27 | KM27: 29 | KN27: 25 | KO27: 1 | KP27: 0 | KQ27: 0 | KR27: 1 | KS27: 0 | KT27: 0 | KU27: 1 | KV27: 0 | KW27: 0 | KX27: 0 | KY27: 0 | KZ27: 0 | LA27: 0 | LB27: 0 | LC27: 0 | LD27: 1 | LE27: 0 | LF27: 0 | LG27: 0 | LH27: 0
A28: 206010875 | B28: LAKE MERRITT HEALTHCARE CENTER | C28: 45292 | D28: 45657 | E28: 366 | F28: In Process | G28: No | H28: Alameda | I28: SNF | J28: Investor Owned | K28: 05 - East Bay | L28: 0417 | M28: 510-836-3770 | N28: 309 MACARTHUR BOULEVARD | O28: OAKLAND | P28: 94610 | Q28: 1801345772 | R28: EVA CHAVARRIA | S28: Yes | U28: 53 | V28: 53 | W28: 1-59 | X28: 19398 | Y28: 17981 | Z28: 217.48 | AA28: 106 | AB28: 109 | AC28: 2892 | AD28: 130 | AE28: 990 | AF28: 12897 | AH28: 247 | AJ28: 825 | AK28: Skilled Nursing Care Only | AL28: 17981 | AU28: 6183701 | AV28: 695152 | AW28: -2059456 | AX28: 3395 | AY28: 8941704 | AZ28: 8642272 | BA28: 299432 | BB28: -23780 | BC28: 12590 | BE28: 263062 | BF28: 989649 | BG28: 43823 | BH28: 342730 | BI28: 4322295 | BK28: 83265 | BL28: 122244 | BM28: 279695 | BN28: 6183701 | BW28: 552180 | BY28: 28759 | CA28: 4528 | CC28: 54716 | CG28: 54642 | CK28: 327 | CM28: 576 | CN28: 0 | CO28: 180906 | CP28: 0 | CQ28: 293553 | CR28: 128029 | CS28: 83157 | CT28: 5757 | CV28: 3174 | EC28: -1439128 | EE28: -9261 | EG28: -26229 | EI28: -540995 | EM28: -17595 | EO28: -26248 | FG28: 3962195 | FH28: 1011170 | FI28: 3668907 | FJ28: 177066 | FK28: 3596471 | FT28: 4657 | FU28: 3896 | FV28: 112989 | FX28: 146583 | FY28: 76128 | FZ28: 126308 | GA28: 7543 | GC28: 8891 | GD28: 298028 | GE28: 176089 | GF28: 120630 | GG28: 629529 | GH28: 62624 | GI28: 114229 | GJ28: 130307 | GK28: 2335711 | GL28: 66676 | GM28: 438727 | GN28: 42638 | GO28: 11328 | GR28: 132290 | GS28: 2408003 | GU28: 110792 | GV28: 8250 | GW28: 2865190 | GX28: 517251 | GY28: 5909486 | GZ28: 3805782 | HC28: 2103704 | HD28: 5909486 | HF28: 2779513 | HI28: 0 | HK28: 173524 | HL28: 90224 | HM28: 263748 | HN28: -152956 | HT28: 0.00 | HU28: 0 | HV28: 1861 | HW28: 0 | HX28: 7205 | HY28: 14623 | HZ28: 48391 | IA28: 0 | IB28: 0 | IC28: 5469 | IE28: 1488 | IH28: 13774 | II28: 1815 | IJ28: 3714 | IK28: 2224 | IL28: 10582 | IM28: 111146 | IN28: 0 | IO28: 0 | IP28: 0 | IQ28: 0 | IR28: 0 | IS28: 0 | IT28: 0 | IU28: 142257 | IV28: 0 | IW28: 418439 | IX28: 684025 | IY28: 1317593 | IZ28: 0 | JA28: 0 | JB28: 224069 | JD28: 45161 | JG28: 309735 | JH28: 50862 | JI28: 88040 | JJ28: 106794 | JK28: 575220 | JL28: 3962195 | JM28: 0 | JN28: 0 | JO28: 0 | JP28: 0 | JQ28: 0 | JR28: 0 | JS28: 0 | KF28: 81 | KG28: 102 | KH28: 47 | KI28: 57 | KJ28: 71 | KK28: 34 | KL28: 32 | KM28: 38 | KN28: 23 | KO28: 1 | KP28: 0 | KQ28: 0 | KR28: 1 | KS28: 0 | KT28: 0 | KU28: 1 | KV28: 0 | KW28: 0 | KX28: 0 | KY28: 0 | KZ28: 0 | LA28: 0 | LB28: 0 | LC28: 0 | LD28: 1 | LE28: 0 | LF28: 0 | LG28: 0 | LH28: 0
A29: 206010876 | B29: HAYWARD GARDENS POST ACUTE | C29: 45292 | D29: 45657 | E29: 366 | F29: In Process | G29: No | H29: Alameda | I29: SNF | J29: Investor Owned | K29: 05 - East Bay | L29: 0421 | M29: 510582463 | N29: 1628 B STREET | O29: HAYWARD | P29: 94541 | Q29: 1417663105 | R29: STEVE STOCK | S29: Yes | U29: 75 | V29: 75 | W29: 60-99 | X29: 27450 | Y29: 25410 | Z29: 211.75 | AA29: 491 | AB29: 491 | AC29: 3413 | AD29: 6851 | AE29: 1610 | AF29: 12329 | AI29: 293 | AJ29: 914 | AK29: Skilled Nursing Care Only | AL29: 25410 | AU29: 18416097 | AV29: 3107288 | AW29: 6975536 | AX29: 12658 | AY29: 14560507 | AZ29: 14469633 | BA29: 90874 | BB29: -2 | BE29: 90872 | BF29: 1890184 | BG29: 6847612 | BH29: 950881 | BI29: 8066111 | BL29: 116687 | BM29: 544622 | BN29: 18416097 | BW29: 965740 | BY29: 2122995 | CA29: 11345 | CC29: 6858 | CI29: 350 | CM29: 31132 | CN29: 0 | CO29: 1029122 | CP29: 0 | CQ29: 846760 | CR29: 171190 | CS29: 894502 | CT29: 78042 | CV29: 56540 | EC29: -971910 | EE29: 4946137 | EG29: 401454 | EI29: 2381165 | EO29: 218690 | FG29: 5609154 | FH29: 1524506 | FI29: 7335973 | FJ29: 102004 | FK29: 5740836 | FT29: 16884 | FV29: 598414 | FX29: 394680 | FY29: 44076 | FZ29: 320078 | GA29: 97372 | GC29: 56229 | GD29: 492029 | GE29: 263170 | GF29: 162303 | GG29: 845025 | GH29: 58378 | GI29: 122005 | GJ29: 109467 | GK29: 2948444 | GL29: 17608 | GM29: 1530930 | GN29: 79964 | GO29: 23001 | GQ29: 10222 | GR29: 538518 | GS29: 2473141 | GU29: 75776 | GY29: 2548917 | GZ29: 2001727 | HC29: 547190 | HD29: 2548917 | HG29: 562211 | HI29: 0 | HK29: 39885 | HL29: 64205 | HM29: 104090 | HN29: -28314 | HT29: 0 | HU29: 0 | HV29: 2036 | HW29: 0 | HX29: 15356 | HY29: 24218 | HZ29: 47196 | IA29: 0 | IB29: 0 | IC29: 0 | ID29: 9281 | IE29: 3976 | IH29: 16952 | II29: 1682 | IJ29: 4051 | IK29: 1487 | IL29: 16328 | IM29: 142563 | IN29: 0 | IO29: 47 | IP29: 1305 | IQ29: 16588 | IR29: 0 | IS29: 0 | IT29: 17940 | IU29: 225964 | IV29: 0 | IW29: 954053 | IX29: 1144917 | IY29: 1284280 | IZ29: 0 | JA29: 0 | JB29: 0 | JC29: 577676 | JD29: 93556 | JG29: 413471 | JH29: 47761 | JI29: 82188 | JJ29: 79768 | JK29: 705520 | JL29: 5609154 | JM29: 0 | JN29: 3415 | JO29: 78238 | JP29: 640589 | JQ29: 0 | JR29: 0 | JS29: 722242 | JY29: 9281 | KE29: 577676 | KF29: 78 | KG29: 143 | KH29: 42 | KI29: 55 | KJ29: 111 | KK29: 26 | KL29: 26 | KM29: 58 | KN29: 12 | KO29: 1 | KP29: 0 | KQ29: 0 | KR29: 0 | KS29: 1 | KT29: 0 | KU29: 1 | KV29: 0 | KW29: 0 | KX29: 0 | KY29: 0 | KZ29: 0 | LA29: 0 | LB29: 0 | LC29: 0 | LD29: 1 | LE29: 0 | LF29: 0 | LG29: 0 | LH29: 0
A30: 206010879 | B30: MASONIC HOME | C30: 45231 | D30: 45596 | E30: 366 | F30: In Process | G30: No | H30: Alameda | I30: SNF | J30: Not-for-Profit | K30: 05 - East Bay | L30: 0421 | M30: 510-471-3434 | N30: 34400 MISSION BLVD. | O30: UNION CITY | P30: 94587-3604 | Q30: 1043426588 | R30: CYNTHIA CRUZ | S30: No | U30: 125 | V30: 125 | W30: 100+ | X30: 45750 | Y30: 22466 | Z30: 49.11 | AA30: 319 | AB30: 347 | AC30: 3736 | AD30: 950 | AE30: 3882 | AF30: 8935 | AG30: 6 | AI30: 3883 | AJ30: 1074 | AK30: Skilled Nursing Care Only | AL30: 22466 | AU30: 9542599 | AV30: 4395857 | AW30: 384843 | AX30: 333877 | AY30: 13887490 | AZ30: 23675435 | BA30: -9787945 | BB30: 115603774 | BE30: 105815829 | BF30: 2180167 | BH30: 4623306 | BI30: 352577 | BJ30: 2670 | BL30: 1875829 | BM30: 508050 | BN30: 9542599 | BW30: 1860081 | CE30: 2535776 | CM30: 6779 | CN30: 0 | CO30: 733556 | CP30: 0 | CQ30: 562289 | CR30: 148951 | CS30: 2893974 | CT30: 38793 | CV30: 11515 | EC30: -679192 | EG30: 552827 | EK30: 502414 | EO30: 8794 | FG30: 8740725 | FH30: 4575262 | FI30: 10359448 | FJ30: 536043 | FK30: 10613398 | FT30: 175943 | FV30: 785350 | FX30: 217665 | FY30: 30422 | FZ30: 3275046 | GA30: 55046 | GC30: 148605 | GD30: 1446729 | GE30: 672064 | GF30: 468482 | GG30: 1378577 | GH30: 135795 | GI30: 103387 | GK30: 1213594 | GL30: 2481121 | GM30: 64896 | GN30: 97890 | GO30: 311425 | GS30: 61170514 | GT30: 932572669 | GU30: 194977210 | GV30: 5324576 | GW30: 23394216 | GY30: 1217439185 | GZ30: 59077063 | HB30: 41949485 | HC30: 1116412637 | HD30: 1217439185 | HG30: 35500250 | HI30: 46455233 | HJ30: 287841966 | HK30: 244541 | HL30: 31278235 | HM30: 365819975 | HN30: -170842765 | HR30: 41949485 | HT30: 0.08 | HU30: 4726165 | HV30: 2703 | HW30: 0 | HX30: 26177 | HY30: 49617 | HZ30: 93360 | IA30: 0 | IB30: 0 | IC30: 5911 | ID30: 16454 | IE30: 10597 | IF30: 16379 | IG30: 12308 | II30: 2588 | IJ30: 1594 | IL30: 6585 | IM30: 244273 | IN30: 0 | IO30: 2 | IP30: 724 | IQ30: 2120 | IR30: 0 | IS30: 0 | IT30: 2846 | IU30: 237506 | IV30: 0 | IW30: 1461574 | IX30: 2039331 | IY30: 2585956 | IZ30: 0 | JA30: 0 | JB30: 310942 | JC30: 734228 | JD30: 310922 | JE30: 362562 | JF30: 236113 | JH30: 89192 | JI30: 39721 | JK30: 332678 | JL30: 8740725 | JM30: 0 | JN30: 140 | JO30: 40835 | JP30: 85995 | JQ30: 0 | JR30: 0 | JS30: 126970 | JY30: 16454 | KE30: 734228 | KF30: 91 | KG30: 394 | KH30: 91 | KI30: 77 | KJ30: 230 | KK30: 77 | KL30: 41 | KM30: 153 | KN30: 41 | KO30: 0 | KP30: 1 | KQ30: 0 | KR30: 0 | KS30: 0 | KT30: 1 | KU30: 1 | KV30: 0 | KW30: 0 | KX30: 0 | KY30: 0 | KZ30: 0 | LA30: 0 | LB30: 0 | LC30: 0 | LD30: 1 | LE30: 0 | LF30: 0 | LG30: 0 | LH30: 0
A31: 206010881 | B31: MCCLURE POST ACUTE | C31: 45292 | D31: 45657 | E31: 366 | F31: In Process | G31: No | H31: Alameda | I31: SNF | J31: Investor Owned | K31: 05 - East Bay | L31: 0417 | M31: 510-836-3677 | N31: 2910 MCCLURE ST | O31: OAKLAND | P31: 94609-0000 | Q31: 1396122297 | R31: ANDREW SNIDER | S31: Yes | U31: 60 | V31: 60 | W31: 60-99 | X31: 21960 | Y31: 20463 | Z31: 218.62 | AA31: 319 | AB31: 315 | AC31: 6317 | AD31: 5090 | AE31: 1718 | AF31: 6933 | AI31: 209 | AJ31: 196 | AK31: Skilled Nursing Care Only | AL31: 20463 | AU31: 17394185 | AV31: 4892815 | AW31: 6274777 | AX31: 21622 | AY31: 16033845 | AZ31: 12737716 | BA31: 3296129 | BB31: -1 | BE31: 3296128 | BF31: 7896250 | BG31: 6362500 | BH31: 581210 | BI31: 2417000 | BL31: 70895 | BM31: 66330 | BN31: 17394185 | BW31: 3191706 | BY31: 1677602 | CA31: 6550 | CC31: 16957 | CM31: 0 | CN31: 0 | CO31: 1357720 | CP31: 0 | CQ31: 2113325 | CR31: 729585 | CS31: 610590 | CT31: 66127 | CV31: 15468 | EC31: 2419277 | EE31: 3942204 | EG31: -65421 | EI31: -21625 | EO31: 342 | FG31: 5236617 | FH31: 1361555 | FI31: 6139544 | FJ31: 89575 | FK31: 4434917 | FV31: 544747 | FX31: 433865 | FY31: 184081 | FZ31: 285655 | GA31: 42504 | GC31: 132986 | GD31: 570462 | GE31: 345695 | GF31: 66442 | GG31: 679367 | GH31: 123924 | GI31: 83512 | GJ31: 120075 | GK31: 3441362 | GL31: 62958 | GM31: 835033 | GN31: 65017 | GO31: 50284 | GQ31: 8178 | GR31: 226652 | GS31: 31477538 | GU31: 430637 | GY31: 31908175 | GZ31: 2037714 | HC31: 29870461 | HD31: 31908175 | HE31: 29080391 | HI31: 0 | HK31: 309996 | HL31: 491504 | HM31: 801500 | HN31: -370863 | HT31: 0.03 | HU31: 61131.42 | HV31: 2043 | HW31: 0 | HX31: 8860 | HY31: 18764 | HZ31: 53615 | IA31: 0 | IB31: 0 | IC31: 0 | ID31: 4802 | IE31: 3077 | IF31: 11389 | IG31: 1934 | IH31: 12998 | II31: 2008 | IJ31: 1140 | IK31: 2044 | IL31: 7550 | IM31: 130224 | IN31: 0 | IO31: 0 | IP31: 0 | IQ31: 0 | IR31: 0 | IS31: 0 | IT31: 0 | IU31: 316719 | IV31: 0 | IW31: 503976 | IX31: 865380 | IY31: 1420890 | IZ31: 0 | JA31: 0 | JB31: 0 | JC31: 332880 | JD31: 122388 | JE31: 225554 | JF31: 35497 | JG31: 262137 | JH31: 71626 | JI31: 36648 | JJ31: 99119 | JK31: 943803 | JL31: 5236617 | JM31: 0 | JN31: 0 | JO31: 0 | JP31: 0 | JQ31: 0 | JR31: 0 | JS31: 0 | JY31: 4802 | KE31: 332880 | KF31: 73 | KG31: 129 | KH31: 42 | KI31: 48 | KJ31: 88 | KK31: 26 | KL31: 29 | KM31: 47 | KN31: 18 | KO31: 1 | KP31: 0 | KQ31: 0 | KR31: 0 | KS31: 1 | KT31: 0 | KU31: 1 | KV31: 0 | KW31: 0 | KX31: 0 | KY31: 0 | KZ31: 0 | LA31: 0 | LB31: 0 | LC31: 0 | LD31: 1 | LE31: 0 | LF31: 0 | LG31: 0 | LH31: 0
A32: 206010889 | B32: FRUITVALE HEALTHCARE CENTER | C32: 45292 | D32: 45657 | E32: 366 | F32: In Process | G32: No | H32: Alameda | I32: SNF | J32: Investor Owned | K32: 05 - East Bay | L32: 0417 | M32: 510-261-5613 | N32: 3020 EAST 15TH STREET | O32: OAKLAND | P32: 94601 | Q32: 1144856535 | R32: NICHOLAS PERSINGER | S32: Yes | T32: NATIONAL SENIOR CARE, INC. | U32: 140 | V32: 140 | W32: 100+ | X32: 51240 | Y32: 46854 | Z32: 154.23 | AA32: 164 | AB32: 153 | AC32: 1629 | AD32: 3693 | AE32: 4435 | AF32: 35269 | AI32: 67 | AJ32: 1761 | AK32: Skilled Nursing Care Only | AL32: 46854 | AU32: 19281387 | AV32: 6577031 | AW32: 7062880 | AY32: 18795538 | AZ32: 19995214 | BA32: -1199676 | BB32: 7615 | BE32: -1192061 | BF32: 673499 | BG32: 1550144 | BH32: 1783522 | BI32: 14526213 | BL32: 27592 | BM32: 720417 | BN32: 19281387 | BW32: 3937843 | BY32: 2450750 | CA32: 32470 | CC32: 150117 | CK32: 5851 | CM32: 0 | CN32: 0 | CO32: 2890202 | CP32: 543 | CQ32: 2508240 | CR32: 914040 | CS32: 219863 | CT32: 34095 | CV32: 10048 | EC32: 2201358 | EE32: 1514586 | EG32: 429703 | EI32: 2788408 | EO32: 128824 | FE32: 1 | FG32: 6217057 | FH32: 2551574 | FI32: 11226583 | FJ32: 200834 | FK32: 8900535 | FT32: 53521 | FV32: 505445 | FW32: 9670 | FX32: 448476 | FY32: 169130 | FZ32: 108740 | GA32: 39081 | GC32: 22940 | GD32: 558974 | GE32: 562449 | GF32: 210167 | GG32: 1262401 | GH32: 156698 | GI32: 190874 | GK32: 4439897 | GL32: 74711 | GM32: 1648543 | GN32: 151513 | GO32: 101455 | GP32: 3931 | GR32: 376063 | GS32: 6874408 | GU32: 3427408 | GV32: 13676 | GW32: 266798 | GX32: 781954 | GY32: 11364244 | GZ32: 14281926 | HB32: 1452115 | HC32: -4369797 | HD32: 11364244 | HE32: 1884211 | HG32: 9563215 | HI32: 13030 | HJ32: 6167926 | HL32: 115258 | HM32: 6296214 | HN32: -2868806 | HR32: 1452115 | HT32: 0 | HU32: 0 | HV32: 5872 | HW32: 0 | HX32: 12033 | HY32: 27435 | HZ32: 69302 | IA32: 0 | IB32: 0 | IC32: 3914 | IE32: 1649 | IF32: 16501 | IG32: 6621 | IH32: 22795 | II32: 2934 | IJ32: 5941 | IL32: 15424 | IM32: 190421 | IN32: 0 | IO32: 1328 | IP32: 7335 | IQ32: 57540 | IR32: 0 | IS32: 0 | IT32: 66203 | IU32: 416412 | IV32: 0 | IW32: 685661 | IX32: 1274230 | IY32: 1813336 | IZ32: 0 | JA32: 0 | JB32: 151701 | JD32: 44640 | JE32: 353599 | JF32: 129267 | JG32: 521707 | JH32: 112147 | JI32: 130688 | JK32: 583669 | JL32: 6217057 | JM32: 0 | JN32: 84666 | JO32: 398509 | JP32: 2023010 | JQ32: 0 | JR32: 0 | JS32: 2506185 | KF32: 157 | KG32: 185 | KH32: 131 | KI32: 99 | KJ32: 114 | KK32: 85 | KL32: 60 | KM32: 68 | KN32: 53 | KO32: 1 | KP32: 0 | KQ32: 0 | KR32: 0 | KS32: 0 | KT32: 1 | KU32: 1 | KV32: 0 | KW32: 0 | KX32: 0 | KY32: 0 | KZ32: 0 | LA32: 0 | LB32: 0 | LC32: 0 | LD32: 1 | LE32: 0 | LF32: 0 | LG32: 0 | LH32: 0
A33: 206010900 | B33: GARFIELD NEUROBEHAVIORAL CENTER | C33: 45108 | D33: 45473 | E33: 366 | F33: In Process | G33: No | H33: Alameda | I33: SNF | J33: Investor Owned | K33: 05 - East Bay | L33: 0417 | M33: 510-261-9191 | N33: 1451 - 28TH STREET | O33: OAKLAND | P33: 94601-0000 | Q33: LTC90070F | R33: CRAIG DANBY | S33: Yes | T33: TELECARE CORPORATION | U33: 96 | V33: 96 | W33: 60-99 | X33: 35136 | Y33: 21982 | Z33: 62.56 | AA33: 11 | AB33: 11 | AE33: 491 | AF33: 21491 | AK33: Skilled Nursing Care Only | AL33: 21982 | AU33: 19913400 | AV33: 27052 | AW33: 9861451 | AY33: 10079001 | AZ33: 9842951 | BA33: 236050 | BB33: 1999507 | BE33: 2235557 | BH33: 441900 | BI33: 19471500 | BN33: 19913400 | CA33: 600 | CC33: 26452 | CM33: 0 | CN33: 0 | CO33: 0 | CP33: 0 | CQ33: 0 | CR33: 0 | CS33: 0 | CT33: 21719 | CV33: 5333 | EG33: 252460 | EI33: 9608991 | FG33: 4608616 | FH33: 2555714 | FI33: 2678621 | FJ33: 111167 | FK33: 5731287 | FZ33: 10274 | GA33: 21719 | GC33: 5333 | GD33: 388643 | GE33: 270588 | GF33: 120484 | GG33: 1051664 | GI33: 43387 | GJ33: 54865 | GK33: 1974163 | GL33: 120035 | GM33: 16390 | GN33: 29240 | GO33: 4879 | GS33: 2133473 | GT33: 3749 | GU33: 1790077 | GV33: 308645 | GW33: 32275747 | GY33: 36511691 | GZ33: 3776834 | HB33: 543 | HC33: 32734314 | HD33: 36511691 | HF33: 32275747 | HI33: 339630 | HJ33: 5267912 | HL33: 554234 | HM33: 6161776 | HN33: -4371699 | HR33: 543 | HT33: 0.00 | HU33: 0 | HV33: 4083 | HW33: 0 | HX33: 6572 | HY33: 17788 | HZ33: 59812 | IA33: 0 | IB33: 0 | IC33: 34 | IE33: 1822 | IF33: 7832 | IG33: 3313 | IH33: 18863 | IK33: 664 | IL33: 6136 | IM33: 126919 | IN33: 0 | IO33: 0 | IP33: 0 | IQ33: 0 | IR33: 0 | IS33: 0 | IT33: 0 | IU33: 437733 | IV33: 0 | IW33: 501613 | IX33: 913315 | IY33: 1712990 | IZ33: 0 | JA33: 0 | JB33: 2330 | JD33: 66802 | JE33: 158486 | JF33: 72723 | JG33: 431625 | JJ33: 30200 | JK33: 280800 | JL33: 4608617 | JM33: 0 | JN33: 0 | JO33: 0 | JP33: 0 | JQ33: 0 | JR33: 0 | JS33: 0 | KF33: 104 | KG33: 120 | KH33: 89 | KI33: 57 | KJ33: 63 | KK33: 52 | KL33: 36 | KM33: 38 | KN33: 35 | KO33: 1 | KP33: 0 | KQ33: 0 | KR33: 0 | KS33: 1 | KT33: 0 | KU33: 1 | KV33: 0 | KW33: 0 | KX33: 0 | KY33: 0 | KZ33: 0 | LA33: 0 | LB33: 0 | LC33: 0 | LD33: 1 | LE33: 0 | LF33: 0 | LG33: 0 | LH33: 0
A34: 206010904 | B34: BAY MARINA POST ACUTE | C34: 45292 | D34: 45657 | E34: 366 | F34: In Process | G34: No | H34: Alameda | I34: SNF | J34: Investor Owned | K34: 05 - East Bay | L34: 0417 | M34: 510-261-8564 | N34: 2919 FRUITVALE AVENUE | O34: OAKLAND | P34: 94602-2194 | Q34: 1386958965 | R34: THEARTIS ALDRIDGE | S34: Yes | U34: 94 | V34: 94 | W34: 60-99 | X34: 34404 | Y34: 32539 | Z34: 221.9 | AA34: 168 | AB34: 148 | AC34: 2239 | AE34: 1650 | AF34: 26337 | AH34: 1501 | AI34: 1 | AJ34: 811 | AK34: Skilled Nursing Care Only | AL34: 32539 | AU34: 15379890 | AV34: 3590942 | AW34: 4532319 | AY34: 14438513 | AZ34: 15061441 | BA34: -622928 | BB34: 85861 | BC34: 800 | BE34: -537867 | BF34: 2013555 | BH34: 617025 | BI34: 11110920 | BK34: 1335530 | BL34: 385 | BM34: 302475 | BN34: 15379890 | BW34: 1698391 | CA34: 97222 | CC34: 1165269 | CG34: 629440 | CK34: 620 | CM34: 27805 | CN34: 105414 | CO34: 926945 | CP34: 0 | CQ34: 930645 | CR34: 614713 | CS34: 401949 | CT34: 76297 | CV34: 507174 | DY34: -1700 | EC34: 806667 | EG34: 64277 | EI34: 3052117 | EM34: 566301 | EO34: 44657 | FG34: 7001527 | FH34: 1760555 | FI34: 6299359 | FJ34: 356506 | FK34: 6586319 | FT34: 12409 | FU34: 54925 | FV34: 269236 | FX34: 214765 | FY34: 205594 | FZ34: 147270 | GA34: 31485 | GC34: 248255 | GD34: 820011 | GE34: 366532 | GF34: 150558 | GG34: 925914 | GH34: 126484 | GI34: 195613 | GJ34: 135281 | GK34: 2962009 | GL34: 109002 | GM34: 1128203 | GN34: 154645 | GO34: 27541 | GQ34: 2274 | GR34: 187116 | GS34: 4727989 | GU34: 424827 | GX34: 4646168 | GY34: 9798984 | GZ34: 8392229 | HC34: 1406755 | HD34: 9798984 | HE34: 2275175 | HG34: 1103194 | HI34: 0 | HK34: 516694 | HL34: 854879 | HM34: 1371573 | HN34: -946746 | HT34: 0.01 | HU34: 83922.29 | HV34: 2486 | HW34: 0 | HX34: 9232 | HY34: 20042 | HZ34: 86389 | IA34: 0 | IB34: 0 | IC34: 4801 | ID34: 7087 | IE34: 3975 | IF34: 13698 | IG34: 5711 | IH34: 21476 | II34: 2927 | IJ34: 6519 | IK34: 2139 | IL34: 18280 | IM34: 204762 | IN34: 0 | IO34: 1962 | IP34: 2820 | IQ34: 1524 | IR34: 0 | IS34: 0 | IT34: 6306 | IU34: 191634 | IV34: 0 | IW34: 560923 | IX34: 1012279 | IY34: 2503757 | IZ34: 0 | JA34: 0 | JB34: 201684 | JC34: 385884 | JD34: 142202 | JE34: 265536 | JF34: 107551 | JG34: 522870 | JH34: 105749 | JI34: 160713 | JJ34: 109100 | JK34: 731645 | JL34: 7001527 | JM34: 0 | JN34: 154458 | JO34: 172039 | JP34: 56937 | JQ34: 0 | JR34: 0 | JS34: 383434 | JY34: 7087 | KE34: 385884 | KF34: 172 | KG34: 248 | KH34: 117 | KI34: 103 | KJ34: 143 | KK34: 73 | KL34: 65 | KM34: 84 | KN34: 50 | KO34: 1 | KP34: 0 | KQ34: 0 | KR34: 0 | KS34: 1 | KT34: 0 | KU34: 1 | KV34: 0 | KW34: 0 | KX34: 0 | KY34: 0 | KZ34: 0 | LA34: 0 | LB34: 0 | LC34: 0 | LD34: 1 | LE34: 0 | LF34: 0 | LG34: 0 | LH34: 0
A35: 206010906 | B35: EXCELL HEALTH CARE CENTER | C35: 45292 | D35: 45657 | E35: 366 | F35: In Process | G35: No | H35: Alameda | I35: SNF | J35: Investor Owned | K35: 05 - East Bay | L35: 0417 | M35: 512-261-5200 | N35: 3025 HIGH STREET | O35: OAKLAND | P35: 94619 | Q35: 1699345900 | R35: ELMA CONWAY | S35: Yes | U35: 99 | V35: 99 | W35: 60-99 | X35: 36234 | Y35: 34180 | Z35: 214.44 | AA35: 243 | AB35: 273 | AC35: 7146 | AD35: 95 | AE35: 2595 | AF35: 24033 | AI35: 205 | AJ35: 106 | AK35: Skilled Nursing Care Only | AL35: 34180 | AU35: 13504955 | AV35: 7481379 | AW35: 2942194 | AX35: 49820 | AY35: 18093960 | AZ35: 15090667 | BA35: 3003293 | BB35: 992256 | BE35: 3995549 | BF35: 2532725 | BG35: 33898 | BH35: 916479 | BI35: 9897388 | BL35: 80004 | BM35: 44461 | BN35: 13504955 | BW35: 6780724 | BY35: 88378 | CA35: 2250 | CC35: 593286 | CK35: 16741 | CM35: 0 | CN35: 0 | CO35: 3571800 | CP35: 0 | CQ35: 3401950 | CR35: 169700 | CS35: 285539 | CT35: 24744 | CV35: 27646 | EC35: 848993 | EE35: 45051 | EG35: -255743 | EI35: 2326446 | EO35: -22553 | FG35: 8088659 | FH35: 1600678 | FI35: 5401330 | FJ35: 45515 | FK35: 6208176 | FT35: 34606 | FV35: 395493 | FX35: 326048 | FY35: 23595 | FZ35: 229005 | GA35: 32531 | GC35: 40476 | GD35: 585642 | GE35: 355549 | GF35: 162672 | GG35: 1208024 | GH35: 215157 | GI35: 162523 | GJ35: 118481 | GK35: 3798544 | GL35: 9912 | GM35: 1215326 | GN35: 69140 | GQ35: 26174 | GR35: -126407 | GS35: 2568156 | GU35: 598572 | GW35: 6085854 | GY35: 9252582 | GZ35: 1453181 | HC35: 7799401 | HD35: 9252582 | HI35: 0 | HK35: 474448 | HL35: 197005 | HM35: 671453 | HN35: -72881 | HT35: 0.00 | HU35: 0 | HV35: 2080 | HW35: 0 | HX35: 12084 | HY35: 32098 | HZ35: 84498 | IA35: 0 | IB35: 0 | IC35: 4707 | ID35: 11623 | IE35: 4267 | IF35: 11812 | IG35: 6319 | IH35: 22443 | II35: 5794 | IJ35: 4220 | IK35: 2079 | IL35: 16111 | IM35: 220135 | IN35: 0 | IO35: 0 | IP35: 225 | IQ35: 0 | IR35: 0 | IS35: 0 | IT35: 225 | IU35: 260694 | IV35: 0 | IW35: 685560 | IX35: 1398120 | IY35: 2408718 | IZ35: 0 | JA35: 0 | JB35: 239129 | JC35: 620541 | JD35: 132053 | JE35: 264906 | JF35: 115960 | JG35: 506315 | JH35: 181131 | JI35: 108690 | JJ35: 100594 | JK35: 1066247 | JL35: 8088658 | JM35: 0 | JN35: 0 | JO35: 11620 | JP35: 0 | JQ35: 0 | JR35: 0 | JS35: 11620 | JY35: 11623 | KE35: 620541 | KF35: 119 | KG35: 165 | KH35: 86 | KI35: 80 | KJ35: 104 | KK35: 61 | KL35: 45 | KM35: 58 | KN35: 36 | KO35: 1 | KP35: 0 | KQ35: 0 | KR35: 0 | KS35: 1 | KT35: 0 | KU35: 1 | KV35: 0 | KW35: 0 | KX35: 0 | KY35: 0 | KZ35: 0 | LA35: 0 | LB35: 0 | LC35: 0 | LD35: 1 | LE35: 0 | LF35: 0 | LG35: 0 | LH35: 0
A36: 206010912 | B36: WE CARE SKILLED NURSING - FREMONT | C36: 45505 | D36: 45657 | E36: 153 | F36: In Process | G36: No | H36: Alameda | I36: SNF | J36: Investor Owned | K36: 05 - East Bay | L36: 0421 | M36: 510-797-5300 | N36: 2100 PARKSIDE DRIVE | O36: FREMONT | P36: 94536-5326 | Q36: 1205695350 | R36: ALDWIN FAJARDO-PONDER | S36: Yes | U36: 99 | V36: 99 | W36: 60-99 | X36: 15147 | Y36: 10297 | Z36: 64.2 | AA36: 101 | AB36: 85 | AC36: 2104 | AE36: 5712 | AI36: 310 | AJ36: 2171 | AK36: Skilled Nursing Care Only | AL36: 10297 | AU36: 3582099 | AV36: 979399 | AW36: -849895 | AX36: 5199 | AY36: 5416592 | AZ36: 3960645 | BA36: 1455947 | BE36: 1455947 | BF36: 735790 | BH36: 2735719 | BL36: 110590 | BN36: 3582099 | BW36: 575587 | CA36: 399175 | CI36: 4637 | CM36: 0 | CN36: 0 | CO36: 427300 | CP36: 0 | CQ36: 241273 | CR36: 112706 | CS36: 178541 | CT36: 17891 | CV36: 1688 | EC36: -770694 | EG36: -79201 | FG36: 2007151 | FH36: 563678 | FI36: 1389816 | FJ36: 130006 | FK36: 1956675 | FV36: 158811 | FX36: 65126 | FY36: 34345 | FZ36: 121977 | GA36: 7308 | GC36: 2005 | GD36: 152603 | GE36: 146158 | GF36: 22849 | GG36: 280731 | GH36: 23825 | GI36: 45493 | GJ36: 41831 | GK36: 547454 | GM36: 353454 | GS36: 2962545 | GY36: 2962545 | GZ36: 189598 | HC36: 2772947 | HD36: 2962545 | HI36: 0 | HM36: 0 | HN36: 0 | HT36: 0 | HU36: 0 | HV36: 1691 | HW36: 0 | HX36: 3738 | HY36: 6230 | HZ36: 25862 | IA36: 0 | IB36: 0 | IC36: 881 | ID36: 3924 | IE36: 35 | IF36: 7707 | IH36: 7708 | II36: 833 | IJ36: 2247 | IK36: 891 | IL36: 5887 | IM36: 67634 | IN36: 0 | IO36: 0 | IP36: 0 | IQ36: 2357 | IR36: 0 | IS36: 0 | IT36: 2357 | IU36: 73875 | IV36: 0 | IW36: 178790 | IX36: 344837 | IY36: 651987 | IZ36: 0 | JA36: 0 | JB36: 39490 | JC36: 202134 | JD36: 644 | JE36: 130934 | JG36: 149612 | JH36: 21608 | JI36: 38178 | JJ36: 38154 | JK36: 136908 | JL36: 2007151 | JM36: 0 | JN36: 0 | JO36: 0 | JP36: 73053 | JQ36: 0 | JR36: 0 | JS36: 73053 | JY36: 3924 | KE36: 202134 | KF36: 110 | KG36: 149 | KH36: 102 | KI36: 57 | KJ36: 78 | KK36: 40 | KL36: 32 | KM36: 42 | KN36: 21 | KO36: 1 | KP36: 0 | KQ36: 0 | KR36: 0 | KS36: 1 | KT36: 0 | KU36: 1 | KV36: 0 | KW36: 0 | KX36: 0 | KY36: 0 | KZ36: 0 | LA36: 0 | LB36: 0 | LC36: 0 | LD36: 1 | LE36: 0 | LF36: 0 | LG36: 0 | LH36: 0
A37: 206010914 | B37: KAISER PERMANENTE POST ACUTE CARE CENTER | C37: 45292 | D37: 45494 | E37: 203 | F37: In Process | G37: No | H37: Alameda | I37: SNF | J37: Not-for-Profit | K37: 05 - East Bay | L37: 0421 | M37: 510-481-8575 | N37: 1440 168TH AVENUE | O37: SAN LEANDRO | P37: 94578-0000 | R37: MARC BRIAN | S37: Yes | T37: KAISER FOUNDATION HOSPITALS | U37: 176 | V37: 176 | W37: 100+ | X37: 35728 | Y37: 6126 | Z37: 17.15 | AA37: 444 | AB37: 456 | AC37: 88 | AD37: 4161 | AG37: 212 | AH37: 1489 | AI37: 46 | AJ37: 130 | AK37: Skilled Nursing Care Only | AL37: 6126 | AU37: 15033440 | AV37: 2158147 | AW37: 12281395 | AY37: 4910192 | AZ37: 49516455 | BA37: -44606263 | BE37: -44606263 | BF37: 376805 | BG37: 10095110 | BJ37: 556260 | BK37: 3530285 | BL37: 474980 | BN37: 15033440 | BW37: 44835 | BY37: 1371584 | CE37: 65692 | CG37: 599686 | CI37: 76350 | CM37: 0 | CN37: 0 | CO37: 1417018 | CP37: 0 | CQ37: 0 | CR37: 0 | CS37: 0 | CT37: 720046 | CV37: 21083 | CW37: 28902 | CY37: 38609 | DE37: 1590 | DG37: 34433 | DI37: 133840 | DM37: 71547 | DO37: 51012 | DU37: 17 | DY37: 387647 | EC37: 320616 | EE37: 8124302 | EK37: 607820 | EM37: 2474618 | ES37: 2300 | FA37: 1211 | FC37: 2931 | FG37: 15621010 | FH37: 11208901 | FI37: 22686544 | FJ37: 283312 | FK37: 17905821 | FT37: 315530 | FV37: 3157148 | FZ37: 320592 | GA37: 134552 | GC37: 16658 | GD37: 2007375 | GE37: 1146499 | GF37: 41285 | GG37: 1922529 | GH37: 813165 | GI37: 507757 | GJ37: 322244 | GK37: 14743407 | GL37: 5115375 | GM37: 982614 | GN37: 63904 | HI37: 0 | HM37: 0 | HN37: 0 | HT37: 0 | HU37: 0 | HV37: 14285 | HW37: 0 | HX37: 36194 | HY37: 41214 | HZ37: 107647 | IA37: 6661 | IB37: 0 | IC37: 0 | ID37: 26829 | IE37: 6939 | IF37: 25203 | IH37: 23366 | II37: 8790 | IJ37: 7645 | IK37: 2413 | IL37: 13000 | IM37: 320186 | IN37: 0 | IO37: 0 | IP37: 0 | IQ37: 0 | IR37: 0 | IS37: 0 | IT37: 0 | IU37: 872599 | IV37: 0 | IW37: 2957543 | IX37: 2254274 | IY37: 3692186 | IZ37: 492056 | JA37: 0 | JB37: 0 | JC37: 1781496 | JD37: 285196 | JE37: 694769 | JG37: 926825 | JH37: 470148 | JI37: 279257 | JJ37: 189330 | JK37: 725331 | JL37: 15621010 | JM37: 0 | JN37: 0 | JO37: 0 | JP37: 0 | JQ37: 0 | JR37: 0 | JS37: 0 | JX37: 22722 | JY37: 4107 | KD37: 1535881 | KE37: 245615 | KF37: 222 | KG37: 269 | KH37: 222 | KI37: 153 | KJ37: 184 | KK37: 152 | KL37: 75 | KM37: 100 | KN37: 68 | KO37: 0 | KP37: 1 | KQ37: 0 | KR37: 0 | KS37: 0 | KT37: 1 | KU37: 1 | KV37: 0 | KW37: 0 | KX37: 0 | KY37: 0 | KZ37: 0 | LA37: 0 | LB37: 0 | LC37: 0 | LD37: 1 | LE37: 0 | LF37: 0 | LG37: 0 | LH37: 0
A38: 206010915 | B38: MISSION VALLEY POST ACUTE | C38: 45292 | D38: 45657 | E38: 366 | F38: In Process | G38: No | H38: Alameda | I38: SNF | J38: Investor Owned | K38: 05 - East Bay | L38: 0421 | M38: 510793722 | N38: 2400 PARKSIDE DRIVE | O38: FREMONT | P38: 94536 | Q38: 1245946938 | R38: KELLY BILLS | S38: Yes | U38: 85 | V38: 85 | W38: 60-99 | X38: 31110 | Y38: 28069 | Z38: 211.68 | AA38: 401 | AB38: 400 | AC38: 9061 | AD38: 3651 | AE38: 995 | AF38: 12794 | AI38: 521 | AJ38: 1047 | AK38: Skilled Nursing Care Only | AL38: 28069 | AU38: 20563950 | AV38: 2902333 | AW38: 5231726 | AX38: 11265 | AY38: 18245822 | AZ38: 16015319 | BA38: 2230503 | BB38: -3 | BE38: 2230500 | BF38: 5929900 | BG38: 4739200 | BH38: 640250 | BI38: 8282600 | BL38: 283750 | BM38: 688250 | BN38: 20563950 | BW38: 2100157 | BY38: 793932 | CA38: 1676 | CC38: 6568 | CM38: 10654 | CN38: 0 | CO38: 981870 | CP38: 252 | CQ38: 828465 | CR38: 124100 | CS38: 744802 | CT38: 163080 | CV38: 49110 | EC38: -2264772 | EE38: 3001108 | EG38: 345506 | EI38: 3828964 | EO38: 320920 | FG38: 6521391 | FH38: 1718892 | FI38: 7775036 | FJ38: 122217 | FK38: 6182158 | FT38: 10601 | FV38: 620086 | FW38: 28135 | FX38: 516239 | FY38: 45497 | FZ38: 295901 | GA38: 73268 | GC38: 91006 | GD38: 643252 | GE38: 241390 | GF38: 161990 | GG38: 897265 | GH38: 110983 | GI38: 75217 | GJ38: 130456 | GK38: 3751210 | GL38: 30357 | GM38: 1723235 | GN38: 125336 | GO38: 22592 | GQ38: 11585 | GR38: 227560 | GS38: 4493838 | GU38: 398352 | GV38: 13128 | GY38: 4905318 | GZ38: 1149574 | HC38: 3755744 | HD38: 4905318 | HE38: 2141793 | HI38: 0 | HK38: 419565 | HL38: 24627 | HM38: 444192 | HN38: -45840 | HT38: 0.00 | HU38: 0 | HV38: 2035 | HW38: 0 | HX38: 10605 | HY38: 36842 | HZ38: 53529 | IA38: 0 | IB38: 0 | IC38: 0 | ID38: 12608 | IE38: 2141 | IH38: 17512 | II38: 2039 | IJ38: 2453 | IK38: 2033 | IL38: 19283 | IM38: 161080 | IN38: 0 | IO38: 0 | IP38: 0 | IQ38: 14641 | IR38: 0 | IS38: 0 | IT38: 14641 | IU38: 184018 | IV38: 0 | IW38: 614917 | IX38: 1720701 | IY38: 1430773 | IZ38: 0 | JA38: 0 | JB38: 0 | JC38: 710379 | JD38: 89017 | JG38: 378139 | JH38: 78723 | JI38: 51810 | JJ38: 89315 | JK38: 1173599 | JL38: 6521391 | JM38: 0 | JN38: 0 | JO38: 0 | JP38: 589169 | JQ38: 0 | JR38: 0 | JS38: 589169 | JY38: 12608 | KE38: 710379 | KF38: 92 | KG38: 168 | KH38: 55 | KI38: 68 | KJ38: 130 | KK38: 38 | KL38: 33 | KM38: 56 | KN38: 26 | KO38: 1 | KP38: 0 | KQ38: 0 | KR38: 0 | KS38: 1 | KT38: 0 | KU38: 1 | KV38: 0 | KW38: 0 | KX38: 0 | KY38: 0 | KZ38: 0 | LA38: 0 | LB38: 0 | LC38: 0 | LD38: 1 | LE38: 0 | LF38: 0 | LG38: 0 | LH38: 0
A39: 206010917 | B39: EDEN HEALTHCARE CENTER | C39: 45292 | D39: 45657 | E39: 366 | F39: In Process | G39: No | H39: Alameda | I39: SNF | J39: Investor Owned | K39: 05 - East Bay | L39: 0421 | M39: 510-783-8150 | N39: 27350 TAMPA AVE | O39: HAYWARD | P39: 94544 | Q39: 1144913880 | R39: ALEXANDER LATTIN | S39: Yes | U39: 121 | V39: 121 | W39: 100+ | X39: 44286 | Y39: 43457 | Z39: 231.71 | AC39: 5700 | AE39: 29850 | AH39: 7307 | AJ39: 600 | AK39: Skilled Nursing Care Only | AL39: 43457 | AU39: 23736768 | AV39: 10172225 | AW39: 7551562 | AX39: 31247 | AY39: 26388678 | AZ39: 22618088 | BA39: 3770590 | BE39: 3770590 | BF39: 3053700 | BH39: 14704201 | BK39: 5658667 | BM39: 320200 | BN39: 23736768 | BW39: 8303358 | CA39: 494758 | CG39: 1373359 | CK39: 750 | CM39: 0 | CN39: 0 | CO39: 4639872 | CP39: 14329 | CQ39: 4447000 | CR39: 808000 | CS39: 206031 | CT39: 32272 | CV39: 24721 | EC39: 3921396 | EG39: 3231685 | EM39: 318459 | EO39: 80022 | FG39: 10486157 | FH39: 2298333 | FI39: 9833598 | FJ39: 377177 | FK39: 8318083 | FT39: 360 | FU39: 37280 | FV39: 373372 | FX39: 534630 | FY39: 144027 | FZ39: 115527 | GA39: 44131 | GC39: 34861 | GD39: 632308 | GE39: 430079 | GF39: 195581 | GG39: 1175893 | GH39: 162502 | GI39: 1373212 | GJ39: 120056 | GK39: 6138268 | GL39: 16870 | GM39: 1673587 | GN39: 213258 | GO39: 16634 | GQ39: 15615 | GR39: 851954 | GS39: 8540287 | GU39: 98679 | GW39: 451296 | GY39: 9090262 | GZ39: 3503854 | HB39: 1679291 | HC39: 3907117 | HD39: 9090262 | HF39: 451296 | HI39: 0 | HK39: 8111 | HL39: 115507 | HM39: 123618 | HN39: -24939 | HR39: 1679291 | HT39: 0.18 | HU39: 630693.72 | HV39: 2436 | HW39: 0 | HX39: 22444 | HY39: 21713 | HZ39: 103765 | IA39: 0 | IB39: 0 | IC39: 8351 | ID39: 13768 | IE39: 1607 | IF39: 16188 | IG39: 7918 | IH39: 20752 | II39: 3038 | IJ39: 55198 | IK39: 1756 | IL39: 20746 | IM39: 299680 | IN39: 0 | IO39: 0 | IP39: 1343 | IQ39: 378 | IR39: 0 | IS39: 0 | IT39: 1721 | IU39: 247772 | IV39: 0 | IW39: 1348420 | IX39: 980956 | IY39: 2878399 | IZ39: 0 | JA39: 0 | JB39: 466227 | JC39: 854426 | JD39: 79244 | JE39: 339992 | JF39: 158055 | JG39: 448668 | JH39: 134157 | JI39: 1141084 | JJ39: 96729 | JK39: 1312028 | JL39: 10486157 | JM39: 0 | JN39: 0 | JO39: 40294 | JP39: 7568 | JQ39: 0 | JR39: 0 | JS39: 47862 | JY39: 13768 | KE39: 854426 | KO39: 1 | KP39: 0 | KQ39: 0 | KR39: 0 | KS39: 0 | KT39: 1 | KU39: 1 | KV39: 0 | KW39: 0 | KX39: 0 | KY39: 0 | KZ39: 0 | LA39: 0 | LB39: 0 | LC39: 0 | LD39: 1 | LE39: 0 | LF39: 0 | LG39: 0 | LH39: 0
A40: 206010920 | B40: PIEDMONT GARDENS HEALTH FACILITY | C40: 45292 | D40: 45657 | E40: 366 | F40: In Process | G40: Yes | H40: Alameda | I40: SNF/RES | J40: Not-for-Profit | K40: 05 - East Bay | L40: 0417 | M40: 510-596-2600 | N40: 110 41ST STREET | O40: OAKLAND | P40: 94611-0000 | Q40: 1437230943 | R40: JANA GESINGER | S40: Yes | T40: HUMANGOOD | U40: 94 | V40: 94 | W40: 60-99 | X40: 34404 | Y40: 23921 | Z40: 160.05 | AA40: 370 | AB40: 369 | AC40: 3746 | AD40: 3767 | AE40: 2608 | AF40: 5874 | AG40: 27 | AI40: 7899 | AK40: Skilled Nursing Care Only | AL40: 23921 | AU40: 12144947 | AV40: 2380613 | AW40: 331606 | AX40: 93868 | AY40: 14287822 | AZ40: 13915776 | BA40: 372046 | BB40: 936483 | BE40: 1308529 | BF40: 1901884 | BG40: 1912546 | BH40: 1324109 | BI40: 2982292 | BJ40: 13708 | BL40: 4010408 | BN40: 12144947 | BW40: 1029408 | BX40: 60692 | BY40: 1067837 | BZ40: 71619 | CA40: 14914 | CC40: 74866 | CE40: 10572 | CI40: 50705 | CM40: 191195 | CN40: 0 | CO40: 759347 | CP40: 0 | CQ40: 709595 | CR40: 123360 | CS40: 389298 | CT40: 141395 | CV40: 66423 | DI40: 36234 | EC40: -1464150 | ED40: 30624 | EE40: 464336 | EF40: 38361 | EG40: 459448 | EI40: 1123318 | EK40: -356565 | FG40: 13756716 | FH40: 6085361 | FI40: 16743282 | FJ40: 714311 | FK40: 6907417 | FT40: 278374 | FV40: 253185 | FW40: 16128 | FX40: 239351 | FY40: 36566 | FZ40: 221811 | GA40: 84104 | GC40: 19745 | GD40: 409886 | GE40: 147554 | GF40: 110122 | GG40: 1105611 | GH40: 203338 | GI40: 415079 | GJ40: 154010 | GK40: 2529244 | GL40: 265392 | GM40: 15580 | GN40: 33813 | GO40: 26823 | GP40: 51410 | GR40: 391233 | GS40: 2723934 | GU40: 17110488 | GV40: 6487231 | GW40: 63145551 | GX40: 349475 | GY40: 89816679 | GZ40: 1722667 | HA40: 21794047 | HB40: 16760936 | HC40: 49539029 | HD40: 89816679 | HF40: 63145551 | HI40: 2599704 | HJ40: 20485340 | HL40: 22966748 | HM40: 46051792 | HN40: -28941304 | HQ40: 16901093 | HR40: 16901093 | HS40: -140157 | HT40: 0.00 | HU40: 0 | HV40: 3771 | HW40: 0 | HX40: 14206 | HY40: 24140 | HZ40: 68185 | IA40: 0 | IB40: 0 | IC40: 4880 | IE40: 2318 | IF40: 4048 | IG40: 2691 | IH40: 17553 | II40: 3608 | IJ40: 9156 | IK40: 1760 | IL40: 12462 | IM40: 168778 | IN40: 0 | IO40: 0 | IP40: 0 | IQ40: 268 | IR40: 0 | IS40: 0 | IT40: 268 | IU40: 274050 | IV40: 0 | IW40: 839630 | IX40: 1113722 | IY40: 2068594 | IZ40: 0 | JA40: 0 | JB40: 159549 | JD40: 71282 | JE40: 91577 | JF40: 61248 | JG40: 399510 | JH40: 140772 | JI40: 254002 | JJ40: 112478 | JK40: 518601 | JL40: 6105015 | JM40: 0 | JN40: 0 | JO40: 0 | JP40: 11655 | JQ40: 0 | JR40: 0 | JS40: 11655 | KF40: 110 | KG40: 155 | KH40: 89 | KI40: 91 | KJ40: 132 | KK40: 75 | KL40: 50 | KM40: 81 | KN40: 36 | KO40: 0 | KP40: 1 | KQ40: 0 | KR40: 0 | KS40: 1 | KT40: 0 | KU40: 1 | KV40: 0 | KW40: 0 | KX40: 0 | KY40: 0 | KZ40: 0 | LA40: 0 | LB40: 0 | LC40: 0 | LD40: 0 | LE40: 0 | LF40: 1 | LG40: 0 | LH40: 0
A41: 206010926 | B41: PLEASANTON NURSING AND REHABILITATION CTR | C41: 45292 | D41: 45657 | E41: 366 | F41: In Process | G41: No | H41: Alameda | I41: SNF | J41: Investor Owned | K41: 05 - East Bay | L41: 0419 | M41: 925-462-2400 | N41: 300 NEAL STREET | O41: PLEASANTON | P41: 94566-0000 | Q41: ZZR06392I | R41: ED JOHNSON | S41: Yes | T41: LIFE GENERATIONS HEALTHCARE | U41: 139 | V41: 139 | W41: 100+ | X41: 50874 | Y41: 46289 | Z41: 210.77 | AA41: 947 | AB41: 938 | AC41: 7551 | AD41: 10996 | AE41: 5958 | AF41: 18751 | AI41: 1225 | AJ41: 1808 | AK41: Skilled Nursing Care Only | AL41: 46289 | AU41: 20525920 | AV41: 9288770 | AW41: 2343158 | AX41: 38445 | AY41: 27509977 | AZ41: 24967252 | BA41: 2542725 | BB41: -23 | BE41: 2542702 | BF41: 3442568 | BG41: 5014941 | BH41: 2372641 | BI41: 8356829 | BL41: 547220 | BM41: 791721 | BN41: 20525920 | BW41: 3187213 | BY41: 5038660 | CA41: 78505 | CC41: 161502 | CI41: 34975 | CK41: 787915 | CM41: 144242 | CN41: 0 | CO41: 2799650 | CP41: 775220 | CQ41: 2803380 | CR41: 1118640 | CS41: 1030521 | CT41: 431030 | CV41: 186087 | EC41: -975250 | EE41: 1605907 | EG41: 382986 | EI41: 1218988 | EO41: 110527 | FG41: 10704767 | FH41: 2580469 | FI41: 11682016 | FJ41: 36200 | FK41: 9896241 | FT41: 155504 | FV41: 1180669 | FW41: 189393 | FX41: 893367 | FY41: 201274 | FZ41: 543165 | GA41: 228840 | GC41: 107374 | GD41: 819570 | GE41: 492176 | GF41: 67995 | GG41: 1483281 | GH41: 315263 | GI41: 284663 | GJ41: 275119 | GK41: 4367166 | GL41: 22218 | GM41: 2459309 | GN41: 92096 | GO41: 50114 | GR41: 842455 | GS41: 37745893 | GU41: 17061 | GW41: 25722 | GY41: 37788676 | GZ41: -13752116 | HA41: 127425 | HB41: 11344 | HC41: 51402023 | HD41: 37788676 | HG41: -15355361 | HI41: 0 | HK41: 5159 | HL41: 201640 | HM41: 206799 | HN41: -189738 | HR41: 25722 | HS41: -14378 | HT41: -2.29 | HU41: 31492346 | HV41: 5602 | HW41: 0 | HX41: 23961 | HY41: 69315 | HZ41: 111945 | IA41: 0 | IB41: 0 | IC41: 1408 | ID41: 7376 | IE41: 8113 | IF41: 18306 | IG41: 1973 | IH41: 30969 | II41: 7143 | IJ41: 10202 | IK41: 6545 | IL41: 26724 | IM41: 329582 | IN41: 0 | IO41: 0 | IP41: 0 | IQ41: 0 | IR41: 0 | IS41: 0 | IT41: 0 | IU41: 367287 | IV41: 0 | IW41: 1197426 | IX41: 2856149 | IY41: 3113280 | IZ41: 0 | JA41: 0 | JB41: 23879 | JC41: 265340 | JD41: 171486 | JE41: 344519 | JF41: 34803 | JG41: 699390 | JH41: 215320 | JI41: 217879 | JJ41: 219651 | JK41: 978358 | JL41: 10704767 | JM41: 0 | JN41: 0 | JO41: 0 | JP41: 0 | JQ41: 0 | JR41: 0 | JS41: 0 | JX41: 7376 | KD41: 265340 | KF41: 244 | KG41: 369 | KH41: 159 | KI41: 174 | KJ41: 272 | KK41: 103 | KL41: 109 | KM41: 175 | KN41: 60 | KO41: 1 | KP41: 0 | KQ41: 0 | KR41: 0 | KS41: 0 | KT41: 1 | KU41: 1 | KV41: 0 | KW41: 0 | KX41: 0 | KY41: 0 | KZ41: 0 | LA41: 0 | LB41: 0 | LC41: 0 | LD41: 1 | LE41: 0 | LF41: 0 | LG41: 0 | LH41: 0
A42: 206010934 | B42: CANYON CREEK POST ACUTE | C42: 45292 | D42: 45657 | E42: 366 | F42: In Process | G42: No | H42: Alameda | I42: SNF | J42: Investor Owned | K42: 05 - East Bay | L42: 0421 | M42: 510-534-8848 | N42: 22103 REDWOOD ROAD | O42: CASTRO VALLEY | P42: 94546 | Q42: 1346942695 | R42: ERIC A. CORPUZ | S42: Yes | U42: 70 | V42: 70 | W42: 60-99 | X42: 25620 | Y42: 23661 | Z42: 218.07 | AA42: 411 | AB42: 408 | AC42: 2867 | AE42: 3215 | AF42: 11215 | AH42: 5190 | AI42: 119 | AJ42: 1055 | AK42: Skilled Nursing Care Only | AL42: 23661 | AU42: 9185273 | AV42: 3373259 | AW42: 1187401 | AX42: 18300 | AY42: 11389431 | AZ42: 11829593 | BA42: -440162 | BB42: 6 | BC42: 6800 | BE42: -446956 | BF42: 1112978 | BH42: 1248073 | BI42: 4353698 | BK42: 2014774 | BL42: 46196 | BM42: 409554 | BN42: 9185273 | BW42: 408737 | CA42: 458350 | CC42: 1598881 | CG42: 739917 | CI42: 16967 | CK42: 150407 | CM42: 33243 | CN42: 108073 | CO42: 985538 | CP42: 194669 | CQ42: 1091160 | CR42: 235521 | CS42: 550732 | CT42: 128546 | CV42: 45777 | EC42: -6795188 | EG42: 1204563 | EI42: 4353698 | EM42: 2014774 | EO42: 409554 | FG42: 5377604 | FH42: 1075841 | FI42: 5376148 | FJ42: 87522 | FK42: 4695680 | FT42: 9641 | FU42: 54182 | FV42: 471655 | FW42: 939 | FX42: 386554 | FY42: 80733 | FZ42: 237938 | GA42: 64784 | GC42: 23207 | GD42: 328820 | GE42: 214565 | GF42: 112524 | GG42: 767604 | GH42: 130104 | GI42: 90681 | GJ42: 116968 | GK42: 2401522 | GL42: 264927 | GM42: 1207734 | GN42: 41428 | GO42: 13799 | GR42: 113604 | GS42: 3363211 | GU42: 69861 | GV42: 883055 | GW42: 2894167 | GX42: 47559 | GY42: 7257853 | GZ42: 1368090 | HB42: 7664887 | HC42: -1775124 | HD42: 7257853 | HH42: 4210606 | HI42: 0 | HK42: 18795 | HL42: 59147 | HM42: 77942 | HN42: -8081 | HO42: 3049035 | HR42: 7664887 | HT42: 0.27 | HU42: 369384.3 | HV42: 1956 | HW42: 0 | HX42: 10522 | HY42: 17238 | HZ42: 48941 | IA42: 0 | IB42: 0 | IC42: 2490 | ID42: 11160 | IE42: 2070 | IF42: 8473 | IG42: 4622 | IH42: 16342 | II42: 2938 | IJ42: 2810 | IK42: 1860 | IL42: 13797 | IM42: 145219 | IN42: 0 | IO42: 357 | IP42: 6997 | IQ42: 14706 | IR42: 0 | IS42: 0 | IT42: 22060 | IU42: 166025 | IV42: 0 | IW42: 604249 | IX42: 781485 | IY42: 1382000 | IZ42: 0 | JA42: 0 | JB42: 208064 | JC42: 781450 | JD42: 62082 | JE42: 157907 | JF42: 87456 | JG42: 386716 | JH42: 79378 | JI42: 71826 | JJ42: 96129 | JK42: 512836 | JL42: 5377603 | JM42: 0 | JN42: 14289 | JO42: 209924 | JP42: 294115 | JQ42: 0 | JR42: 0 | JS42: 518328 | JY42: 11160 | KE42: 781450 | KF42: 112 | KG42: 228 | KH42: 60 | KI42: 79 | KJ42: 179 | KK42: 38 | KL42: 40 | KM42: 87 | KN42: 19 | KO42: 1 | KP42: 0 | KQ42: 0 | KR42: 0 | KS42: 1 | KT42: 0 | KU42: 1 | KV42: 0 | KW42: 0 | KX42: 0 | KY42: 0 | KZ42: 0 | LA42: 0 | LB42: 0 | LC42: 0 | LD42: 1 | LE42: 0 | LF42: 0 | LG42: 0 | LH42: 0
A43: 206010944 | B43: SAN LEANDRO HEALTHCARE CENTER | C43: 45292 | D43: 45657 | E43: 366 | F43: In Process | G43: No | H43: Alameda | I43: SNF | J43: Investor Owned | K43: 05 - East Bay | L43: 0421 | M43: 510-357-4015 | N43: 368 JUANA AVENUE | O43: SAN LEANDRO | P43: 94577 | Q43: 1790850329 | R43: CARLOS CORTEZ | S43: Yes | U43: 62 | V43: 62 | W43: 60-99 | X43: 22692 | Y43: 19634 | Z43: 199.17 | AA43: 286 | AB43: 283 | AC43: 3247 | AD43: 1272 | AE43: 889 | AF43: 9680 | AH43: 3542 | AI43: 129 | AJ43: 875 | AK43: Skilled Nursing Care Only | AL43: 19634 | AU43: 8834122 | AV43: 1793243 | AW43: -741707 | AX43: 1070 | AY43: 11370142 | AZ43: 9956468 | BA43: 1413674 | BB43: 213818 | BC43: 88163 | BE43: 1539329 | BF43: 1460955 | BG43: 572324 | BH43: 399997 | BI43: 4355419 | BK43: 1593687 | BL43: 58042 | BM43: 393698 | BN43: 8834122 | BW43: 802040 | BY43: 226057 | CA43: 35833 | CC43: 90036 | CG43: 629474 | CI43: 5766 | CK43: 4037 | CM43: 22420 | CN43: 0 | CO43: 619220 | CP43: 0 | CQ43: 612806 | CR43: 68784 | CS43: 317818 | CT43: 109088 | CV43: 43107 | EC43: -1145200 | EE43: -56411 | EG43: -3216 | EI43: 565039 | EM43: -157081 | EO43: 55162 | FG43: 3872700 | FH43: 958513 | FI43: 5125255 | FJ43: 80041 | FK43: 4024982 | FT43: 21769 | FV43: 446451 | FX43: 312183 | FY43: 44562 | FZ43: 218853 | GA43: 74338 | GC43: 27195 | GD43: 435874 | GE43: 301106 | GF43: 75928 | GG43: 622420 | GH43: 146112 | GI43: 94697 | GJ43: 45618 | GK43: 2373968 | GL43: 48497 | GM43: 446400 | GN43: 24900 | GO43: 20671 | GR43: 149944 | GS43: 9134245 | GU43: 138780 | GY43: 9273025 | GZ43: 1375887 | HC43: 7897138 | HD43: 9273025 | HI43: 27003 | HK43: 319030 | HL43: 313765 | HM43: 659798 | HN43: -521018 | HT43: 3.63 | HU43: 4994469.8 | HV43: 1859 | HW43: 0 | HX43: 5673 | HY43: 19856 | HZ43: 38133 | IA43: 0 | IB43: 0 | IC43: 1889 | IE43: 3473 | IF43: 9299 | IG43: 2813 | IH43: 13897 | II43: 3875 | IJ43: 2244 | IK43: 782 | IL43: 11173 | IM43: 114966 | IN43: 0 | IO43: 45 | IP43: 3225 | IQ43: 18627 | IR43: 0 | IS43: 0 | IT43: 21897 | IU43: 147077 | IV43: 0 | IW43: 271537 | IX43: 871129 | IY43: 975315 | IZ43: 0 | JA43: 0 | JB43: 119603 | JD43: 110623 | JE43: 191795 | JF43: 52364 | JG43: 329416 | JH43: 118439 | JI43: 58758 | JJ43: 33245 | JK43: 593399 | JL43: 3872700 | JM43: 0 | JN43: 3068 | JO43: 181129 | JP43: 638878 | JQ43: 0 | JR43: 0 | JS43: 823075 | KF43: 69 | KG43: 107 | KH43: 57 | KI43: 38 | KJ43: 60 | KK43: 31 | KL43: 22 | KM43: 36 | KN43: 18 | KO43: 1 | KP43: 0 | KQ43: 0 | KR43: 0 | KS43: 1 | KT43: 0 | KU43: 1 | KV43: 0 | KW43: 0 | KX43: 0 | KY43: 0 | KZ43: 0 | LA43: 0 | LB43: 0 | LC43: 0 | LD43: 1 | LE43: 0 | LF43: 0 | LG43: 0 | LH43: 0
A44: 206010952 | B44: BAY VIEW REHABILITATION HOSPITAL | C44: 45292 | D44: 45657 | E44: 366 | F44: In Process | G44: No | H44: Alameda | I44: SNF | J44: Investor Owned | K44: 05 - East Bay | L44: 0417 | M44: 510-521-5600 | N44: 516 WILLOW STREET | O44: ALAMEDA | P44: 94501-6132 | Q44: 1386998664 | R44: GARY YOSHIDA | S44: Yes | U44: 170 | V44: 170 | W44: 100+ | X44: 62220 | Y44: 58611 | Z44: 219.6 | AA44: 394 | AB44: 191 | AC44: 10231 | AD44: 894 | AE44: 2146 | AF44: 40508 | AJ44: 4832 | AK44: Skilled Nursing Care Only | AL44: 58611 | AU44: 76194300 | AV44: 8104245 | AW44: 58600164 | AX44: 126201 | AY44: 25824582 | AZ44: 26969193 | BA44: -1144611 | BB44: 312985 | BE44: -831626 | BF44: 13300300 | BG44: 1162200 | BH44: 2789800 | BI44: 52660400 | BM44: 6281600 | BN44: 76194300 | BW44: 6571982 | BY44: 356022 | CA44: 645744 | CC44: 431816 | CK44: 98681 | CM44: 22466 | CN44: 0 | CO44: 5048400 | CP44: 0 | CQ44: 1820750 | CR44: 848000 | CS44: 280119 | CT44: 63059 | CV44: 21451 | EC44: 9936592 | EE44: 1060066 | EG44: -1359731 | EI44: 44159287 | EO44: 4803950 | FG44: 14160297 | FH44: 2455866 | FI44: 10353030 | FJ44: 589428 | FK44: 10994705 | FT44: 15430 | FU44: 5144 | FV44: 691127 | FX44: 253485 | FY44: 118059 | FZ44: 476927 | GA44: 86335 | GC44: 56849 | GD44: 918905 | GE44: 819044 | GF44: 134005 | GG44: 2643277 | GH44: 247977 | GI44: 175311 | GJ44: 175728 | GK44: 5835518 | GL44: 105732 | GM44: 2561217 | GN44: 224932 | GO44: 212736 | GR44: 216750 | GS44: 3618307 | GU44: 243778 | GW44: 32629148 | GX44: 11808216 | GY44: 48299449 | GZ44: 3805220 | HB44: 21729855 | HC44: 22764374 | HD44: 48299449 | HH44: 9762727 | HI44: 0 | HL44: 885235 | HM44: 885235 | HN44: -641457 | HP44: 11967128 | HR44: 21729855 | HT44: 0.00 | HU44: 0 | HV44: 2289 | HW44: 0 | HX44: 24540 | HY44: 52569 | HZ44: 166438 | IA44: 0 | IB44: 0 | IC44: 2790 | ID44: 14342 | IE44: 14473 | IF44: 32221 | IG44: 4821 | IH44: 53226 | II44: 7899 | IJ44: 6290 | IK44: 2613 | IL44: 50414 | IM44: 434925 | IN44: 0 | IO44: 0 | IP44: 194 | IQ44: 101 | IR44: 0 | IS44: 0 | IT44: 295 | IU44: 213679 | IV44: 0 | IW44: 1432719 | IX44: 2396386 | IY44: 4752818 | IZ44: 0 | JA44: 0 | JB44: 158078 | JC44: 915900 | JD44: 305842 | JE44: 645872 | JF44: 87382 | JG44: 1142381 | JH44: 209894 | JI44: 146358 | JJ44: 144356 | JK44: 1608632 | JL44: 14160297 | JM44: 0 | JN44: 0 | JO44: 11038 | JP44: 3563 | JQ44: 0 | JR44: 0 | JS44: 14601 | JY44: 14342 | KE44: 915900 | KF44: 241 | KG44: 308 | KH44: 186 | KI44: 143 | KJ44: 178 | KK44: 113 | KL44: 78 | KM44: 100 | KN44: 59 | KO44: 1 | KP44: 0 | KQ44: 0 | KR44: 0 | KS44: 0 | KT44: 1 | KU44: 1 | KV44: 0 | KW44: 0 | KX44: 0 | KY44: 0 | KZ44: 0 | LA44: 0 | LB44: 0 | LC44: 0 | LD44: 1 | LE44: 0 | LF44: 0 | LG44: 0 | LH44: 0
A45: 206010953 | B45: ALAMEDA HEALTHCARE AND WELLNESS CENTER | C45: 45170 | D45: 45535 | E45: 366 | F45: In Process | G45: No | H45: Alameda | I45: SNF | J45: Investor Owned | K45: 05 - East Bay | L45: 0417 | M45: 510-658-2041 | N45: 430 WILLOW STREET | O45: ALAMEDA | P45: 94501 | Q45: 1578885778 | R45: MARY GOLDHOFF | S45: Yes | U45: 166 | V45: 166 | W45: 100+ | X45: 60756 | Y45: 55411 | Z45: 91.2 | AA45: 281 | AB45: 241 | AC45: 5888 | AE45: 7093 | AF45: 38514 | AG45: 1227 | AI45: 167 | AJ45: 2522 | AK45: Mixed Care | AL45: 47630 | AP45: 7781 | AU45: 29025040 | AV45: 5643210 | AW45: 10096347 | AY45: 24571903 | AZ45: 27257877 | BA45: -2685974 | BB45: 771382 | BC45: 11590 | BE45: -1926182 | BF45: 5848787 | BH45: 3713562 | BI45: 17366322 | BJ45: 1127252 | BL45: 54929 | BM45: 914188 | BN45: 22371472 | BR45: 6653568 | BW45: 3283141 | CA45: 301729 | CC45: 1348071 | CE45: 692464 | CI45: 1749 | CK45: 16056 | CM45: 890134 | CN45: 247033 | CO45: 1482306 | CP45: 6099 | CQ45: 1260342 | CR45: 422158 | CS45: 892019 | CT45: 170710 | CV45: 272409 | DY45: -35021 | EC45: 1425190 | EG45: 1500435 | EI45: 6143649 | EK45: 789633 | EO45: 272461 | FG45: 12150033 | FH45: 2365514 | FI45: 12742330 | FJ45: 454223 | FK45: 9300789 | FO45: 4705600 | FT45: 4822 | FU45: 134522 | FV45: 302625 | FX45: 312878 | FY45: 124335 | FZ45: 317904 | GA45: 56521 | GC45: 142745 | GD45: 1077086 | GE45: 710815 | GF45: 149231 | GG45: 1362665 | GH45: 172849 | GI45: 233505 | GJ45: 149211 | GK45: 4682243 | GL45: 55188 | GM45: 2660896 | GN45: 154009 | GO45: 25396 | GQ45: 28498 | GR45: 393544 | GS45: 7278533 | GU45: 117513 | GV45: 353620 | GW45: 16575560 | GY45: 24325226 | GZ45: 26575821 | HC45: -2250595 | HD45: 24325226 | HE45: 4936 | HG45: 3948760 | HI45: 0 | HK45: 675709 | HL45: 513077 | HM45: 1188786 | HN45: -1071273 | HT45: 0.03 | HU45: 797274.63 | HV45: 3336 | HW45: 0 | HX45: 23926 | HY45: 61255 | HZ45: 86518 | IA45: 6357 | IB45: 713 | IC45: 12934 | ID45: 11150 | IE45: 3770 | IF45: 23854 | IG45: 3821 | IH45: 30370 | II45: 4374 | IJ45: 7155 | IK45: 1931 | IL45: 20927 | IM45: 302391 | IN45: 0 | IO45: 5173 | IP45: 7116 | IQ45: 40559 | IR45: 0 | IS45: 0 | IT45: 52848 | IU45: 303986 | IV45: 0 | IW45: 1607726 | IX45: 3129491 | IY45: 2744548 | IZ45: 337802 | JA45: 21174 | JB45: 590390 | JC45: 572001 | JD45: 122203 | JE45: 499969 | JF45: 78106 | JG45: 746569 | JH45: 144244 | JI45: 188835 | JJ45: 107729 | JK45: 955260 | JL45: 12150033 | JM45: 0 | JN45: 369636 | JO45: 448140 | JP45: 1425226 | JQ45: 0 | JR45: 0 | JS45: 2243002 | JY45: 11150 | KE45: 572001 | KF45: 243 | KG45: 382 | KH45: 142 | KI45: 153 | KJ45: 248 | KK45: 91 | KL45: 76 | KM45: 119 | KN45: 47 | KO45: 1 | KP45: 0 | KQ45: 0 | KR45: 0 | KS45: 0 | KT45: 1 | KU45: 1 | KV45: 0 | KW45: 0 | KX45: 0 | KY45: 1 | KZ45: 0 | LA45: 0 | LB45: 0 | LC45: 0 | LD45: 1 | LE45: 0 | LF45: 0 | LG45: 0 | LH45: 0
A46: 206010959 | B46: SERENETHOS CARE CENTER | C46: 45292 | D46: 45657 | E46: 366 | F46: In Process | G46: No | H46: Alameda | I46: SNF | J46: Investor Owned | K46: 05 - East Bay | L46: 0421 | M46: 510-537-4844 | N46: 22822 MYRTLE STREET | O46: HAYWARD | P46: 94541 | Q46: 1760471346 | R46: JAMES SCHINDLER | S46: Yes | U46: 36 | V46: 36 | W46: 1-59 | X46: 13176 | Y46: 11909 | Z46: 208.05 | AA46: 24 | AB46: 25 | AC46: 924 | AE46: 1683 | AF46: 9013 | AH46: 289 | AK46: Skilled Nursing Care Only | AL46: 11909 | AU46: 4768152 | AV46: 607493 | AW46: 1169579 | AX46: 24798 | AY46: 4230864 | AZ46: 4423945 | BA46: -193081 | BB46: 7564 | BE46: -185517 | BF46: 369600 | BH46: 809152 | BI46: 3473800 | BK46: 115600 | BN46: 4768152 | BW46: 516719 | CC46: 8813 | CG46: 81961 | CM46: 0 | CN46: 0 | CO46: 216555 | CP46: 0 | CQ46: 244925 | CR46: 50998 | CS46: 74641 | CT46: 4980 | CV46: 15394 | EC46: -160276 | EG46: 249155 | EI46: 1171600 | EM46: -90900 | FG46: 1842001 | FH46: 665470 | FI46: 1916474 | FJ46: 102233 | FK46: 2056065 | FT46: 5618 | FU46: 9399 | FV46: 170000 | FX46: 200000 | FY46: 30000 | FZ46: 45070 | GA46: 4401 | GC46: 6468 | GD46: 156048 | GE46: 95821 | GF46: 111210 | GG46: 588716 | GI46: 124100 | GK46: 587831 | GL46: 22769 | GM46: 179706 | GN46: 6112 | GO46: 7068 | GR46: 17543 | GS46: 2503411 | GU46: 106188 | GW46: 29457 | GX46: 450000 | GY46: 3089056 | GZ46: 1269664 | HC46: 1819392 | HD46: 3089056 | HG46: 153819 | HI46: 0 | HK46: 83700 | HL46: 124842 | HM46: 208542 | HN46: -102354 | HT46: 1.20 | HU46: 1523596.8 | HV46: 0 | HW46: 0 | HX46: 3159 | HY46: 10670 | HZ46: 24584 | IA46: 0 | IB46: 0 | IC46: 0 | IE46: 148 | IF46: 2246 | IG46: 3937 | IH46: 8435 | IJ46: 3542 | IM46: 56721 | IN46: 0 | IO46: 0 | IP46: 0 | IQ46: 8169 | IR46: 0 | IS46: 0 | IT46: 8169 | IU46: 0 | IV46: 0 | IW46: 201559 | IX46: 450056 | IY46: 636178 | IZ46: 0 | JA46: 0 | JB46: 0 | JD46: 3313 | JE46: 39670 | JF46: 70655 | JG46: 357249 | JI46: 83321 | JL46: 1842001 | JM46: 0 | JN46: 0 | JO46: 0 | JP46: 179726 | JQ46: 0 | JR46: 0 | JS46: 179726 | KF46: 39 | KG46: 46 | KH46: 36 | KI46: 25 | KJ46: 29 | KK46: 23 | KL46: 14 | KM46: 16 | KN46: 13 | KO46: 1 | KP46: 0 | KQ46: 0 | KR46: 1 | KS46: 0 | KT46: 0 | KU46: 1 | KV46: 0 | KW46: 0 | KX46: 0 | KY46: 0 | KZ46: 0 | LA46: 0 | LB46: 0 | LC46: 0 | LD46: 1 | LE46: 0 | LF46: 0 | LG46: 0 | LH46: 0
A47: 206010961 | B47: ST. JOHN KRONSTADT CONVALESCENT CENTER | C47: 45292 | D47: 45657 | E47: 366 | F47: In Process | G47: No | H47: Alameda | I47: SNF | J47: Not-for-Profit | K47: 05 - East Bay | L47: 0421 | M47: 510-889-7000 | N47: 4432 JAMES AVENUE | O47: CASTRO VALLEY | P47: 94546 | Q47: ZZR55016G | R47: JEREMY GRIMES | S47: No | U47: 49 | V47: 49 | W47: 1-59 | X47: 17934 | Y47: 15450 | Z47: 165.95 | AA47: 30 | AB47: 32 | AC47: 784 | AE47: 2422 | AF47: 11767 | AG47: 93 | AI47: 384 | AK47: Skilled Nursing Care Only | AL47: 15450 | AU47: 6053676 | AV47: 263052 | AW47: 114496 | AX47: 436787 | AY47: 6639019 | AZ47: 6718446 | BA47: -79427 | BB47: -2832 | BE47: -82259 | BF47: 307110 | BH47: 975794 | BI47: 4580372 | BJ47: 36970 | BL47: 153430 | BN47: 6053676 | BW47: 238723 | CA47: 8 | CE47: 21617 | CI47: 2704 | CM47: 11645 | CN47: 0 | CO47: 108895 | CP47: 0 | CQ47: 95550 | CR47: 6198 | CS47: 31940 | CT47: 5127 | CV47: 3697 | DM47: -3004 | DY47: -2769 | EC47: -328287 | EG47: 67021 | EI47: 344464 | EK47: 37071 | FG47: 3273703 | FH47: 1342667 | FI47: 2102076 | FJ47: 86070 | FK47: 3171286 | FT47: 9582 | FV47: 135136 | FX47: 112164 | FY47: 6157 | FZ47: 20810 | GA47: 10591 | GC47: 5889 | GD47: 352824 | GE47: 229114 | GF47: 81421 | GG47: 694971 | GH47: 72704 | GI47: 236703 | GJ47: 86230 | GK47: 1328220 | GL47: 121069 | GM47: 19247 | GN47: 9025 | GO47: 7370 | GR47: 7933 | GS47: 3745484 | GU47: 2065744 | GW47: 1394882 | GY47: 7206110 | GZ47: 425419 | HC47: 6780691 | HD47: 7206110 | HI47: 953955 | HJ47: 2047485 | HL47: 738822 | HM47: 3740262 | HN47: -1674518 | HT47: 6.49 | HU47: 2760969.3 | HV47: 1958 | HW47: 0 | HX47: 2364 | HY47: 16522 | HZ47: 37357 | IA47: 0 | IB47: 0 | IC47: 795 | ID47: 3121 | IE47: 1865 | IF47: 6793 | IG47: 2099 | IH47: 13410 | II47: 1759 | IJ47: 6497 | IK47: 1341 | IL47: 3545 | IM47: 99426 | IN47: 0 | IO47: 0 | IP47: 181 | IQ47: 3533 | IR47: 0 | IS47: 0 | IT47: 3714 | IU47: 122353 | IV47: 0 | IW47: 133354 | IX47: 726399 | IY47: 1032227 | IZ47: 0 | JA47: 0 | JB47: 39996 | JC47: 181336 | JD47: 67272 | JE47: 149039 | JF47: 48107 | JG47: 362275 | JH47: 50140 | JI47: 164097 | JJ47: 58541 | JK47: 138567 | JL47: 3273703 | JM47: 0 | JN47: 0 | JO47: 9702 | JP47: 116426 | JQ47: 0 | JR47: 0 | JS47: 126128 | JY47: 3121 | KE47: 181336 | KF47: 65 | KG47: 103 | KH47: 51 | KI47: 38 | KJ47: 57 | KK47: 29 | KL47: 23 | KM47: 37 | KN47: 18 | KO47: 0 | KP47: 1 | KQ47: 0 | KR47: 1 | KS47: 0 | KT47: 0 | KU47: 1 | KV47: 0 | KW47: 0 | KX47: 0 | KY47: 0 | KZ47: 0 | LA47: 0 | LB47: 0 | LC47: 0 | LD47: 1 | LE47: 0 | LF47: 0 | LG47: 0 | LH47: 0
A48: 206010966 | B48: ST. PAUL'S TOWERS | C48: 45017 | D48: 45382 | E48: 366 | F48: In Process | G48: Yes | H48: Alameda | I48: SNF/RES | J48: Not-for-Profit | K48: 05 - East Bay | L48: 0417 | M48: 510-835-4700 | N48: 100 BAY PLACE | O48: OAKLAND | P48: 94610-0000 | R48: CONNIE YUEN | S48: Yes | T48: FRONT PORCH COMMUNITIES AND SERVICES | U48: 43 | V48: 43 | W48: 1-59 | X48: 15738 | Y48: 10679 | Z48: 67.85 | AA48: 121 | AB48: 126 | AC48: 2277 | AH48: 643 | AI48: 7116 | AJ48: 643 | AK48: Skilled Nursing Care Only | AL48: 10679 | AU48: 4323036 | AV48: 2058631 | AW48: 672497 | AX48: 6503 | AY48: 5715673 | AZ48: 7753450 | BA48: -2037777 | BB48: 3552202 | BE48: 1514425 | BF48: 1256904 | BK48: 354936 | BL48: 2711196 | BN48: 4323036 | BW48: 1536286 | BX48: 241353 | CG48: 224555 | CH48: 29184 | CI48: 27195 | CJ48: 58 | CM48: 37902 | CN48: 0 | CO48: 992907 | CP48: 0 | CQ48: 759064 | CR48: 154897 | CS48: 76799 | CT48: 15321 | CV48: 21741 | DY48: 185700 | EC48: 323099 | ED48: 74696 | EM48: 83360 | FC48: 5642 | FG48: 3146741 | FH48: 1307868 | FI48: 3298841 | FJ48: 101344 | FK48: 2788956 | FT48: 7885 | FV48: 292201 | FX48: 205959 | FY48: 8825 | FZ48: 76522 | GA48: 29815 | GC48: 63809 | GD48: 210255 | GE48: 80913 | GF48: 106666 | GG48: 913499 | GI48: 100009 | GJ48: 1600 | GK48: 2321060 | GL48: 377972 | GM48: 780 | GO48: 166724 | GS48: 81112144 | GU48: 98098585 | GV48: 5938549 | GW48: 128404 | GX48: 9240000 | GY48: 194517682 | GZ48: 15671602 | HA48: 34437061 | HB48: 52609263 | HC48: 91799756 | HD48: 194517682 | HH48: 52609263 | HI48: 25390829 | HJ48: 85663329 | HL48: 3174969 | HM48: 114229127 | HN48: -16130542 | HR48: 52609263 | HT48: 0.00 | HU48: 0 | HV48: 2178 | HW48: 0 | HX48: 8242 | HY48: 17513 | HZ48: 37996 | IA48: 0 | IB48: 0 | IC48: 0 | IE48: 804 | IF48: 1492 | IG48: 1967 | IH48: 10367 | IJ48: 2139 | IL48: 19086 | IM48: 101784 | IN48: 0 | IO48: 0 | IP48: 2548 | IQ48: 6053 | IR48: 0 | IS48: 0 | IT48: 8601 | IU48: 160049 | IV48: 0 | IW48: 295596 | IX48: 534561 | IY48: 678083 | IZ48: 0 | JA48: 0 | JB48: 0 | JD48: 21023 | JE48: 31061 | JF48: 40947 | JG48: 223002 | JI48: 63220 | JK48: 1099198 | JL48: 3146740 | JM48: 0 | JN48: 0 | JO48: 156911 | JP48: 258006 | JQ48: 0 | JR48: 0 | JS48: 414917 | KF48: 86 | KG48: 217 | KH48: 68 | KI48: 63 | KJ48: 165 | KK48: 48 | KL48: 35 | KM48: 84 | KN48: 28 | KO48: 0 | KP48: 1 | KQ48: 0 | KR48: 1 | KS48: 0 | KT48: 0 | KU48: 1 | KV48: 0 | KW48: 0 | KX48: 0 | KY48: 0 | KZ48: 0 | LA48: 0 | LB48: 0 | LC48: 0 | LD48: 0 | LE48: 0 | LF48: 1 | LG48: 0 | LH48: 0
A49: 206010968 | B49: WE CARE SKILLED NURSING FACILITY | C49: 45292 | D49: 45657 | E49: 366 | F49: In Process | G49: No | H49: Alameda | I49: SNF | J49: Investor Owned | K49: 05 - East Bay | L49: 0421 | M49: 510-750-1245 | N49: 21863 VALLEJO STREET | O49: HAYWARD | P49: 94541-0000 | Q49: 1346750478 | R49: ALDWIN FAJARDO PONDER | S49: No | U49: 28 | V49: 28 | W49: 1-59 | X49: 10248 | Y49: 8163 | Z49: 173.53 | AA49: 126 | AB49: 127 | AC49: 4691 | AE49: 1290 | AF49: 2157 | AI49: 25 | AK49: Skilled Nursing Care Only | AL49: 8163 | AU49: 3307900 | AV49: 2345520 | AW49: -1151527 | AX49: 2743 | AY49: 6807690 | AZ49: 5055579 | BA49: 1752111 | BE49: 1752111 | BF49: 1899000 | BH49: 522000 | BI49: 876674 | BL49: 10226 | BN49: 3307900 | BW49: 2070743 | CA49: 17585 | CC49: 256517 | CI49: 675 | CM49: 0 | CN49: 0 | CO49: 1082130 | CP49: 0 | CQ49: 982575 | CR49: 51625 | CS49: 229190 | CT49: 0 | CV49: 0 | EC49: -1557094 | EG49: 11105 | EI49: 394462 | FG49: 2660814 | FH49: 395731 | FI49: 1999034 | FJ49: 40945 | FK49: 1742226 | FV49: 269794 | FX49: 398292 | FY49: 25701 | FZ49: 165822 | GD49: 161306 | GE49: 88138 | GF49: 63616 | GG49: 287008 | GH49: 43646 | GI49: 72911 | GJ49: 61000 | GK49: 1191134 | GL49: 108180 | GM49: 366000 | GN49: 10805 | GS49: 5142015 | GU49: 164521 | GX49: 908434 | GY49: 6214970 | GZ49: 733259 | HC49: 5481711 | HD49: 6214970 | HI49: 0 | HK49: 199607 | HL49: 154782 | HM49: 354389 | HN49: -189868 | HT49: 2.03 | HU49: 1488515.8 | HV49: 3858 | HW49: 0 | HX49: 558 | HY49: 10732 | HZ49: 22421 | IA49: 0 | IB49: 0 | IC49: 848 | ID49: 10915 | IF49: 2080 | IH49: 7363 | II49: 1211 | IJ49: 1758 | IL49: 8237 | IM49: 69981 | IN49: 0 | IO49: 44 | IP49: 0 | IQ49: 1280 | IR49: 0 | IS49: 0 | IT49: 1324 | IU49: 250933 | IV49: 0 | IW49: 24667 | IX49: 460737 | IY49: 594160 | IZ49: 0 | JA49: 0 | JB49: 45572 | JC49: 599035 | JE49: 78096 | JG49: 174800 | JH49: 37342 | JI49: 57432 | JK49: 338040 | JL49: 2660814 | JM49: 0 | JN49: 2880 | JO49: 0 | JP49: 39666 | JQ49: 0 | JR49: 0 | JS49: 42546 | JY49: 10915 | KE49: 599035 | KF49: 49 | KG49: 82 | KH49: 43 | KI49: 26 | KJ49: 43 | KK49: 19 | KL49: 15 | KM49: 28 | KN49: 11 | KO49: 1 | KP49: 0 | KQ49: 0 | KR49: 1 | KS49: 0 | KT49: 0 | KU49: 1 | KV49: 0 | KW49: 0 | KX49: 0 | KY49: 0 | KZ49: 0 | LA49: 0 | LB49: 0 | LC49: 0 | LD49: 1 | LE49: 0 | LF49: 0 | LG49: 0 | LH49: 0
A50: 206010972 | B50: MEDICAL HILL HEALTHCARE CENTER | C50: 45292 | D50: 45657 | E50: 366 | F50: In Process | G50: No | H50: Alameda | I50: SNF | J50: Investor Owned | K50: 05 - East Bay | L50: 0417 | M50: 510-832-3222 | N50: 475 29TH STREET | O50: OAKLAND | P50: 94609-0000 | Q50: 1982127338 | R50: ANDREW SNIDER | S50: Yes | U50: 124 | V50: 124 | W50: 100+ | X50: 45384 | Y50: 44169 | Z50: 225.44 | AA50: 211 | AB50: 209 | AC50: 7056 | AD50: 2872 | AE50: 3795 | AF50: 30422 | AH50: 1 | AI50: 23 | AK50: Skilled Nursing Care Only | AL50: 44169 | AU50: 26597743 | AV50: 3743382 | AW50: 1136757 | AX50: 9541 | AY50: 29213909 | AZ50: 24876538 | BA50: 4337371 | BE50: 4337371 | BF50: 8379350 | BG50: 3498313 | BH50: 1627570 | BI50: 13082474 | BK50: 1250 | BL50: 8786 | BN50: 26597743 | BW50: 2532580 | BY50: 1148461 | CA50: 20074 | CC50: 42055 | CG50: 212 | CM50: 0 | CN50: 0 | CO50: 1324000 | CP50: 28211 | CQ50: 995575 | CR50: 484050 | CS50: 654443 | CT50: 196469 | CV50: 60634 | EC50: 2227329 | EE50: 2698148 | EG50: -7147854 | EI50: 3358597 | EM50: 537 | FG50: 10675193 | FH50: 2693816 | FI50: 11507529 | FJ50: 315391 | FK50: 9154208 | FV50: 637868 | FW50: 8499 | FX50: 284877 | FY50: 179833 | FZ50: 255530 | GA50: 81210 | GC50: 171299 | GD50: 731538 | GE50: 611205 | GF50: 154777 | GG50: 1551879 | GH50: 106946 | GI50: 323201 | GJ50: 172824 | GK50: 6210947 | GL50: 83567 | GM50: 3110400 | GN50: 449684 | GO50: 36771 | GQ50: 16901 | GR50: 542574 | GS50: 42831221 | GU50: 818799 | GY50: 43650020 | GZ50: 6505647 | HC50: 37144373 | HD50: 43650020 | HE50: 39572206 | HI50: 0 | HK50: 721545 | HL50: 474131 | HM50: 1195676 | HN50: -376877 | HT50: 0.00 | HU50: 0 | HV50: 2040 | HW50: 0 | HX50: 18768 | HY50: 37026 | HZ50: 128942 | IA50: 0 | IB50: 0 | IC50: 0 | ID50: 6417 | IE50: 5089 | IF50: 23989 | IG50: 5988 | IH50: 31468 | II50: 1983 | IJ50: 12098 | IK50: 2010 | IL50: 8237 | IM50: 284055 | IN50: 0 | IO50: 0 | IP50: 0 | IQ50: 0 | IR50: 0 | IS50: 0 | IT50: 0 | IU50: 499356 | IV50: 0 | IW50: 1081492 | IX50: 1736430 | IY50: 3257652 | IZ50: 0 | JA50: 0 | JB50: 0 | JC50: 416092 | JD50: 112445 | JE50: 432900 | JF50: 106470 | JG50: 665107 | JH50: 78220 | JI50: 230586 | JJ50: 111828 | JK50: 1946615 | JL50: 10675193 | JM50: 0 | JN50: 0 | JO50: 0 | JP50: 0 | JQ50: 0 | JR50: 0 | JS50: 0 | JY50: 6417 | KE50: 416092 | KF50: 171 | KG50: 276 | KH50: 115 | KI50: 118 | KJ50: 200 | KK50: 73 | KL50: 77 | KM50: 125 | KN50: 52 | KO50: 1 | KP50: 0 | KQ50: 0 | KR50: 0 | KS50: 0 | KT50: 1 | KU50: 1 | KV50: 0 | KW50: 0 | KX50: 0 | KY50: 0 | KZ50: 0 | LA50: 0 | LB50: 0 | LC50: 0 | LD50: 1 | LE50: 0 | LF50: 0 | LG50: 0 | LH50: 0
A51: 206010974 | B51: GOOD SAMARITAN HEALTHCARE CENTER - HAYWARD | C51: 45292 | D51: 45657 | E51: 366 | F51: In Process | G51: No | H51: Alameda | I51: SNF | J51: Investor Owned | K51: 05 - East Bay | L51: 0421 | M51: 510-582-8311 | N51: S. SUNSET BLVD | O51: HAYWARD | P51: 94541-3832 | Q51: 1467446278 | R51: RICARDO BAUTISTA | S51: Yes | U51: 99 | V51: 99 | W51: 60-99 | X51: 36234 | Y51: 22618 | Z51: 135.99 | AA51: 151 | AB51: 144 | AC51: 334 | AE51: 2544 | AF51: 17324 | AI51: 300 | AJ51: 2116 | AK51: Skilled Nursing Care Only | AL51: 22618 | AU51: 7646879 | AV51: 626520 | AW51: -35139 | AX51: 90049 | AY51: 8398587 | AZ51: 10117025 | BA51: -1718438 | BE51: -1718438 | BF51: 108655 | BH51: 894034 | BI51: 5690895 | BL51: 165775 | BM51: 787520 | BN51: 7646879 | BW51: 524232 | CA51: 2464 | CC51: 61949 | CI51: 1456 | CK51: 36419 | CM51: 333252 | CN51: 0 | CO51: 122866 | CP51: 0 | CQ51: 128302 | CR51: 32844 | CS51: 5516 | CT51: 3608 | CV51: 132 | DM51: 60287 | EG51: -28286 | EI51: -183782 | EO51: 116642 | FG51: 4912851 | FH51: 591691 | FI51: 4612483 | FK51: 4015893 | FT51: 3233 | FV51: 89887 | FX51: 86263 | FY51: 20251 | FZ51: 31308 | GA51: 4597 | GC51: 5625 | GD51: 454346 | GE51: 384531 | GF51: 97380 | GG51: 909173 | GH51: 73075 | GI51: 203351 | GJ51: 127743 | GK51: 1797468 | GM51: 1188289 | GN51: 128540 | GR51: 496072 | GS51: 1967812 | GX51: 1500000 | GY51: 3467812 | GZ51: 7033045 | HC51: -3565233 | HD51: 3467812 | HG51: 2807899 | HI51: 0 | HM51: 0 | HN51: 0 | HT51: 0.01 | HU51: 70330.45 | HV51: 1925 | HW51: 0 | HX51: 7275 | HY51: 21398 | HZ51: 64615 | IA51: 0 | IB51: 0 | IC51: 1994 | IE51: 2988 | IF51: 16526 | IG51: 4303 | IH51: 30025 | II51: 2036 | IJ51: 10488 | IK51: 2351 | IL51: 19498 | IM51: 185422 | IN51: 0 | IO51: 798 | IP51: 3317 | IQ51: 757 | IR51: 0 | IS51: 0 | IT51: 4872 | IU51: 152737 | IV51: 0 | IW51: 290989 | IX51: 839864 | IY51: 1663839 | IZ51: 0 | JA51: 0 | JB51: 119586 | JD51: 74690 | JE51: 315645 | JF51: 79605 | JG51: 556656 | JH51: 50902 | JI51: 188778 | JJ51: 117574 | JK51: 461986 | JL51: 4912851 | JM51: 0 | JN51: 75821 | JO51: 232203 | JP51: 35599 | JQ51: 0 | JR51: 0 | JS51: 343623 | KF51: 94 | KG51: 116 | KH51: 72 | KI51: 54 | KJ51: 71 | KK51: 37 | KL51: 33 | KM51: 43 | KN51: 24 | KO51: 1 | KP51: 0 | KQ51: 0 | KR51: 0 | KS51: 1 | KT51: 0 | KU51: 1 | KV51: 0 | KW51: 0 | KX51: 0 | KY51: 0 | KZ51: 0 | LA51: 0 | LB51: 0 | LC51: 0 | LD51: 1 | LE51: 0 | LF51: 0 | LG51: 0 | LH51: 0
A52: 206010988 | B52: WASHINGTON CENTER | C52: 45292 | D52: 45657 | E52: 366 | F52: In Process | G52: No | H52: Alameda | I52: SNF | J52: Investor Owned | K52: 05 - East Bay | L52: 0421 | M52: 510-352-2211 | N52: 14766 WASHINGTON AVENUE | O52: SAN LEANDRO | P52: 94578-0 | Q52: ZZRO6121H | R52: REMEDIOS TIBAYAN | S52: Yes | T52: BOLD QUAIL 3 OPERATIONS HOLDINGS, LLC | U52: 99 | V52: 99 | W52: 60-99 | X52: 36234 | Y52: 32805 | Z52: 213.78 | AA52: 221 | AB52: 186 | AC52: 3837 | AE52: 1059 | AF52: 24775 | AG52: 3125 | AI52: 9 | AK52: Skilled Nursing Care Only | AL52: 32805 | AU52: 16279134 | AV52: 1587694 | AW52: 1568732 | AX52: 10917 | AY52: 16309013 | AZ52: 15669987 | BA52: 639026 | BC52: 536 | BE52: 638490 | BF52: 2501170 | BH52: 1289996 | BI52: 9905782 | BJ52: 1254310 | BL52: 8573 | BM52: 1319303 | BN52: 16279134 | BW52: 941269 | CA52: 6966 | CC52: 57491 | CE52: 414616 | CI52: 177 | CK52: 167175 | CM52: 0 | CN52: 0 | CO52: 718312 | CP52: 6071 | CQ52: 356965 | CR52: 220829 | CS52: 244704 | CT52: 24004 | CV52: 16809 | DY52: 41854 | EC52: -1073354 | EG52: 491829 | EI52: 2468782 | EK52: 208011 | EO52: -568390 | FG52: 5985975 | FH52: 1623355 | FI52: 8060657 | FJ52: 409504 | FK52: 5736917 | FV52: 583374 | FW52: 17588 | FX52: 88867 | FY52: 57906 | FZ52: 238385 | GA52: 18414 | GC52: 20235 | GD52: 525647 | GE52: 323821 | GF52: 234309 | GG52: 1155224 | GH52: 535656 | GI52: 152388 | GJ52: 34833 | GK52: 3931107 | GL52: 28178 | GM52: 1580122 | GN52: 133802 | GO52: 37180 | GQ52: 16390 | GR52: 219644 | GS52: 5692417 | GT52: 25567092 | GW52: 167442 | GY52: 31426951 | GZ52: 11742185 | HB52: 19628546 | HC52: 56220 | HD52: 31426951 | HG52: 6462892 | HI52: 0 | HM52: 0 | HN52: 0 | HP52: 19628546 | HR52: 19628546 | HT52: 0.00 | HU52: 0 | HV52: 1945 | HW52: 0 | HX52: 14888 | HY52: 36159 | HZ52: 121535 | IA52: 0 | IB52: 0 | IC52: 2166 | IE52: 2022 | IH52: 1211 | II52: 9887 | IJ52: 5444 | IK52: 678 | IL52: 14428 | IM52: 210363 | IN52: 0 | IO52: 0 | IP52: 0 | IQ52: 0 | IR52: 0 | IS52: 0 | IT52: 0 | IU52: 167683 | IV52: 0 | IW52: 662207 | IX52: 1177554 | IY52: 2246424 | IZ52: 0 | JA52: 0 | JB52: 126915 | JD52: 82783 | JG52: 111907 | JH52: 413049 | JI52: 114905 | JJ52: 29318 | JK52: 853230 | JL52: 5985975 | JM52: 0 | JN52: 0 | JO52: 0 | JP52: 0 | JQ52: 0 | JR52: 0 | JS52: 0 | KF52: 105 | KG52: 137 | KH52: 67 | KI52: 82 | KJ52: 111 | KK52: 50 | KL52: 52 | KM52: 66 | KN52: 37 | KO52: 1 | KP52: 0 | KQ52: 0 | KR52: 0 | KS52: 1 | KT52: 0 | KU52: 1 | KV52: 0 | KW52: 0 | KX52: 0 | KY52: 0 | KZ52: 0 | LA52: 0 | LB52: 0 | LC52: 0 | LD52: 1 | LE52: 0 | LF52: 0 | LG52: 0 | LH52: 0
A53: 206010990 | B53: THE REHABILITATION CENTER OF OAKLAND | C53: 45170 | D53: 45535 | E53: 366 | F53: In Process | G53: No | H53: Alameda | I53: SNF | J53: Investor Owned | K53: 05 - East Bay | L53: 0417 | M53: 510-658-2041 | N53: 210 - 40TH STREET WAY | O53: OAKLAND | P53: 94611 | Q53: 1386966588 | R53: KENT CHAMBERS | S53: Yes | U53: 70 | V53: 70 | W53: 60-99 | X53: 25620 | Y53: 24113 | Z53: 94.12 | AA53: 161 | AB53: 121 | AC53: 3111 | AE53: 2783 | AF53: 16452 | AG53: 945 | AI53: 62 | AJ53: 760 | AK53: Skilled Nursing Care Only | AL53: 24113 | AU53: 11044996 | AV53: 3234417 | AW53: 3631934 | AX53: 500 | AY53: 10647979 | AZ53: 12392144 | BA53: -1744165 | BB53: 570621 | BC53: 12590 | BE53: -1186134 | BF53: 2799900 | BH53: 971023 | BI53: 6145848 | BJ53: 840798 | BL53: 21437 | BM53: 265990 | BN53: 11044996 | BW53: 2038126 | CA53: 111552 | CC53: 556120 | CE53: 507308 | CI53: 15784 | CK53: 5527 | CM53: 18968 | CN53: 55913 | CO53: 1029315 | CP53: 0 | CQ53: 980809 | CR53: 383328 | CS53: 447654 | CT53: 53992 | CV53: 264438 | DY53: 12115 | EC53: 988316 | EG53: 234814 | EI53: 1811639 | EK53: 529373 | EO53: 55677 | FG53: 5314606 | FH53: 1129651 | FI53: 5947887 | FJ53: 206038 | FK53: 5656082 | FT53: 9299 | FU53: 26431 | FV53: 264088 | FX53: 276186 | FY53: 91895 | FZ53: 131984 | GA53: 29280 | GC53: 127267 | GD53: 617818 | GE53: 118391 | GF53: 187923 | GG53: 785515 | GH53: 86171 | GI53: 122089 | GJ53: 46136 | GK53: 2361362 | GL53: 71126 | GM53: 1073380 | GN53: 131450 | GO53: 20664 | GQ53: 801 | GR53: 156806 | GS53: 1741001 | GU53: 174835 | GW53: 333530 | GY53: 2249366 | GZ53: 7699006 | HC53: -5449640 | HD53: 2249366 | HE53: 2005 | HG53: 5731390 | HI53: 0 | HK53: 776117 | HL53: 269080 | HM53: 1045197 | HN53: -870362 | HT53: -0.01 | HU53: -76990.06 | HV53: 1885 | HW53: 0 | HX53: 4703 | HY53: 22498 | HZ53: 49736 | IA53: 54 | IB53: 0 | IC53: 5537 | ID53: 8178 | IE53: 1888 | IF53: 4156 | IG53: 7442 | IH53: 16029 | II53: 1904 | IJ53: 3957 | IK53: 695 | IL53: 13533 | IM53: 142195 | IN53: 0 | IO53: 1346 | IP53: 4019 | IQ53: 21184 | IR53: 0 | IS53: 0 | IT53: 26549 | IU53: 168730 | IV53: 0 | IW53: 279117 | IX53: 1159284 | IY53: 1462096 | IZ53: 1147 | JA53: 0 | JB53: 284868 | JC53: 416343 | JD53: 63981 | JE53: 71949 | JF53: 131430 | JG53: 390353 | JH53: 68375 | JI53: 102711 | JJ53: 33740 | JK53: 680482 | JL53: 5314606 | JM53: 0 | JN53: 108915 | JO53: 261628 | JP53: 773392 | JQ53: 0 | JR53: 0 | JS53: 1143935 | JY53: 8178 | KE53: 416343 | KF53: 122 | KG53: 173 | KH53: 79 | KI53: 68 | KJ53: 95 | KK53: 44 | KL53: 40 | KM53: 50 | KN53: 29 | KO53: 1 | KP53: 0 | KQ53: 0 | KR53: 0 | KS53: 1 | KT53: 0 | KU53: 1 | KV53: 0 | KW53: 0 | KX53: 0 | KY53: 0 | KZ53: 0 | LA53: 0 | LB53: 0 | LC53: 0 | LD53: 1 | LE53: 0 | LF53: 0 | LG53: 0 | LH53: 0
A54: 206010994 | B54: CRESTWOOD MANOR - FREMONT | C54: 45292 | D54: 45657 | E54: 366 | F54: In Process | G54: No | H54: Alameda | I54: SNF | J54: Investor Owned | K54: 05 - East Bay | L54: 0421 | M54: 510-651-1244 | N54: 4303 STEVENSON BLVD | O54: FREMONT | P54: 94538-0000 | Q54: 1902828403 | R54: BUSTICHI, RACHAEL FAY | S54: Yes | T54: CRESTWOOD BEHAVIORAL HEALTH, INC. | U54: 126 | V54: 126 | W54: 100+ | X54: 46116 | Y54: 39795 | Z54: 86.29 | AA54: 45 | AB54: 45 | AE54: 16715 | AF54: 19906 | AJ54: 3174 | AK54: Mixed Care | AL54: 23431 | AN54: 16364 | AU54: 18676930 | AV54: 291939 | AW54: -4922079 | AX54: 31620 | AY54: 23922568 | AZ54: 20476706 | BA54: 3445862 | BB54: 402281 | BE54: 3848143 | BH54: 7850510 | BI54: 9354000 | BM54: 1472420 | BN54: 10991390 | BP54: 7685540 | CA54: 38810 | CC54: 26420 | CK54: 226709 | CM54: 0 | CN54: 0 | CO54: 0 | CP54: 0 | CQ54: 0 | CR54: 0 | CS54: 216271 | CT54: 53834 | CV54: 21834 | EG54: -4954128 | EI54: 255762 | EO54: -223713 | FG54: 10358781 | FH54: 3897951 | FI54: 6219974 | FJ54: 283540 | FK54: 6894219 | FM54: 3339117 | FZ54: 234244 | GA54: 53965 | GC54: 31716 | GD54: 660607 | GE54: 1029857 | GF54: 641710 | GG54: 1567417 | GH54: 353304 | GI54: 595093 | GJ54: 155968 | GK54: 3652967 | GL54: 378859 | GM54: 733480 | GN54: 72117 | GO54: 32357 | GP54: 10733 | GQ54: 29688 | GR54: 9288 | GS54: 4350941 | GU54: 898931 | GY54: 5249872 | GZ54: 2139904 | HB54: 257260 | HC54: 2852708 | HD54: 5249872 | HG54: 379565 | HH54: 284798 | HI54: 0 | HK54: 3529490 | HL54: 854936 | HM54: 4384426 | HN54: -3485495 | HR54: 284798 | HS54: -27538 | HT54: 0 | HU54: 0 | HV54: 3967 | HW54: 0 | HX54: 30147 | HY54: 39632 | HZ54: 94211 | IA54: 0 | IB54: 16212 | IC54: 0 | IE54: 5171 | IF54: 27410 | IG54: 18865 | IH54: 25923 | II54: 6378 | IJ54: 16935 | IK54: 1821 | IL54: 13768 | IM54: 300440 | IN54: 0 | IO54: 0 | IP54: 0 | IQ54: 2000 | IR54: 0 | IS54: 0 | IT54: 2000 | IU54: 317528 | IV54: 0 | IW54: 1516176 | IX54: 1829346 | IY54: 2907497 | IZ54: 0 | JA54: 418191 | JB54: 0 | JD54: 154942 | JE54: 661784 | JF54: 428701 | JG54: 666795 | JH54: 256635 | JI54: 418313 | JJ54: 111966 | JK54: 670907 | JL54: 10358781 | JM54: 0 | JN54: 0 | JO54: 0 | JP54: 165700 | JQ54: 0 | JR54: 0 | JS54: 165700 | KF54: 161 | KG54: 198 | KH54: 131 | KI54: 93 | KJ54: 117 | KK54: 77 | KL54: 44 | KM54: 49 | KN54: 40 | KO54: 1 | KP54: 0 | KQ54: 0 | KR54: 0 | KS54: 0 | KT54: 1 | KU54: 1 | KV54: 0 | KW54: 1 | KX54: 0 | KY54: 0 | KZ54: 0 | LA54: 0 | LB54: 0 | LC54: 0 | LD54: 1 | LE54: 0 | LF54: 0 | LG54: 0 | LH54: 0
A55: 206010995 | B55: PRINCETON MANOR HEALTHCARE CENTER, LLC | C55: 45292 | D55: 45657 | E55: 366 | F55: In Process | G55: No | H55: Alameda | I55: SNF | J55: Investor Owned | K55: 05 - East Bay | L55: 0417 | M55: 510-261-2628 | N55: 2124 57TH AVENUE | O55: OAKLAND | P55: 94621 | Q55: 1891146593 | R55: THERESA WHITE | S55: Yes | U55: 82 | V55: 82 | W55: 60-99 | X55: 30012 | Y55: 28313 | Z55: 221.33 | AA55: 136 | AB55: 101 | AC55: 1253 | AE55: 1235 | AF55: 24580 | AH55: 115 | AJ55: 1130 | AK55: Skilled Nursing Care Only | AL55: 28313 | AU55: 12102551 | AV55: 2063029 | AW55: 3479029 | AY55: 10686551 | AZ55: 11103587 | BA55: -417036 | BB55: 29144 | BC55: 12590 | BE55: -400482 | BF55: 1116717 | BH55: 444048 | BI55: 10037999 | BK55: 103500 | BM55: 400287 | BN55: 12102551 | BW55: 1258789 | CA55: 26911 | CC55: 734743 | CG55: 37905 | CK55: 4681 | CM55: 22755 | CN55: 2840 | CO55: 723095 | CP55: 0 | CQ55: 775862 | CR55: 225786 | CS55: 192070 | CT55: 43795 | CV55: 76826 | EC55: 673848 | EG55: -175113 | EI55: 2886557 | EM55: 20569 | EO55: 73168 | FG55: 5367121 | FH55: 1238451 | FI55: 4498015 | FJ55: 138297 | FK55: 4927245 | FT55: 12369 | FU55: 1420 | FV55: 271433 | FX55: 145589 | FY55: 44517 | FZ55: 45655 | GA55: 8035 | GC55: 45918 | GD55: 510139 | GE55: 290057 | GF55: 141080 | GG55: 828843 | GH55: 77755 | GI55: 129186 | GJ55: 118318 | GK55: 2172222 | GL55: 21551 | GM55: 1016041 | GN55: 103870 | GO55: 40900 | GQ55: 6786 | GR55: 144658 | GS55: 5902523 | GU55: 200309 | GW55: 1582717 | GY55: 7685549 | GZ55: 3790911 | HC55: 3894638 | HD55: 7685549 | HE55: 4480176 | HG55: 6000 | HI55: 0 | HK55: 167715 | HL55: 107238 | HM55: 274953 | HN55: -74644 | HT55: 0.12 | HU55: 454909.32 | HV55: 1184 | HW55: 0 | HX55: 2667 | HY55: 28068 | HZ55: 60362 | IA55: 0 | IB55: 0 | IC55: 3701 | ID55: 5946 | IE55: 1898 | IF55: 11080 | IG55: 5150 | IH55: 20489 | II55: 1852 | IJ55: 4228 | IK55: 1688 | IL55: 12244 | IM55: 160557 | IN55: 0 | IO55: 654 | IP55: 346 | IQ55: 8179 | IR55: 0 | IS55: 0 | IT55: 9179 | IU55: 101384 | IV55: 0 | IW55: 151547 | IX55: 1337926 | IY55: 1626973 | IZ55: 0 | JA55: 0 | JB55: 150043 | JC55: 319006 | JD55: 66427 | JE55: 211135 | JF55: 97761 | JG55: 447639 | JH55: 63711 | JI55: 100618 | JJ55: 97683 | JK55: 595268 | JL55: 5367121 | JM55: 0 | JN55: 81488 | JO55: 17852 | JP55: 279628 | JQ55: 0 | JR55: 0 | JS55: 378968 | JY55: 5946 | KE55: 319006 | KF55: 128 | KG55: 178 | KH55: 89 | KI55: 71 | KJ55: 105 | KK55: 48 | KL55: 42 | KM55: 57 | KN55: 30 | KO55: 1 | KP55: 0 | KQ55: 0 | KR55: 0 | KS55: 1 | KT55: 0 | KU55: 1 | KV55: 0 | KW55: 0 | KX55: 0 | KY55: 0 | KZ55: 0 | LA55: 0 | LB55: 0 | LC55: 0 | LD55: 1 | LE55: 0 | LF55: 0 | LG55: 0 | LH55: 0
A56: 206011527 | B56: CHAPARRAL HOUSE | C56: 45108 | D56: 45473 | E56: 366 | F56: In Process | G56: No | H56: Alameda | I56: SNF | J56: Not-for-Profit | K56: 05 - East Bay | L56: 0415 | M56: 510-848-8774 | N56: 1309 ALLSTON WAY | O56: BERKELEY | P56: 94702 | Q56: 1659366771 | R56: SON LY | S56: No | U56: 49 | V56: 49 | W56: 1-59 | X56: 17934 | Y56: 15870 | Z56: 88.49 | AA56: 71 | AB56: 71 | AC56: 2803 | AE56: 208 | AF56: 5527 | AH56: 1581 | AI56: 5751 | AK56: Skilled Nursing Care Only | AL56: 15870 | AU56: 7966025 | AV56: 1607544 | AW56: -396883 | AX56: 8155 | AY56: 9978607 | AZ56: 9267707 | BA56: 710900 | BB56: 77687 | BE56: 788587 | BF56: 1410620 | BH56: 95520 | BI56: 3212830 | BK56: 240500 | BL56: 3006555 | BN56: 7966025 | BW56: 1227957 | CA56: 64 | CC56: 121279 | CG56: 99173 | CI56: 159071 | CM56: 48926 | CN56: 0 | CO56: 605964 | CP56: 0 | CQ56: 534562 | CR56: 96767 | CS56: 96580 | CT56: 0 | CV56: 224745 | DQ56: -418590 | EC56: -231469 | EG56: 3198 | EI56: 173306 | EM56: 41530 | FC56: 35142 | FG56: 4892583 | FH56: 1840762 | FI56: 2534362 | FJ56: 191118 | FK56: 4340058 | FT56: 1094 | FV56: 234425 | FX56: 217692 | FY56: 33051 | FZ56: 126332 | GA56: 36591 | GC56: 66647 | GD56: 492044 | GE56: 344355 | GF56: 88134 | GG56: 816272 | GH56: 148081 | GI56: 324772 | GJ56: 149652 | GK56: 1706006 | GL56: 116084 | GN56: 4844 | GO56: 9180 | GR56: 12393 | GS56: 4017949 | GU56: 498649 | GV56: 120151 | GY56: 4636749 | GZ56: 401350 | HC56: 4235399 | HD56: 4636749 | HI56: 309641 | HJ56: 2150157 | HL56: 620320 | HM56: 3080118 | HN56: -2581469 | HT56: 5.99 | HU56: 2404086.5 | HV56: 5860 | HW56: 0 | HX56: 8596 | HY56: 14800 | HZ56: 41051 | IA56: 0 | IB56: 0 | IC56: 0 | IE56: 3378 | IF56: 9297 | IG56: 1782 | IH56: 15279 | II56: 2694 | IJ56: 8358 | IK56: 1723 | IL56: 14300 | IM56: 127118 | IN56: 0 | IO56: 0 | IP56: 0 | IQ56: 0 | IR56: 0 | IS56: 0 | IT56: 0 | IU56: 429217 | IV56: 0 | IW56: 514548 | IX56: 782311 | IY56: 1123657 | IZ56: 0 | JA56: 0 | JB56: 0 | JD56: 129750 | JE56: 242041 | JF56: 50287 | JG56: 409566 | JH56: 99814 | JI56: 219173 | JJ56: 110311 | JK56: 781908 | JL56: 4892583 | JM56: 0 | JN56: 0 | JO56: 0 | JP56: 0 | JQ56: 0 | JR56: 0 | JS56: 0 | KF56: 80 | KG56: 120 | KH56: 55 | KI56: 44 | KJ56: 71 | KK56: 30 | KL56: 23 | KM56: 42 | KN56: 14 | KO56: 0 | KP56: 1 | KQ56: 0 | KR56: 1 | KS56: 0 | KT56: 0 | KU56: 1 | KV56: 0 | KW56: 0 | KX56: 0 | KY56: 0 | KZ56: 0 | LA56: 0 | LB56: 0 | LC56: 0 | LD56: 1 | LE56: 0 | LF56: 0 | LG56: 0 | LH56: 0
